Workbook

Sheet App Support
A1: Number | B1: Created | C1: Priority | D1: Status | E1: Channel | F1: Active | G1: Short Description | H1: Description | I1: Assignment Group | J1: Assigned to | K1: Action | L1: Parent | M1: Problem | N1: Caused by Change | O1: Location | P1: Resolution codes | Q1: Resolution notes | R1: Tags | S1: Module | T1: Type Of Issue | U1: Standard Type of Issue | V1: Action taken? | W1: Remarks
A2: INCTEC1613822 | B2: 46113.398 | C2: 4 - Low | D2: Closed | E2: Phone | F2: FALSE | G2: RACPAD | Receipt Reversal Failure | H2: Store number: 05569 Coworker name and ID: Tenika Davis (101141) Customer name and number: Brown Ellen (114943798) Issue description: Coworker is not able to reverse the receipt, getting "Failed to reverse the payment" error. Receipt No: 461702892 Steps taken to arrive at problem: Time of occurrence (Recreate the issue and notate the time if needed): Screen shot required: YES | I2: RACPad Support | J2: Lalit RameshTurkar | K2: RACPAD - Payment | M2: PRB0044395 | O2: 05569 - EMPORIA-MAIN - A - M0386 - R0007 - S08 - RACUSA | P2: Incident-App-DataFixDeployed | Q2: Dear user , As per the request we have reversed the receipt - 461702892 . Please check and confirm if we are good to resolve the incident . | S2: Payment | T2: Payment reversal | U2: =VLOOKUP(T2,'Standard Type of Issue'!$B$1:$C$332,2,0) -> Payment reversal
A3: INCTEC1614096 | B3: 46114.352 | C3: 4 - Low | D3: Closed | E3: Self Service | F3: FALSE | G3: RACPAD - Payment | Customer Refund | | H3: Customer Name: DARLEEN BROOKS Last 4 of Card Used: 6672 Exact Amount of Refund: 137.21 Exact Date of Refund: 04-01-2026 Agreement or Receipt #: 08252467838 Detailed Description of Issue: Took payment for a living room set that is being returned need to refund the money back on to the customers card. | I3: RACPad Support | J3: Sushmitha Sannidhi | K3: RACPAD - Payment | M3: PRB0044395 | O3: 04467 - DUNKIRK-4TH ST - A - M0417 - R0058 - S08 - RACUSA | P3: Incident-App-DataFixDeployed | Q3: Receipt # 461738829 is reversed from backend as per the request. For the reversed receipt, refund request is raised by treasury team for the overpayment collected in the amount of $ 397.72 as requested. Please allow up to 7-10 business days for the customer to receive funds back to the card . Reversed Receipt number: 461738829 Also, please refer the email sent for more details. | S3: Payment | T3: Payment reversal | U3: =VLOOKUP(T3,'Standard Type of Issue'!$B$1:$C$332,2,0) -> Payment reversal
A4: INCTEC1614099 | B4: 46114.359 | C4: 4 - Low | D4: Closed | E4: Self Service | F4: FALSE | G4: RACPAD - Payment | Reverse Payment | | H4: Good Morning, Alphonso Brown was never delivered and merchandise not received, Agreement was taken down in 11/09/24. Clubs have continued to charge through 02/14/2026. Please reverse these payments and refund customer from transactions dating from 10/22/2024-02/14/2026, As he should not have been charged. Please follow up with me As soon as possible if I need to submit a DM check or the refunds can be processed on the back end. Club Memeber ship ID# 100014595910 Agreement Number: 8170619055 Customer ID: 110840503 Customer Name: Alphonso Brown Date and Time Issue Was Occured: 2024-10-22 00:00:00 | I4: RACPad Support | J4: racha sahithya | K4: RACPAD - Payment | M4: PRB0044395 | O4: 05532 - LEESBURG-NORTH BLVD - A - M0132 - R0024 - S08 - RACUSA | P4: Request-Fulfilled | Q4: We have received a response from Business that we shouldn't reverse the 34 receipts mentioned. An agreement is not required to continue the RAC Benefits Plus membership. It is the customer's decision to stay a member or cancel their membership. If the District Manager reviews the account and a refund is determined to be owed. they should submit a check request for the amount of refund owed to the customer and send it to Accounts Payable. Store agreed to close the ticket. | S4: Payment | T4: Payment reversal | U4: =VLOOKUP(T4,'Standard Type of Issue'!$B$1:$C$332,2,0) -> Payment reversal
A5: INCTEC1614128 | B5: 46114.412 | C5: 4 - Low | D5: Closed | E5: Self Service | F5: FALSE | G5: RACPAD - Agreement | Loaner Agreement | | H5: cannot return loaner agreement Agreement Number: 8172324712 Customer ID: 906313 Customer Name: Christina McAlister Date and Time Issue Was Occured: 2026-04-02 09:53:20 Its a loaner agreement. While trying to return the agreement, its asking user to reverse the payment to void the agreement. There is no payment needed in loaner agreement as per CW | I5: RACPad Support | J5: Abhishek TV | K5: RACPAD - Agreement | M5: PRB0044395 | O5: 04059 - SPRINGFIELD-N. KANSAS - A - M0214 - R0080 - S08 - RACUSA | P5: Incident-App-DataFixDeployed | Q5: Steps taken for resolution: The agreement #8172324712 is updated to 'Void' and also updated the item #9999220877135 status to 'rent ready'. The end_date of the agreement inventory for the Agreement is also updated. Screenshots are attached for reference. Category: Agreement Void | S5: Payment | T5: Payment reversal | U5: =VLOOKUP(T5,'Standard Type of Issue'!$B$1:$C$332,2,0) -> Payment reversal
A6: INCTEC1614271 | B6: 46114.557 | C6: 4 - Low | D6: Closed | E6: Self Service | F6: FALSE | G6: RACPAD | Unable to Void Agreement | H6: eCommerce -Other - need this order cancelled please - Pending 8175023424 Richmond 72" Unfold Assembly - unable to void on my end. | I6: RACPad Support | J6: Pratik Singar | K6: RACPAD - Payment | M6: PRB0044395 | O6: 02982 - YELM AVENUE - A - M0329 - R0050 - S07 - RACUSA | P6: Incident-App-DataFixDeployed | Q6: Receipt 459773707 has been reversed and agreement 8175023424 voided. Received confirmation from store. Please refer attachment. | S6: Payment | T6: Payment reversal | U6: =VLOOKUP(T6,'Standard Type of Issue'!$B$1:$C$332,2,0) -> Payment reversal
A7: INCTEC1614337 | B7: 46114.628 | C7: 4 - Low | D7: Closed | E7: Self Service | F7: FALSE | G7: RACPAD - Payment | Customer Refund | | H7: Customer Name: TYLER ENGLEHART Customer ID : 5402772 Last 4 of Card Used: 2301 Exact Amount of Refund: $41.70 For 1 Amount is the Charge: $13.90 Exact Date of Refund: 02/03/2026, 03/11/2026, 04/01/2026 Agreement or Receipt #: 456336592, 459791400, 461716629 Detailed Description of Issue: Customer was being charged for BP after returning item and requests a refund for the last 3 payments on BP | I7: RACPad Support | J7: Rashmitha Shetty | K7: RACPAD - Payment | M7: PRB0044395 | O7: 03596 - HARTFORD CITY-JEFFERSON - A - M0177 - R0019 - S08 - RACUSA | P7: Incident-App-DataFixDeployed | Q7: As per the request we have reversed below receipts: Receipt: 456336592, 459791400, 461716629 Customer Name: TYLER ENGLEHART Customer ID: 5402772 Amount: $41.70(13.90 for each receipt) And treasury team has initiated the refund. We have informed store to allow up to 7-10 business days for the customer to receive funds back to the card used. category: Receipt Reversal. | R7: SR | S7: Payment | T7: Payment reversal | U7: =VLOOKUP(T7,'Standard Type of Issue'!$B$1:$C$332,2,0) -> Payment reversal
A8: INCTEC1614554 | B8: 46115.458 | C8: 4 - Low | D8: Resolved | E8: Phone | F8: TRUE | G8: RACPAD - Web order items not delivered but payments processed – unable to void agreement | H8: Store number: 02234 Coworker name and ID: Renee Rhoden (116316) Customer name and number: Janice Tubb (108233818) Issue description: Coworker called in reporting that a customer never received items from a web order, however payments continued to process successfully. Agreement # 8174655973 Item # 9999221979487 itme # 9999221448131 Screen shot required: YES | I8: RACPad Support | J8: racha sahithya | K8: RACPAD - Agreement | M8: PRB0044395 | O8: 02234 - HOU-34TH ST - A - M0051 - R0079 - S07 - RACUSA | P8: Incident-App-DataFixDeployed | Q8: Agreement #8174655973 has been voided from backend. | S8: Payment | T8: Payment reversal | U8: =VLOOKUP(T8,'Standard Type of Issue'!$B$1:$C$332,2,0) -> Payment reversal
A9: INCTEC1614580 | B9: 46115.484 | C9: 4 - Low | D9: Closed | E9: Self Service | F9: FALSE | G9: RACPAD - Payment | Unable to reverse the payment | | H9: trying to do a payment refund and Its not going to allow me to do it Agreement Number: 8174954887 Customer ID: 4596264 Hostname - 04474-HMLWV93 Customer Name: Brian Taft Date and Time Issue Was Occured: 2026-04-03 12:16:20 | I9: RACPad Support | J9: Rashmitha Shetty | K9: RACPAD - Payment | M9: PRB0044395 | O9: 04474 - BATH-WASHINGTON - A - M0476 - R0058 - S08 - RACUSA | P9: Incident-App-DataFixDeployed | Q9: As per the request, we have reversed below receipt: Receipt: 461895225 Customer Name: Brian Taft Customer ID : 4596264 Payment-method: Credit Payment Amount: $ 91.17 And Treasury team has initiated the refund for the same. Informed store to allow up to 7-10 business days for the customer to receive funds back to the card used. As request is completed resolving the incident category: Receipt reversal | R9: SR | S9: Payment | T9: Payment reversal | U9: =VLOOKUP(T9,'Standard Type of Issue'!$B$1:$C$332,2,0) -> Payment reversal
A10: INCTEC1614988 | B10: 46116.657 | C10: 4 - Low | D10: Closed | E10: Self Service | F10: FALSE | G10: RACPAD - Agreement | Agreement Void | | H10: customer never got item changed mind, we are unable to get account to void Agreement Number: 8174993651 Customer ID: 111788474 Customer Name: Amy Walkos Date and Time Issue Was Occured: 2026-04-04 15:35:52 | I10: RACPad Support | J10: Rashmitha Shetty | K10: RACPAD - Agreement | M10: PRB0044395 | O10: 02406 - MORGANTOWN - A - M0337 - R0058 - S08 - RACUSA | P10: Incident-App-DataFixDeployed | Q10: As per the request we have voided the Agreement Number: 8174993651 and updated associated item #"9999221909790" to rent ready. Received Store confirmation also, thus resolving the incident. category: Void Agreement | R10: SR | S10: Payment | T10: Payment reversal | U10: =VLOOKUP(T10,'Standard Type of Issue'!$B$1:$C$332,2,0) -> Payment reversal
A11: INCTEC1615503 | B11: 46118.597 | C11: 4 - Low | D11: Closed | E11: Self Service | F11: FALSE | G11: RACPAD - Payment | Customer Refund | | H11: Customer Name: Adam Drell Last 4 of Card Used: 0569 Exact Amount of Refund: 116.64 Exact Date of Refund: 04.01.26 Agreement or Receipt #: 8175216558 Detailed Description of Issue: Customer processed payment for special order & then another agreement was processed for in stock item & another payment was made. The customer no longer wants the special order item so we need to cancel & refund the amount he paid for on the special order. It will not allow us to refund that particular agreement only the last payment that was made. | I11: RACPad Support | J11: Pratik Singar | K11: RACPAD - Payment | M11: PRB0044395 | O11: 01871 - LAS VEGAS-TROPICANA - A - M0257 - R0050 - S07 - RACUSA | P11: Request-Fulfilled | Q11: After 3 strike not receied any updated from store, Hence resolving incident. | S11: Payment | T11: Payment reversal | U11: =VLOOKUP(T11,'Standard Type of Issue'!$B$1:$C$332,2,0) -> Payment reversal
A12: INCTEC1617278 | B12: 46123.61 | C12: 4 - Low | D12: Closed | E12: Self Service | F12: FALSE | G12: Racpad | H12: need help voiding a customer Customer Name : HARVEY JEFFERSON Customer ID : 110101914 Cust Name & ID : BERNI CEDENO - 740626 | I12: RACPad Support | J12: Lalit RameshTurkar | K12: RACPAD - Agreement | M12: PRB0044395 | O12: 03990 - LANTANA-LANTANA RD - A - M0155 - R0024 - S08 - RACUSA | P12: Incident-App-DataFixDeployed | Q12: Hi store , As per the store's request we have voided the agreement 8169481079- Harvey Jefferson 8170726072- Berni Cedeno .Please find the attached screenshot below for reference. As the receipt -390947881 is aged you can submit the check request for customer refund .Attached the process doc for check request. | S12: Payment | T12: Payment reversal | U12: =VLOOKUP(T12,'Standard Type of Issue'!$B$1:$C$332,2,0) -> Payment reversal
A13: INCTEC1622484 | B13: 46139.42 | C13: 4 - Low | D13: Resolved | E13: Self Service | F13: TRUE | G13: RACPAD - Payment | Customer Refund | | H13: Customer Name: Jajuan Carson Last 4 of Card Used: 7166 Exact Amount of Refund: $ 137.13 Exact Date of Refund: 04/16/2026 Agreement or Receipt #: 463186291 Detailed Description of Issue: Customer requesting refund for order that was cancelled before delivery. Racpad will not allow me to issue refund to customer | I13: RACPad Support | J13: Aditi Nayak | K13: RACPAD - Payment | M13: PRB0044395 | O13: 00346 - HAMPTON-MERCURY - A - M0007 - R0007 - S08 - RACUSA | P13: Incident-App-DataFixDeployed | Q13: Resolution steps: Reversed receipt 463186291, and the Treasury team has initiated a refund. Category: Receipt reversal | S13: Payment | T13: Payment reversal | U13: =VLOOKUP(T13,'Standard Type of Issue'!$B$1:$C$332,2,0) -> Payment reversal
A14: INCTEC1615973 | B14: 46119.681 | C14: 4 - Low | D14: Closed | E14: Self Service | F14: FALSE | G14: RACPAD - Payment | Customer Refund | | H14: Customer Name: Mohan Gupta Last 4 of Card Used: 7411 Exact Amount of Refund: 298.96 Exact Date of Refund: 4/7 Agreement or Receipt #: 462035391 Detailed Description of Issue: Customer need refund account dropped before payment ran | I14: RACPad Support | J14: Abhishek TV | K14: RACPAD - Payment | M14: PRB0044395 | O14: 00827 - BEAUFORT - A - M0001 - R0007 - S08 - RACUSA | P14: Incident-App-DataFixDeployed | Q14: Steps taken for resolution: Receipt #462035391 reversed and revenue recog also done. Treasury has requested a refund for the overpayment collected in the amount of $298.96 as requested: Please allow up to 7-10 business days for the customer to receive funds back to the card used. Category: Customer refund - receipt reversal | S14: Payment | T14: Payment reversal | U14: =VLOOKUP(T14,'Standard Type of Issue'!$B$1:$C$332,2,0) -> Payment reversal
A15: INCTEC1623367 | B15: 46141.475 | C15: 4 - Low | D15: Awaiting Change | E15: Self Service | F15: TRUE | G15: RACPAD - Payment | Customer Refund | | H15: Customer Name: Ted Lafortune Last 4 of Card Used: 1756 Exact Amount of Refund: $88.27 Exact Date of Refund: 4/28/26 Agreement or Receipt #: 464275887 Detailed Description of Issue: customer returned, same day ecomm pulled, need payment reversed! | I15: RACPad Support | J15: Lalit RameshTurkar | K15: RACPAD - Payment | M15: PRB0044395 | O15: 04678 - CLARKSVILLE-PROVIDENCE - A - M0488 - R0070 - S08 - RACUSA | S15: Payment | T15: Payment reversal | U15: =VLOOKUP(T15,'Standard Type of Issue'!$B$1:$C$332,2,0) -> Payment reversal
A16: INCTEC1616522 | B16: 46121.422 | C16: 4 - Low | D16: Closed | E16: Self Service | F16: FALSE | G16: RACPAD - Payment | Customer Refund | | H16: I am trying to give a customer back his refund because he canceled his agreement he processed online and will not allow me to do but the payment for his benefits plus not his other payment he processed. He paid $154.71 plus the monthly payment for benefits plus. Agreement Number: 8175248456 Customer ID: 3276828 Customer Name: Frank Fondi Date and Time Issue Was Occured: 2026-04-09 00:00:00 | I16: RACPad Support | J16: Rashmitha Shetty | K16: RACPAD - Payment | M16: PRB0044395 | O16: 04753 - MARTINSVILLE - A - M0033 - R0007 - S08 - RACUSA | P16: Incident-App-DataFixDeployed | Q16: Incident INCTEC1616522 closed based on closure of change CHG0051338 | R16: SR | S16: Payment | T16: Payment reversal | U16: =VLOOKUP(T16,'Standard Type of Issue'!$B$1:$C$332,2,0) -> Payment reversal
A17: INCTEC1616553 | B17: 46121.459 | C17: 4 - Low | D17: Closed | E17: Phone | F17: FALSE | G17: RACPAD Customer refund issue | H17: Co-worker name: Erik Sadlowski Employee ID: 369514 Store: 00892 Customer name: Terrence Lakin Customer ID: 109571545 Agreement #: 8173477983 Receipt #: 462597851 Amount #: $152.70 Need to refund on this Card: Card ending with 9421 Issue: CW called and mentioned need to refund this Amount #: $152.70 to the customer. Because customer is using 2account and CW charged from the wrong account. So, need to refund back to the customer. But CW is unable to refund back to the customer. Need help with this refund. | I17: RACPad Support | J17: Aditi Nayak | K17: RACPAD - Payment | M17: PRB0044395 | O17: 00892 - FARGO - A - M0529 - R0040 - S07 - RACUSA | P17: Incident-App-DataFixDeployed | Q17: Resolution Steps: Reversed receipt 462507851 for customer Terrence Lakin. Treasury Team has initiated refund of $261.12. | S17: Payment | T17: Payment reversal | U17: =VLOOKUP(T17,'Standard Type of Issue'!$B$1:$C$332,2,0) -> Payment reversal
A18: INCTEC1623469 | B18: 46141.636 | C18: 4 - Low | D18: Acknowledged | E18: Self Service | F18: TRUE | G18: RACPAD - Account Management | Past Due List | | H18: dryers on account wont allow us to drop them off the account Customer ID: 7261744 Customer Name: Danny Collins Date and Time Issue Was Occured: 2026-03-24 15:15:45 | I18: RACPad Support | J18: Prasanth K | K18: RACPAD - Account Management | M18: PRB0044395 | O18: 00381 - COLUMBUS-NORTH - A - M0482 - R0008 - S07 - RACUSA | S18: Payment | T18: Payment reversal | U18: =VLOOKUP(T18,'Standard Type of Issue'!$B$1:$C$332,2,0) -> Payment reversal
A19: INCTEC1616947 | B19: 46122.555 | C19: 4 - Low | D19: Closed | E19: Phone | F19: FALSE | G19: RACFI-Racpad || Reverse Payment | H19: issue : Need to Reverse Payment Customer Name : FILIBERTO LOPEZ Customer ID : 111539786 Amounts need to refund: $759.49 Receipt ID: 459642370 4 Last dight number of CC : 2394 | I19: RACPad Support | J19: Aditi Nayak | K19: RACPAD - Payment | M19: PRB0044395 | O19: 00747 - VISALIA-MOONEY BLVD - A - M0331 - R0999 - S098 - RACFI | P19: Incident-App-DataFixDeployed | Q19: As per the request, we have reversed the following receipt: 459642370 Since this is a Franchise Store, the Treasury team is unable to issue a refund for a payment processed at a franchise location. They do not have access to the chain code under which the transaction was completed. Therefore, informed store to reach out to the Franchise Back Office to issue the refund to the customer | R19: SR | S19: Payment | T19: Payment reversal | U19: =VLOOKUP(T19,'Standard Type of Issue'!$B$1:$C$332,2,0) -> Payment reversal
A20: INCTEC1616953 | B20: 46122.561 | C20: 4 - Low | D20: Closed | E20: Self Service | F20: FALSE | G20: RACPAD - Agreement | Agreement Void | | H20: It is not letting us void a special order from 12/30/23 because it wants us to reverse payment. We cannot reverse payment because we have taken several payments that are to other agreements. We need this agreement void to be able to transfer customer to new store. This store 02174 is closing and it is urgent that we get this done quickly. Agreement Number: 08253475278 Customer ID: 109535772 Customer Name: Wilber I Caxaj Ajanel Date and Time Issue Was Occured: 2026-04-10 13:24:52 | I20: RACPad Support | J20: Vandana K | K20: RACPAD - Agreement | M20: PRB0044395 | O20: 02174 - AUSTIN - RESEARCH - I - M0066 - R0079 - S07 - RACUSA | P20: Incident-App-DataFixDeployed | Q20: Steps taken: As requested, we have voided the agreement 08253475278. Send the confirmation mail and follow-up mail to the store Tried reaching the store via store call,not able to connect Category: Agreement Hence proceeding with closing the ticket expecting that the request is fulfilled,if not please raise a new ticket | S20: Payment | T20: Payment reversal | U20: =VLOOKUP(T20,'Standard Type of Issue'!$B$1:$C$332,2,0) -> Payment reversal
A21: INCTEC1623767 | B21: 46142.544 | C21: 4 - Low | D21: Resolved | E21: Self Service | F21: TRUE | G21: RACPAD - Payment | Customer Refund | | H21: Customer was a level 3 during process of taking payment. Her level changed to a level 5 after payment was taken for the electronic. Level 5 customers are not allowed electronics on rent. I went to process a refund and got the error below . Agreement Number: 8175457661 Customer ID: 8175457661 Customer Name: ADRIANNA BEST Date and Time Issue Was Occured: 2026-04-30 12:59:09 | I21: RACPad Support | J21: Ashwini Shetty | K21: RACPAD - Payment | M21: PRB0044395 | O21: 00391 - WARNER ROBBINS - A - M0482 - R0008 - S07 - RACUSA | P21: Incident-App-TechnicalWorkaround | Q21: Called store to inform that the amount $2.00 is partially reversed to customer account. once a receipt has been partially reversed, the remaining amount cannot be reversed from the backend. For the remaining amount, the store must submit a Check Request through Accounts Payable Also sent email for check request steps. CW agreed Hence proceeding to close the ticket | S21: Payment | T21: Payment reversal | U21: =VLOOKUP(T21,'Standard Type of Issue'!$B$1:$C$332,2,0) -> Payment reversal
A22: INCTEC1617021 | B22: 46122.666 | C22: 4 - Low | D22: Closed | E22: Self Service | F22: FALSE | G22: RACPAD - Payment | Customer Refund | | H22: Customer Name: Daisy Leach Last 4 of Card Used: 5987 Exact Amount of Refund: 52.82 Exact Date of Refund: 4/10/2026 Agreement or Receipt #: 461680155 Detailed Description of Issue: Ordered a fridge and when we got there hotel owner said we were not allowed to deliver said fridge. therefor i want to refund her down payment | I22: RACPad Support | J22: Pratik Singar | K22: RACPAD - Payment | M22: PRB0044395 | O22: 03540 - GREENFIELD-STATE - A - M0177 - R0019 - S08 - RACUSA | P22: Incident-App-DataFixDeployed | Q22: As per request We have reversed the receipt 461680155. Received treasury mail as well. Please refer attachment. | S22: Payment | T22: Payment reversal | U22: =VLOOKUP(T22,'Standard Type of Issue'!$B$1:$C$332,2,0) -> Payment reversal
A23: INCTEC1617058 | B23: 46122.718 | C23: 4 - Low | D23: Closed | E23: Self Service | F23: FALSE | G23: RACPAD - Payment | Customer Refund | | H23: Customer Name: KEVIN BOLTON Last 4 of Card Used: 7016 Exact Amount of Refund: $127.50 Exact Date of Refund: 04/10/2026 Agreement or Receipt #: 462444692 Detailed Description of Issue: On April 8th we started the agreement the customer did a down payment of $127.50. We went and tried to deliver the washer and dryer but it did not fit in the spot that had so they decided they did not want it. We tried to reverse the payment and it showed reversed but it was for $0 but it did change the due date and took it back to April 8th. We tried to reserve it again and the amount for just BP showed up for $14.14 and that reversed like normal. I thought that maybe now if I tried to reserve it again it would have the remaining amount but it says No Eligible Payment Found For This Customer To Reverse. So I am not sure what amount got reversed back to him it should have been the full amount of $127.50 if only the BP did we would still owe him $113.36. Are you able to see if anything reversed back to him? | I23: RACPad Support | J23: Rashmitha Shetty | K23: RACPAD - Payment | M23: PRB0044395 | O23: 01710 - CRYSTAL CITY - A - M0538 - R0039 - S07 - RACUSA | P23: Request-Fulfilled | Q23: The given receipt already reversed we cannot reverse it again from backend and the agreement is already returned to store. so, reached out to store multiple times to get the details on what is the current issue here, but haven't received any response. Thus, resolving the incident. | R23: SR | S23: Payment | T23: Payment reversal | U23: =VLOOKUP(T23,'Standard Type of Issue'!$B$1:$C$332,2,0) -> Payment reversal
A24: INCTEC1623871 | B24: 46142.738 | C24: 4 - Low | D24: Awaiting Confirmation | E24: Self Service | F24: TRUE | G24: RACPAD - Payment | Reverse Payment | | H24: Customer Name: KATREIONA STARKS Customer ID: 111261501 Agreement Number: 8175461284 Date of payment :04/14/2026 Mode of payment : Credit card Last 4 digit :3940 Description: CW is unable to refund the payment $79.91 because it is not a recent transaction need help for same | I24: RACPad Support | J24: Sushmitha Sannidhi | K24: RACPAD - Payment | M24: PRB0044395 | O24: 03742 - EASTEX-LITTLE YORK - A - M0555 - R0079 - S07 - RACUSA | S24: Payment | T24: Payment reversal | U24: =VLOOKUP(T24,'Standard Type of Issue'!$B$1:$C$332,2,0) -> Payment reversal
A25: INCTEC1617222 | B25: 46123.474 | C25: 4 - Low | D25: Closed | E25: Phone | F25: FALSE | G25: Racpad Customer -unable to transfer a customer Store is getting closed | H25: Customer Name: Margarita Ayala Customer ID:6414444 Agreement Number:8172369180/100016533169 Description :unable to transfer a customer Store is getting closed need help with same | I25: RACPad Support | J25: Tejas Acharya | K25: RACPAD - Agreement | M25: PRB0044395 | O25: 02516 - DORCHESTER-COLUMBIA RD - I - M0028 - R0002 - S07 - RACUSA | P25: Incident-App-DataFixDeployed | Q25: Steps taken for resolution: Agreement #07987172389 has been voided as requested. Category: racpad agreement | R25: SR | S25: Payment | T25: Payment reversal | U25: =VLOOKUP(T25,'Standard Type of Issue'!$B$1:$C$332,2,0) -> Payment reversal
A26: INCTEC1617238 | B26: 46123.502 | C26: 4 - Low | D26: Closed | E26: Self Service | F26: FALSE | G26: RACPAD - Payment | Customer Refund | | H26: Customer Name: Tristan Hayden Last 4 of Card Used: 1936 Exact Amount of Refund: $57.87 Exact Date of Refund: 04/11/2026 Agreement or Receipt #: 462749033 Detailed Description of Issue: Customer returned the merchandise prior to due date without the controller. Agreement wasn't taken down immediately upon waiting for the controller. Controller has been returned. Customer requests refund on last payment. | I26: RACPad Support | J26: Aditi Nayak | K26: RACPAD - Payment | M26: PRB0044395 | O26: 03596 - HARTFORD CITY-JEFFERSON - A - M0177 - R0019 - S08 - RACUSA | P26: Incident-App-DataFixDeployed | Q26: Resolution steps: As per the request, we have reversed receipt: 462749033 and the Treasury team has initiated the refund. Category: Receipt reversal | S26: Payment | T26: Payment reversal | U26: =VLOOKUP(T26,'Standard Type of Issue'!$B$1:$C$332,2,0) -> Payment reversal
A27: INCTEC1617765 | B27: 46125.644 | C27: 4 - Low | D27: Closed | E27: Self Service | F27: FALSE | G27: RACPAD - Agreement | Agreement Return | | H27: We cannot void the rental agreement. We are unable to "reopen" the scheduled delivery that was cancelled, therefore it will not allow me to void the agreement. PLEASE DO NOT REFUND THE MOST RECENT RECEIPTS. Agreement Number: 8175006926 Customer ID: 954200 Customer Name: VERONICA D TREJO-GALINO Date and Time Issue Was Occured: 2026-03-30 15:22:18 | I27: RACPad Support | J27: roopesh pothodi | K27: RACPAD - Agreement | M27: PRB0044395 | O27: M0120 - - M0120 - R0020 - S08 - RTO | P27: Incident-App-DataFixDeployed | Q27: Steps taken for resolution: The agreement and inventory tables have been updated to ensure the inventory and agreement statuses are correctly reflected. Category: Void Agreement | S27: Payment | T27: Payment reversal | U27: =VLOOKUP(T27,'Standard Type of Issue'!$B$1:$C$332,2,0) -> Payment reversal
A28: INCTEC1618156 | B28: 46126.611 | C28: 4 - Low | D28: Closed | E28: Self Service | F28: FALSE | G28: RACPAD - Payment | Customer Refund | | H28: Customer Name: MIRIAM KAHAN Last 4 of Card Used: 6004 Exact Amount of Refund: $124.87 Exact Date of Refund: 04/14/26 Agreement or Receipt #: 462310292 Detailed Description of Issue: We picked up the recliner on the same day the autopay pulled. We need to refund the customer please. | I28: RACPad Support | J28: Aditi Nayak | K28: RACPAD - Payment | M28: PRB0044395 | O28: 05046 - - A - M0007 - R0007 - S08 - RACUSA | P28: Request-Fulfilled | Q28: Informed Richard that DM can submit the RACinet form his behalf. If the DM is also unable to submit the form due to access issues, please reach out to AccountsPayable@rentacenter.com for further assistance. | S28: Payment | T28: Payment reversal | U28: =VLOOKUP(T28,'Standard Type of Issue'!$B$1:$C$332,2,0) -> Payment reversal
A29: INCTEC1618176 | B29: 46126.635 | C29: 4 - Low | D29: Closed | E29: Self Service | F29: FALSE | G29: RACPAD - Payment | Customer Refund | | H29: Customer Name: Ramona Smith Last 4 of Card Used: 1187 Exact Amount of Refund: 88.30 Exact Date of Refund: 03/04/2026 Agreement or Receipt #: A#8174968449 Detailed Description of Issue: Refund owed customer as the agreement was canceled (not delivered), and refund was not run before being agreement was closed. | I29: RACPad Support | J29: Rashmitha Shetty | K29: RACPAD - Payment | M29: PRB0044395 | O29: 02447 - CHESAPEAKE - A - M0007 - R0007 - S08 - RACUSA | P29: Incident-App-DataFixDeployed | Q29: As requested we have reversed the receipt and voided the agreement and treasury team has initiated the refund for the same. And informed store to allow up to 7-10 business days for the customer to receive funds back to the card used. Resolving the incident as request is completed. Category: Receipt Reversal and Void agreement | R29: SR | S29: Payment | T29: Payment reversal | U29: =VLOOKUP(T29,'Standard Type of Issue'!$B$1:$C$332,2,0) -> Payment reversal
A30: INCTEC1618214 | B30: 46126.686 | C30: 4 - Low | D30: Closed | E30: Email | F30: FALSE | G30: Transfer Issue 4705-RACPAD | H30: Thanks, Siva Bhargavi RACPad Production Support +1 6605413327 [cid:image001.jpg@01DBA816.356267B0] _____________________________________________ From: Melody Cassel <melody.cassel@upbound.com> Sent: Tuesday, April 14, 2026 4:07 PM To: RACPad Support <RACPadSupport@rentacenter.com> Cc: Joshua Castor <Josh.Castor@rentacenter.com>; Seema Rani <Seema.Rani@Rentacenter.com> Subject: Transfer Issue 4705 Importance: High Hello Team, Can we please investigate two problems. 1st Store 04705 is unable to void agreement 07950910418 as it is requesting a payment reversal that has already been completed. See screenshots below. 2nd issue store 4705 is trying to transfer agreements 8174517850 and 8169769123 to store 3770 but the transfer button is disabled. My assumption is because the agreement above is pending, if this is the case can you please void 07950910418 so the store can proceed with the transfer. Melody Cassel Director of Product Management Melody.Cassel@Upbound.com<mailto:Melody.Cassel@Upbound.com> Upbound Group, Inc. / 5501 Headquarters Dr., Plano, TX 75024 / Ticker: UPBD | I30: RACPad Support | J30: Rashmitha Shetty | K30: RACPAD - Agreement | M30: PRB0044395 | O30: H0003 - - Active - FSC | P30: Incident-App-DataFixDeployed | Q30: As per the request We have voided the agreement#07950910418. Resolving the incident as request is completed. Category: Void Agreement | R30: SR | S30: Payment | T30: Payment reversal | U30: =VLOOKUP(T30,'Standard Type of Issue'!$B$1:$C$332,2,0) -> Payment reversal
A31: INCTEC1618409 | B31: 46127.361 | C31: 4 - Low | D31: Closed | E31: Other | F31: FALSE | G31: Test agreement cancellation | H31: Following test agreement was created in prod as part of predeployment validation. Requesting to cancel this agreement and refund the related payments. Need to be routed to RACPAD support team. First name : testsfcc Last Name: Verifycodefive Agreement # - 8175318830 | I31: RACPad Support | J31: Rashmitha Shetty | K31: RACPAD - Agreement | M31: PRB0044395 | O31: H0003 - - Active - FSC | P31: Incident-App-DataFixDeployed | Q31: Incident INCTEC1618409 closed based on closure of change CHG0051445 | R31: SR | S31: Payment | T31: Payment reversal | U31: =VLOOKUP(T31,'Standard Type of Issue'!$B$1:$C$332,2,0) -> Payment reversal
A32: INCTEC1618736 | B32: 46128.382 | C32: 4 - Low | D32: Closed | E32: Email | F32: FALSE | G32: Special Order PO -Racpad | H32: From: Melissa Swarbrick <Melissa.Swarbrick@racfranchising.com> Sent: Thursday, April 16, 2026 7:35 PM To: RACPad Support <RACPadSupport@rentacenter.com> Cc: Melissa Berry <Melissa.Berry@rentacenter.com> Subject: FW: Special Order PO Hi, can you help the store with this issue? Thank you From: Carlos Rodriguez <Carlos.Rodriguez@rentacenter.com<mailto:Carlos.Rodriguez@rentacenter.com>> Sent: Wednesday, April 15, 2026 10:45 PM To: Melissa Swarbrick <Melissa.Swarbrick@racfranchising.com<mailto:Melissa.Swarbrick@racfranchising.com>>; Melissa Berry <Melissa.Berry@rentacenter.com<mailto:Melissa.Berry@rentacenter.com>> Subject: RE: Special Order PO Melissa, Open a ticket with RACPad Support and send me the ticket number so I can escalate. Thank you, Carlos Rodriguez From: Melissa Swarbrick <Melissa.Swarbrick@racfranchising.com<mailto:Melissa.Swarbrick@racfranchising.com>> Sent: Tuesday, April 14, 2026 2:48 PM To: Melissa Berry <Melissa.Berry@rentacenter.com<mailto:Melissa.Berry@rentacenter.com>> Cc: Carlos Rodriguez <Carlos.Rodriguez@rentacenter.com<mailto:Carlos.Rodriguez@rentacenter.com>> Subject: RE: Special Order PO Hi Carlos, is this something you can help with? From: Melissa Berry <Melissa.Berry@rentacenter.com<mailto:Melissa.Berry@rentacenter.com>> Sent: Tuesday, April 14, 2026 2:42 PM To: Melissa Swarbrick <Melissa.Swarbrick@racfranchising.com<mailto:Melissa.Swarbrick@racfranchising.com>> Subject: Re: Special Order PO That's because all the PO's were canceled already however because the PO is not attached. I can't void the special order to then transfer his other account so I'm not really sure what to do. Get Outlook for iOS<https://aka.ms/o0ukef> ________________________________ From: Melissa Swarbrick <Melissa.Swarbrick@racfranchising.com<mailto:Melissa.Swarbrick@racfranchising.com>> Sent: Tuesday, April 14, 2026 2:34:38 PM To: Melissa Berry <Melissa.Berry@rentacenter.com<mailto:Melissa.Berry@rentacenter.com>> Subject: RE: Special Order PO Hi, I looked up this model and can't find a PO to reinstate for your store? Thanks From: Melissa Berry <Melissa.Berry@rentacenter.com<mailto:Melissa.Berry@rentacenter.com>> Sent: Tuesday, April 14, 2026 12:17 PM To: Melissa Swarbrick <Melissa.Swarbrick@racfranchising.com<mailto:Melissa.Swarbrick@racfranchising.com>> Subject: Re: Special Order PO SO yes, we need to reinstate the PO # so we can take off the customer account, then cancel the PO and transfer the account to another store. I don't have the P.O #; however, I do have RMS-200038135. Will this work? Thanks, Melissa ________________________________ From: Melissa Swarbrick <Melissa.Swarbrick@racfranchising.com<mailto:Melissa.Swarbrick@racfranchising.com>> Sent: Friday, April 10, 2026 12:06 PM To: Melissa Berry <Melissa.Berry@rentacenter.com<mailto:Melissa.Berry@rentacenter.com>> Cc: Store 04832 <Store.04832@rentacenter.com<mailto:Store.04832@rentacenter.com>>; Store 01176 <Store.01176@rentacenter.com<mailto:Store.01176@rentacenter.com>> Subject: RE: Special Order PO Hi, are you needing the PO reinstated? What is the PO number? Thanks From: Melissa Berry <Melissa.Berry@rentacenter.com<mailto:Melissa.Berry@rentacenter.com>> Sent: Friday, April 10, 2026 10:39 AM To: Melissa Swarbrick <Melissa.Swarbrick@racfranchising.com<mailto:Melissa.Swarbrick@racfranchising.com>> Cc: Store 04832 <Store.04832@rentacenter.com<mailto:Store.04832@rentacenter.com>>; Store 01176 <Store.01176@rentacenter.com<mailto:Store.01176@rentacenter.com>> Subject: Special Order PO Melissa anyway you can assist me with this. This customer did a special order and because PO's got canceled I can't check it in or void the sale and can transfer the account out of the closing store. If this is not something you can help with, can you please let me know how can? See pic below Thanks Melissa Berry D0156 [cid:image001.png@01DCCD29.81051760] | I32: RACPad Support | J32: Tejas Acharya | K32: RACPAD - Agreement | M32: PRB0044395 | O32: 04832 - BONITA BEACH ROAD - I - M0156 - R0024 - S08 - RACUSA | P32: Incident-App-DataFixDeployed | Q32: Steps taken for resolution: Voided the agreement and transferred the customer account to store 4143. Category: Racpad Agreement | S32: Payment | T32: Payment reversal | U32: =VLOOKUP(T32,'Standard Type of Issue'!$B$1:$C$332,2,0) -> Payment reversal
A33: INCTEC1618817 | B33: 46128.452 | C33: 4 - Low | D33: Closed | E33: Self Service | F33: FALSE | G33: RACPAD - Agreement | Agreement Void | | H33: This store is closing down and this customer had something on customer order waiting to come and I need to void it to transfer the customer to another store. The system wont let me void it because it wants me to reverse the payment for it. I can't reverse the payment because it wasn't the last transaction on the account. Agreement Number: 8175159437 Customer ID: 17012876 Customer Name: Linda Clark Date and Time Issue Was Occured: 2026-04-16 10:49:42 | I33: RACPad Support | J33: Rashmitha Shetty | K33: RACPAD - Agreement | M33: PRB0044395 | O33: 32009 - - I - M0136 - R0008 - S07 - RACUSA | P33: Incident-App-DataFixDeployed | Q33: As requested, we have voided the agreement#8175159437. Resolving this incident after getting store confirmation. | S33: Payment | T33: Payment reversal | U33: =VLOOKUP(T33,'Standard Type of Issue'!$B$1:$C$332,2,0) -> Payment reversal
A34: INCTEC1618928 | B34: 46128.549 | C34: 4 - Low | D34: Closed | E34: Phone | F34: FALSE | G34: Racpad issue | H34: Emp name: Dalton Craig Emp id: 321288 Store number: 02141 Customer name: Desiree Cahill Wood Customer id: 109984058 Agreement number: 8175346285 Item number: 9999221150439 Reason for : User need to exchange the refrigerator in Rac exchange program. So user is trying to void the agreement but he is getting error while trying to do so Error snap is attached | I34: RACPad Support | J34: ankita singh | K34: RACPAD - Agreement | M34: PRB0044395 | O34: 02141 - KNOXVILLE-ASHVILLE - A - M0202 - R0070 - S08 - RACUSA | P34: Incident-NoIssueFound | Q34: Called the store and spoke with Dalton, Confirmation has been received that the agreement has been delivered and the RAC exchange has been completed. As the issue is resolved, we are proceeding with closing the ticket. | S34: Payment | T34: Payment reversal | U34: =VLOOKUP(T34,'Standard Type of Issue'!$B$1:$C$332,2,0) -> Payment reversal
A35: INCTEC1619048 | B35: 46128.695 | C35: 4 - Low | D35: Closed | E35: Phone | F35: FALSE | G35: RACFI-RacPad Agreement Issue | H35: Cust Name & ID : Bernard Castillo - 115077885 Agreement # : 8175070866 User told that he is unable to void the above mentioned agreement | I35: RACPad Support | J35: Lalit RameshTurkar | K35: RACPAD - Agreement | M35: PRB0044395 | O35: 02635 - LYNNWOOD-LONG BEACH BLVD - A - M0993 - R0999 - S098 - RACFI | P35: Incident-App-DataFixDeployed | Q35: Hi Store , as per the request we have made the changes and Agreement has been voided. Attached screenshot for your reference. | S35: Payment | T35: Payment reversal | U35: =VLOOKUP(T35,'Standard Type of Issue'!$B$1:$C$332,2,0) -> Payment reversal
A36: INCTEC1619665 | B36: 46130.408 | C36: 4 - Low | D36: Closed | E36: Self Service | F36: FALSE | G36: RACPAD - Payment | Customer Refund | | H36: Customer Name: ISABEL FLORES Last 4 of Card Used: 8604 Exact Amount of Refund: 10.00 Exact Date of Refund: N/A Agreement or Receipt #: 8175306780 RECEIPT- 462653896 Detailed Description of Issue: I NEED TO REFUND THE 10 DOLLAR RECEIPT SO I CAN VOID THE AGREEMENT | I36: RACPad Support | J36: Sushmitha Sannidhi | K36: RACPAD - Payment | M36: PRB0044395 | O36: 00794 - LAS VEGAS-DECATUR BLVD - A - M0257 - R0050 - S07 - RACUSA | P36: Incident-App-DataFixDeployed | Q36: Receipt #462653896 is reversed from backend as per the request. For the reversed receipt, refund request is raised by treasury team for the overpayment collected in the amount of $10 as requested. Please allow up to 7-10 business days for the customer to receive funds back to the card . Reversed Receipt number: 462653896 | S36: Payment | T36: Payment reversal | U36: =VLOOKUP(T36,'Standard Type of Issue'!$B$1:$C$332,2,0) -> Payment reversal
A37: INCTEC1619680 | B37: 46130.434 | C37: 4 - Low | D37: Closed | E37: Phone | F37: FALSE | G37: Customer suspense account | H37: Customer name: Vicky Stewart Customer ID: 6176391 Agreement: 8174616144 For this agreement dashboard shows that she has money on suspense account $(202.65) When store try to collect that it says transaction failed Expectation: Store need to collect payment from customer but dashboard says store owe $(202.65) in suspense account and store not able to collect that from customer Please do the needful | I37: RACPad Support | J37: monisha d | K37: RACPAD - Payment | M37: PRB0044395 | O37: 04415 - AHOSKIE-MEMORIAL - A - M0386 - R0007 - S08 - RACUSA | P37: Incident-App-DataFixDeployed | Q37: As per the request, receipt 463613607 has been reversed successfully. We had sent two follow‑up emails requesting confirmation; however, no response was received. hence, we are resolving this incident. Incident INCTEC1619680 closed based on closure of change CHG0051456. | S37: Payment | T37: Payment reversal | U37: =VLOOKUP(T37,'Standard Type of Issue'!$B$1:$C$332,2,0) -> Payment reversal
A38: INCTEC1619718 | B38: 46130.503 | C38: 4 - Low | D38: Closed | E38: Phone | F38: FALSE | G38: RACPAD - Need to void agreement | H38: Store number: 01107 Coworker name and ID: Joanna Ortiz (348971) Customer name and number: Isaiah Padilla (114921646) Issue description: Coworker requested to void the agreement and move the item to the inventory. Agreement # 8175352363 Item # 9999222251029 Steps taken to arrive at problem: Time of occurrence (Recreate the issue and notate the time if needed): Screen shot required: YES | I38: RACPad Support | J38: Tejas Acharya | K38: RACPAD - Agreement | M38: PRB0044395 | O38: 01107 - DENVER-COLFAX & C NORTH - A - M0235 - R0011 - S07 - RACUSA | P38: Incident-App-DataFixDeployed | Q38: Steps taken for resolution: Agreement #8175352363. has been voided as requested. Category: Racpad Agreement | R38: SR | S38: Payment | T38: Payment reversal | U38: =VLOOKUP(T38,'Standard Type of Issue'!$B$1:$C$332,2,0) -> Payment reversal
A39: INCTEC1620261 | B39: 46132.536 | C39: 4 - Low | D39: Closed | E39: Self Service | F39: FALSE | G39: RACPAD - Payment | Customer Refund | | H39: Customer placed order on line for item out of approval limit. Order was cancelled from Ashley on 4-16-26 PO#16421674. Refund amount of $44.16 Agreement Number: 8175349194 Customer ID: 108195697 Customer Name: Anthony Brookshire Date and Time Issue Was Occured: 2026-04-20 03:01:02 | I39: RACPad Support | J39: Aditi Nayak | K39: RACPAD - Payment | M39: PRB0044395 | O39: 04064 - BELLEVUE PARK PLAZA - A - M0538 - R0039 - S07 - RACUSA | P39: Incident-App-DataFixDeployed | Q39: Upon checking, we could see the amount $-3.00 partially refunded to the customer. once a receipt has been partially reversed, the remaining amount cannot be reversed from the backend. For the remaining amount, the store must submit a Check Request through Accounts Payable. | S39: Payment | T39: Payment reversal | U39: =VLOOKUP(T39,'Standard Type of Issue'!$B$1:$C$332,2,0) -> Payment reversal
A40: INCTEC1620292 | B40: 46132.575 | C40: 4 - Low | D40: Closed | E40: Self Service | F40: FALSE | G40: RACPAD - Payment | Customer Refund | | H40: Customer Name: Becca Gahm Last 4 of Card Used: 1937 Exact Amount of Refund: 773.53 Exact Date of Refund: ASAP Agreement or Receipt #: 8173618046 & 100015861454 Detailed Description of Issue: Customer ordered a refrigerator in October, it arrived and was set for delivery, but the customer never received it and had cancelled the order, but it wasn't communicated to the store. She had autopay set up from the start, and it was pulling every two weeks since December. I have attached her payment history as well as her initial payment for the order (it doesn't show on the payment history). The total amount comes to $773.53. While we were not able to get a hold of her until now (she was supposed to move here from Colorado, but that changed at the end of last year), I do feel that she is entitled to her money. The delivery was never confirmed in the system, either. | I40: RACPad Support | J40: Aditi Nayak | K40: RACPAD - Payment | M40: PRB0044395 | O40: 04059 - SPRINGFIELD-N. KANSAS - A - M0214 - R0080 - S08 - RACUSA | P40: Incident-App-DataFixDeployed | Q40: Closing the ticket as per store confirmation | S40: Payment | T40: Payment reversal | U40: =VLOOKUP(T40,'Standard Type of Issue'!$B$1:$C$332,2,0) -> Payment reversal
A41: INCTEC1620390 | B41: 46132.721 | C41: 4 - Low | D41: Closed | E41: Self Service | F41: FALSE | G41: RACPAD - Agreement | Agreement Void | | H41: I need to void this agreement. Order was placed on 11/07/2024. Order was never received, and I am unable to void it. Thank you. Agreement Number: 8170764513 Customer ID: 110902596 Customer Name: Danielle Patton Date and Time Issue Was Occured: 2026-04-20 17:15:40 | I41: RACPad Support | J41: Divya P | K41: RACPAD - Agreement | M41: PRB0044395 | O41: 04219 - SPRINGFIELD-CLEAR LAKE - A - M0209 - R0019 - S08 - RACUSA | P41: Incident-ServiceRestored | Q41: Called the store and talked with Mikeal Anders, he said he is unable to reverse the receipt and informed me to close the ticket. Hence , closing it. | S41: Payment | T41: Payment reversal | U41: =VLOOKUP(T41,'Standard Type of Issue'!$B$1:$C$332,2,0) -> Payment reversal
A42: INCTEC1620481 | B42: 46133.364 | C42: 4 - Low | D42: Awaiting Confirmation | E42: Self Service | F42: TRUE | G42: RACPAD - Agreement | Agreement - Other | | H42: Bryan Mangus and Alysia Meyer have been showing up on our dashboard for years and we need to get them removed. Agreement Number: 8169486938, 07776602518 Customer ID: 1027587, 1028749 Customer Name: Bryan Mangus, Alysia Meyer Date and Time Issue Was Occured: 2026-04-21 09:40:21 | I42: RACPad Support | J42: racha sahithya | K42: RACPAD - Agreement | M42: PRB0044395 | O42: 03512 - SIDNEY-MICHIGAN - A - M0328 - R0019 - S08 - RACUSA | S42: Payment | T42: Payment reversal | U42: =VLOOKUP(T42,'Standard Type of Issue'!$B$1:$C$332,2,0) -> Payment reversal
A43: INCTEC1620773 | B43: 46133.701 | C43: 4 - Low | D43: Closed | E43: Self Service | F43: FALSE | G43: RACPAD - Payment | Unable to reverse the payment | | H43: customer placed a special order. customer canceled tried to void but when it goes to do reversal it is grayed out so cannot select to complete it. Agreement Number: 8175382880 Customer ID: Thompson Customer Name: Dominic Date and Time Issue Was Occured: 2026-04-21 16:42:29 | I43: RACPad Support | J43: Aditi Nayak | K43: RACPAD - Payment | M43: PRB0044395 | O43: 00507 - ROUND ROCK - A - M0066 - R0079 - S07 - RACUSA | P43: Incident-App-DataFixDeployed | Q43: As per the request, we have reversed receipt: 463649043 and The Treasury team has initiated the refund. | S43: Payment | T43: Payment reversal | U43: =VLOOKUP(T43,'Standard Type of Issue'!$B$1:$C$332,2,0) -> Payment reversal
A44: INCTEC1620827 | B44: 46133.884 | C44: 4 - Low | D44: Resolved | E44: Self Service | F44: TRUE | G44: RACPAD - Customer | Customer - Other | | H44: Hood, Anthony is on the home screen of RAC pad. Can you help remove him from there? Thank you Customer ID: 114054689 Customer Name: Hood, Anthony Date and Time Issue Was Occured: 2026-04-21 19:10:40 | I44: RACPad Support | J44: Sushmitha Sannidhi | K44: RACPAD - Agreement | M44: PRB0044395 | O44: 02034 - CLASSEN - A - M0542 - R0080 - S08 - RACUSA | P44: Incident-App-DataFixDeployed | Q44: Agreement #8173629414 is voided and receipt #446138991 is reversed from the backend as per the request. Please refer the attached screenshots. However, treasury team confirmed that they will not be able to issue the refund due to age of the debit card. Store must submit a 'check request' to reimburse the Customer or ask the Customer contact their bank/financial institution to recoup the funds. A document is attached describing the steps to submit a check request. Resolving this incident after getting the store confirmation | S44: Payment | T44: Payment reversal | U44: =VLOOKUP(T44,'Standard Type of Issue'!$B$1:$C$332,2,0) -> Payment reversal
A45: INCTEC1621600 | B45: 46135.753 | C45: 4 - Low | D45: Awaiting Confirmation | E45: Phone | F45: TRUE | G45: RACFI-RACPAD- | H45: Store number: 07133 Coworker name and ID: Damien Flynn || 353486 Customer name and number: Victor Holguin || 114075758 Computer name: 07133-F7V61D3 Agreement No : 8174670739 Item no - 9999221808671 Issue description: Request for Reverse Payment Steps taken to arrive at problem: | I45: RACPad Support | J45: Aditi Agarwal | K45: RACPAD - Payment | M45: PRB0044395 | O45: 07133 - - A - M7033 - R0711 - S722 - RACFI | S45: Payment | T45: Payment reversal | U45: =VLOOKUP(T45,'Standard Type of Issue'!$B$1:$C$332,2,0) -> Payment reversal
A46: INCTEC1621812 | B46: 46136.471 | C46: 4 - Low | D46: Closed | E46: Phone | F46: FALSE | G46: Payment Reversal Issue | H46: Issue The CW reported that he is unable to reverse the payment for his customer. Customer Details Customer Name: Adrian Margarito Customer ID: 6446561 Store: 0205 | I46: RACPad Support | J46: Aditi Nayak | K46: RACPAD - Payment | M46: PRB0044395 | O46: M7022 - - M7022 - R0709 - S715 - FRC | P46: Incident-App-DataFixDeployed | Q46: Resolution steps: Reversed receipt 463766466 from the backend. Since the payment mode was cash, store should refund amount to customer in cash. Category: Receipt reversal | R46: SR | S46: Payment | T46: Payment reversal | U46: =VLOOKUP(T46,'Standard Type of Issue'!$B$1:$C$332,2,0) -> Payment reversal
A47: INCTEC1621823 | B47: 46136.488 | C47: 4 - Low | D47: Awaiting Change | E47: Phone | F47: TRUE | G47: RACFI-Agreement Void / Payment Reversal | H47: Issue The CW requested to void the agreement but is unable to reverse the payment. She stated that the customer purchased three items, one of which is no longer needed and has been returned to the store. Consequently, she needs to void the agreement; however, the system requires a payment reversal to proceed. She is unable to complete this because reversing the payment would affect all three items rather than just the single returned item. Customer Details Customer Name: Robert Sloan Customer ID: 115135799 Store: 07242 Agreement #: 8175230123 Item: 9999222464808 | I47: RACPad Support | J47: shweta wadhwa | K47: RACPAD - Agreement | M47: PRB0044395 | O47: 07242 - - A - M7008 - R0708 - S712 - RACFI | S47: payment | T47: Payment reversal | U47: =VLOOKUP(T47,'Standard Type of Issue'!$B$1:$C$332,2,0) -> Payment reversal
A48: INCTEC1621863 | B48: 46136.529 | C48: 4 - Low | D48: Closed | E48: Self Service | F48: FALSE | G48: RACPAD - Agreement | Agreement Void | | H48: Pending agreement can not be voided. Agreement Number: 8173635998 Customer ID: 111588989 Customer Name: MAURICIO CARVALLO Date and Time Issue Was Occured: 2026-04-24 12:38:59 | I48: RACPad Support | J48: Abhishek TV | K48: RACPAD - Agreement | M48: PRB0044395 | O48: 01399 - MELROSE PARK - I - M0299 - R0039 - S07 - RACUSA | P48: Incident-App-DataFixDeployed | Q48: Steps taken for resolution: As per the request, we have updated the agreement #8173635998 status to 'Void' for the customer listed below. Customer name: MAURICIO CARVALLO Customer ID: 111588989 Agreement #: 8173635998 We have also reversed the receipt id #446180704 associated with the agreement. Treasury team could not be issued the refund to the customer's CC due to age of the debit card transaction: We would kindly ask that the Customer contact their bank/financial institution to recoup the funds. Category: Agreement void | S48: payment | T48: Payment reversal | U48: =VLOOKUP(T48,'Standard Type of Issue'!$B$1:$C$332,2,0) -> Payment reversal
A49: INCTEC1621865 | B49: 46136.53 | C49: 4 - Low | D49: Resolved | E49: Self Service | F49: TRUE | G49: RACPAD - Agreement | Agreement Void | | H49: Pending agreement can not be voided Agreement Number: 2173637110 Customer ID: 111588989 Customer Name: Mauricio Carvallo Date and Time Issue Was Occured: 2026-04-24 12:43:06 | I49: RACPad Support | J49: Sushmitha Sannidhi | K49: RACPAD - Agreement | M49: PRB0044395 | O49: 01399 - MELROSE PARK - I - M0299 - R0039 - S07 - RACUSA | P49: Incident-App-DataFixDeployed | Q49: We have voided the agreements #8173637110 and #8173635998 as per the request. Team, we follow a two-strike policy where we try to get in touch with the store or the coworker via an email or by call for confirmation. We were not able to get in touch with the coworker even after repeated calls and emails. Hence, we believe the issue is resolved. If the issue persists, please raise a new incident. Don't re-open this incident so that we can help you better. Also please refer the email sent for more information. | S49: payment | T49: Payment reversal | U49: =VLOOKUP(T49,'Standard Type of Issue'!$B$1:$C$332,2,0) -> Payment reversal
A50: INCTEC1621867 | B50: 46136.532 | C50: 4 - Low | D50: Closed | E50: Self Service | F50: FALSE | G50: RACPAD - Agreement | Agreement Void | | H50: Pending agreement can not be voided Agreement Number: 8174397192 Customer ID: 107777793 Customer Name: Justin Sidener Date and Time Issue Was Occured: 2026-04-24 12:45:12 | I50: RACPad Support | J50: shweta wadhwa | K50: RACPAD - Agreement | M50: PRB0044395 | O50: 01399 - MELROSE PARK - I - M0299 - R0039 - S07 - RACUSA | P50: Incident-App-DataFixDeployed | Q50: As per the request, the receipt has been reversed, and the agreement has been voided successfully. Same has been validated. Please refer attached screenshot for same. | S50: payment | T50: Payment reversal | U50: =VLOOKUP(T50,'Standard Type of Issue'!$B$1:$C$332,2,0) -> Payment reversal
A51: INCTEC1621938 | B51: 46136.623 | C51: 4 - Low | D51: Awaiting Confirmation | E51: Self Service | F51: TRUE | G51: RACPAD - Agreement | Agreement Void | | H51: Customer ordered the tv during a 50% off event last year. The TV never showed up. The agreement needs to be voided and the customer refunded either as a credit on her account or back onto the card it was paid with. Agreement Number: 8173323773 Customer ID: 2489019 Customer Name: Jacqueline Alley Date and Time Issue Was Occured: 2025-09-15 14:49:42 | I51: RACPad Support | J51: monisha d | K51: RACPAD - Agreement | M51: PRB0044395 | O51: 00953 - VANCOUVER-WEST - A - M0265 - R0050 - S07 - RACUSA | S51: Payment | T51: Payment reversal | U51: =VLOOKUP(T51,'Standard Type of Issue'!$B$1:$C$332,2,0) -> Payment reversal
A52: INCTEC1622120 | B52: 46137.427 | C52: 4 - Low | D52: Work Started | E52: Phone | F52: TRUE | G52: Agreement Void | H52: Agreement need to Void Store is unable to perform this task as Reverse icon is greyed out Agreement: 8175336011 ELIJAH YATES - 114742653 Amount - $10 need to be refunded to customer & void agreement Reason : Verification not successful | I52: RACPad Support | J52: Pratik Singar | K52: RACPAD - Agreement | M52: PRB0044395 | O52: 01980 - DAYTON-3RD ST - A - M0200 - R0061 - S08 - RACUSA | S52: Payment | T52: Payment reversal | U52: =VLOOKUP(T52,'Standard Type of Issue'!$B$1:$C$332,2,0) -> Payment reversal
A53: INCTEC1622165 | B53: 46137.505 | C53: 4 - Low | D53: Awaiting Confirmation | E53: Phone | F53: TRUE | G53: Racpad | customer refund | H53: Wanted to process refund for one of the customer Customer : Cheryl English Customer ID : 112366964 Refund : Sept 2025 till January 2026 | I53: RACPad Support | J53: Sushmitha Sannidhi | K53: RACPAD - Payment | M53: PRB0044395 | O53: 03077 - Greece - A - M0314 - R0002 - S07 - RACUSA | S53: Payment | T53: Payment reversal | U53: =VLOOKUP(T53,'Standard Type of Issue'!$B$1:$C$332,2,0) -> Payment reversal
A54: INCTEC1622200 | B54: 46137.58 | C54: 4 - Low | D54: Awaiting Confirmation | E54: Self Service | F54: TRUE | G54: RACPAD - Payment | Customer Refund | | H54: Cx requested payment reversal. I cannot reverse payment due to last payment. Agreement Number: 8172315968 Customer ID: 2981271 Customer Name: Jarad Poole Date and Time Issue Was Occured: 2026-04-25 12:22:00 | I54: RACPad Support | J54: Sushmitha Sannidhi | K54: RACPAD - Payment | M54: PRB0044395 | O54: 00934 - SANFORD - A - M0322 - R0065 - S08 - RACUSA | S54: Payment | T54: Payment reversal | U54: =VLOOKUP(T54,'Standard Type of Issue'!$B$1:$C$332,2,0) -> Payment reversal
A55: INCTEC1616961 | B55: 46122.579 | C55: 4 - Low | D55: Closed | E55: Phone | F55: FALSE | G55: RACPAD - Duplicate Customer Accounts – Merge Request | H55: Store number: 00818 Coworker name and ID: Martha Caldwell (203312) Customer name and number: Kelsey Hughey Issue description: Coworker reported that customer Kelsey Hughey has two separate accounts. Coworker requested to have both accounts combined into a single account Screen shot required: YES | I55: RACPad Support | J55: Rashmitha Shetty | K55: RACPAD - Dashboard | M55: PRB0044564 | O55: 00818 - DEL CITY - A - M0542 - R0080 - S08 - RACUSA | P55: Request-Rejected | Q55: We tried reaching store multiple times to get the below details: Customer Ids and which customer should be treated as primary account but we haven't received any response. Thus resolving the incident. Category: Merge Customer | R55: SR | S55: Customer | T55: Cannot search customer by name | U55: =VLOOKUP(T55,'Standard Type of Issue'!$B$1:$C$332,2,0) -> search Issue
A56: INCTEC1617051 | B56: 46122.706 | C56: 4 - Low | D56: Work Started | E56: Self Service | F56: TRUE | G56: RACPAD - Customer | Customer Search | | H56: We Cannot pull Elizabeth up with her name we have to use her phone number (843) 557-2611 Customer ID: 2932945 Customer Name: ELIZABETH HOLMES Date and Time Issue Was Occured: 2026-04-10 16:55:42 | I56: RACPad Support | J56: Syeda Asfiya | K56: RACPAD - Customer | M56: PRB0044564 | O56: 00521 - MONCKS CORNER - A - M0001 - R0007 - S08 - RACUSA | S56: Customer | T56: Cannot search customer by name | U56: =VLOOKUP(T56,'Standard Type of Issue'!$B$1:$C$332,2,0) -> search Issue
A57: INCTEC1622389 | B57: 46139.048 | C57: 4 - Low | D57: Resolved | E57: Phone | F57: TRUE | G57: RACPAD - Duplicate Customer Accounts – Merge Request | H57: Store number: 00818 Coworker name and ID: Martha Caldwell (203312) Customer name and number: Kelsey Hughey Issue description: Coworker reported that customer Kelsey Hughey has two separate accounts. Coworker requested to have both accounts combined into a single account Screen shot required: YES | I57: RACPad Support | J57: Tejas Acharya | K57: RACPAD - Dashboard | M57: PRB0044564 | O57: 00818 - DEL CITY - A - M0542 - R0080 - S08 - RACUSA | P57: Incident-App-DataFixDeployed | Q57: Steps taken for resolution: The customer Kelsey Hughey (ID 110374885) has been successfully merged into the primary customer account 114723770 as requested. All agreement and club details have been updated to the primary account accordingly. Category: Racpad Customer | S57: Customer | T57: Cannot search customer by name | U57: =VLOOKUP(T57,'Standard Type of Issue'!$B$1:$C$332,2,0) -> search Issue
A58: INCTEC1618606 | B58: 46127.681 | C58: 4 - Low | D58: Closed | E58: Phone | F58: FALSE | G58: RACFI-RACPAD | H58: User called in for RACPAD Issue | I58: RACPad Support | J58: monisha d | K58: RACPAD - other | M58: PRB0044671 | O58: 01615 - NORTHEAST - A - M0018 - R0994 - S094 - RACFI | P58: Incident-App-DataFixDeployed | Q58: Incident INCTEC1618606 closed based on closure of change CHG0051380. | S58: Dashboard | T58: Store action item is showing pending delivery confirmation even for the return appointment | U58: =VLOOKUP(T58,'Standard Type of Issue'!$B$1:$C$332,2,0) -> Confirm delivery Issue
A59: INCTEC1619189 | B59: 46129.361 | C59: 4 - Low | D59: Closed | E59: Phone | F59: FALSE | G59: RACPAD- | H59: Store number: 02908 Coworker name and ID: 305927 || Shelby Pope Customer name and number: - Computer name: 02908-4ZNMZB3 Issue description: Request to clear store action item Steps taken to arrive at problem: RACPAD - DASHBOARD | I59: RACPad Support | J59: Tejas Acharya | K59: RACPAD - Dashboard | M59: PRB0044671 | O59: 02908 - ELIZABETHTOWN - A - M0004 - R0007 - S08 - RACUSA | P59: Incident-App-DataFixDeployed | Q59: Steps taken for resolution: Store action item from 2024 to March 31, 2026 have been removed as requested. Category: Racpad dashboard | S59: Dashboard | T59: Store action item is showing pending delivery confirmation even for the return appointment | U59: =VLOOKUP(T59,'Standard Type of Issue'!$B$1:$C$332,2,0) -> Confirm delivery Issue
A60: INCTEC1617207 | B60: 46123.453 | C60: 4 - Low | D60: Closed | E60: Self Service | F60: FALSE | G60: RACPAD - Customer | Update Customer | | H60: Customer states he can login to the app, will is not showing his agreement at all Customer ID: 114869390 Customer Name: Dashawn Smith Agreement #: 8174719989 Date and Time Issue Was Occured: 2026-04-11 00:00:00 issue: CW mentioned customer is unable see this Agreement #: 8174719989 and because of that he is unable to pay. Need help with this. | I60: RACPad Support | J60: Vandana K | K60: RACPAD - Customer | M60: PRB0044676 | O60: 02919 - S. DOUGLAS - A - M0333 - R0050 - S07 - RACUSA | P60: Incident-App-DataFixDeployed | Q60: The given OktaID and EmailID are tagged to the CustomerID. Hence proceeding with closing the ticket | S60: Customer | T60: Unable to link the agreement | U60: =VLOOKUP(T60,'Standard Type of Issue'!$B$1:$C$332,2,0) -> Customer Login Issue (EXT)
A61: INCEXT2292193 | B61: 46127.635 | C61: 4 - Low | D61: Closed | E61: Self Service | F61: FALSE | G61: Technical Issues | H61: The customer called in because he encountered trouble logging into his account. He opened the account, but when he tried to link the agreement, the screen froze. He also tried uninstalling and reinstalling the app, but the issue persisted. Additionally, when he tried to do it on the website, the agreement wouldn’t allow him to log in or link. What I advised is that we will escalate this concern directly to the technical team. | I61: RACPad Support | J61: Vandana K | K61: Trouble Linking Agreement | M61: PRB0044676 | O61: 01708 - EXCELSIOR SPRING - A - M0225 - R0039 - S07 - RACUSA | P61: Resolved | Q61: The given OktaID and EmailID are already tagged to the customer ID. Please find the attachment. Hence proceed with closing the ticket | S61: Customer | T61: Unable to link the agreement | U61: =VLOOKUP(T61,'Standard Type of Issue'!$B$1:$C$332,2,0) -> Customer Login Issue (EXT)
A62: INCEXT2292195 | B62: 46127.739 | C62: 4 - Low | D62: Closed | E62: Self Service | F62: FALSE | G62: Unable to link the agreement | H62: The customer called in to raise a concern about her online account. She is unable to see the next payment or her payment history because she's having trouble linking her agreement to her online account. I advised her to escalate her concern to the technical team and to wait 5 business days to be assisted. | I62: RACPad Support | J62: Vandana K | K62: Trouble Linking Agreement | M62: PRB0044676 | O62: 04472 - AMSTERDAM-RIVERFRONT - A - M0471 - R0002 - S07 - RACUSA | P62: Resolved | Q62: The given OktaID and EmailID are tagged to the CustomerID. Please find the attachment. Hence proceeding with closing the ticket | S62: Customer | T62: Unable to link the agreement | U62: =VLOOKUP(T62,'Standard Type of Issue'!$B$1:$C$332,2,0) -> Customer Login Issue (EXT)
A63: INCEXT2292198 | B63: 46128.451 | C63: 4 - Low | D63: Closed | E63: Self Service | F63: FALSE | G63: Able to Sign In but Agreement Isn't There | H63: The store called in because their customer is having trouble linking the agreement on their end. It’s not showing that the store has already assisted the customer, but it's not letting them link the agreement. I advised that we will escalate this issue to the technical team directly. Please give the store a call back to update them about the issue, as well as the customer. Here is the customer’s email address and best callback number: Customer Email: jmurph1999@yahoo.com Customer Phone: (785) 531-2287 Store Phone: (515) 233-6080 | I63: RACPad Support | J63: Vandana K | K63: Trouble Linking Agreement | M63: PRB0044676 | O63: 02610 - AMES-LINCOLN WAY - A - M0088 - R0040 - S07 - RACUSA | P63: Resolved | Q63: The given OktaID and EmailID are tagged to the CustomerID. Please find the attachment. Hence proceeding with closing the ticket | S63: Customer | T63: Unable to link the agreement | U63: =VLOOKUP(T63,'Standard Type of Issue'!$B$1:$C$332,2,0) -> Customer Login Issue (EXT)
A64: INCEXT2292199 | B64: 46128.453 | C64: 4 - Low | D64: Closed | E64: Self Service | F64: FALSE | G64: Able to Sign In but Agreement Isn't There | H64: E-commerce Format: *Customer Name: BRYANT, KIARA *Customer Phone Number: (313) 735-0069 *Email: Kiabryant.1991@gmail.com *Concern: The customer called in stating that she needs help accessing her online account. When she attempts to log in, her furniture agreements are not visible, and the system has not prompted her to link her agreement number. | I64: RACPad Support | J64: Vandana K | K64: Trouble Linking Agreement | M64: PRB0044676 | O64: 01165 - BRADENTON - A - M0156 - R0024 - S08 - RACUSA | P64: Resolved | Q64: The given OktaID and EmailID are tagged to the CustomerID. Please find the attachment. Hence proceeding with closing the ticket | S64: Customer | T64: Unable to link the agreement | U64: =VLOOKUP(T64,'Standard Type of Issue'!$B$1:$C$332,2,0) -> Customer Login Issue (EXT)
A65: INCEXT2292179 | B65: 46126.526 | C65: 4 - Low | D65: Closed | E65: Self Service | F65: FALSE | G65: Can't sign in | H65: E-commerce Format: *Customer Name: MONROE, JORDAN *Customer Phone Number: 5853330034 *Email: jayslain4@gmail.com *Concern: The customer reported a login issue with his online account. Each time he attempts to register or log in, the system indicates that his email address is already associated with another account. However, the customer claims he has never used this email with Rent-A-Center before and that it is a new address. He is inquiring if he can gain access to the existing account referred to by the system or if he must provide a different email address to proceed. | I65: RACPad Support | J65: Vandana K | K65: Can't sign in | M65: PRB0044676 | O65: 03077 - Greece - A - M0314 - R0002 - S07 - RACUSA | P65: Resolved | Q65: The given OktaID and EmailD are already tagged to the customerID. Please find the attachment. Hence proceeding with closing the ticket | S65: Customer | T65: Unable to link the agreement | U65: =VLOOKUP(T65,'Standard Type of Issue'!$B$1:$C$332,2,0) -> Customer Login Issue (EXT)
A66: INCEXT2292188 | B66: 46127.532 | C66: 4 - Low | D66: Closed | E66: Self Service | F66: FALSE | G66: Log in Issue | H66: * Customer Name: Blunt-Stith, Dominique * Customer Phone Number: (804) 720-5789 * Customer Login Email ID: domblun5280@gmail.com * Exact Error Message: Unable to locate agreement. * Agreement Number: 8171010488 * Concern: Wanted to make a payment online. * Troubleshooting Steps: Confirmed email. | I66: RACPad Support | J66: Vandana K | K66: Trouble Linking Agreement | M66: PRB0044676 | O66: 05571 - PETERSBURG-CRATER - A - M0350 - R0058 - S08 - RACUSA | P66: Resolved | Q66: The given OktaID and EmailID are tagged to the CustomerID. Hence proceeding with closing the ticket | S66: Customer | T66: Unable to link the agreement | U66: =VLOOKUP(T66,'Standard Type of Issue'!$B$1:$C$332,2,0) -> Customer Login Issue (EXT)
A67: INCEXT2292189 | B67: 46127.543 | C67: 4 - Low | D67: Closed | E67: Self Service | F67: FALSE | G67: Unable to link agreement | H67: Customer Name: CHAMBERS, SANDRA Customer login Email ID: Sycham51@gmail.com Customer Phone Number: (404) 492-1659 Exact Error Message: Customer called in cause she have a new agreement however when she tried to log in she cant get pass through linking her agreement, She tried to link the agreement however it is not going through the customer said that the store updated the email also to ( Sycham51@gmail.com) Customer said that when she tried to link it there is no specific error or special message its just not going through. Agreement Number:8175337412 Troubleshooting Steps: Tried to link multiple times also assisted by our store | I67: RACPad Support | J67: Vandana K | K67: Trouble Linking Agreement | M67: PRB0044676 | O67: 03156 - - A - M0142 - R0008 - S07 - RACUSA | P67: Resolved | Q67: The given OktaID and EmailID are tagged to the CustomerID. Hence proceeding with closing the ticket | S67: Customer | T67: Unable to link the agreement | U67: =VLOOKUP(T67,'Standard Type of Issue'!$B$1:$C$332,2,0) -> Customer Login Issue (EXT)
A68: INCEXT2292190 | B68: 46127.561 | C68: 4 - Low | D68: Closed | E68: Self Service | F68: FALSE | G68: account log in issue | H68: * Customer Name: Kelsey Warren * Customer Phone Number: (816) 725-7773 * Customer Login Email ID: kelsey.smith.warren@gmail.com * Exact Error Message: cant see agreement * Agreement Number: 8171557921 , 8171557921 * CSM Ticket Number: CSMTKT98584 * Concern: customer can log in but cant see the agreement * Troubleshooting Steps: log out an log in | I68: RACPad Support | J68: Vandana K | K68: Trouble Linking Agreement | M68: PRB0044676 | O68: 01713 - GRANDVIEW-BLUE RIDGE - A - M0353 - R0039 - S07 - RACUSA | P68: Resolved | Q68: The given OktaID and EmailID are tagged to the CustomerID. Hence proceeding with closing the ticket | S68: Customer | T68: Unable to link the agreement | U68: =VLOOKUP(T68,'Standard Type of Issue'!$B$1:$C$332,2,0) -> Customer Login Issue (EXT)
... A85: INCTEC1619074 | B85: 46128.767 | C85: 4 - Low | D85: Closed | E85: Self Service | F85: FALSE | G85: RACPAD - Reports | Daily Report | | H85: REPORT NOT REFLECTING CORRECT OR CLOSE TO NUMBERS LISTED IN HOME SCREEN | I85: RACPad Support | J85: monisha d | K85: RACPAD - Reports | M85: PRB0044727 | O85: 02601 - - A - M0267 - R0050 - S07 - RACUSA | P85: Incident-App-CodeFixDeployed | Q85: The agreement status was not synchronized, which resulted in a mismatch between the daily report and the dashboard values. A data fix was performed to address this issue, and the agreements were successfully synced from RACDB to ENT DB. As a result, the discrepancy has been resolved, and the values are now matching across the daily report and the dashboard. The store has also confirmed that the issue is resolved. Incident INCTEC1619074 closed based on closure of change CHG0051481. | S85: Report | T85: Report discrepency | U85: =VLOOKUP(T85,'Standard Type of Issue'!$B$1:$C$332,2,0) -> Report discrepency
A86: INCTEC1621470 | B86: 46135.535 | C86: 4 - Low | D86: Awaiting Change | E86: Phone | F86: TRUE | G86: Racpad Report | H86: Numbers on Dashboard dose not match from Daily report | I86: RACPad Support | J86: shweta wadhwa | K86: RACPAD - Reports | M86: PRB0044727 | O86: 04617 - PHILADELPHIA-CHELTENHAM - A - M0287 - R0065 - S08 - RACUSA | S86: Report | T86: Report discrepency | U86: =VLOOKUP(T86,'Standard Type of Issue'!$B$1:$C$332,2,0) -> Report discrepency
A87: INCTEC1616658 | B87: 46121.584 | C87: 4 - Low | D87: Closed | E87: Phone | F87: FALSE | G87: Racpad Customer | H87: CW Name :Bruce Hillje2 Emp ID : 176430 Store: 01764 Computer Name: 01764 4SNC1D3 Description : Dashboard and Daily report data dose not match hence cw is getting incorrect data need help with same On RACPAD dashboard PAST DUE TOTAL : 12.3 % 3.8% 7+ days 2.3& 15+days is correct data On Daily report its different highlighted in screen shot Please get it corrected Also the customer ESPERANZA ALVAREZ - 2408587 has new agreement -still same user comes under 31days past due in Daily Credit portfolio received from Centralized Reporting - That incorrect data | I87: RACPad Support | J87: monisha d | K87: RACPAD - Customer | M87: PRB0044947 | O87: 01764 - CHARLOTTE-3114 EASTWAY - A - M0035 - R0008 - S07 - RACUSA | P87: Incident-App-DataFixDeployed | Q87: Incident INCTEC1616658 closed based on closure of change CHG0051445. | S87: Report | T87: Report discrepency | U87: =VLOOKUP(T87,'Standard Type of Issue'!$B$1:$C$332,2,0) -> Report discrepency
A88: INCTEC1614030 | B88: 46113.774 | C88: 4 - Low | D88: Closed | E88: Self Service | F88: FALSE | G88: RACFI-RACiNET | Others | | H88: RACPad Issue confirming delivery for a customer. Customer Name: LINDA COTTINGHAM Agreement #: 8174745779 When attempting to confirm the delivery for the customer via the 'Delivery Method' tab in the agreement. Following this process results in an error that prevents us from confirming the delivery. Delivery Method > Reprint Delivery > [Confirm reprint] > Confirm Delivery > Yes > ERROR OCCURS HERE The prompt "Delivery not Confirmed" appears and the page infinitely loads until it is refreshed. Attempting to repeat the process results in the same error on multiple different devices at the store. The resolution I am looking for is to have the agreement's status set to delivered. | I88: RACPad Support | J88: Tejas Acharya | K88: RACPAD - Agreement | M88: PRB0044979 | O88: 00719 - LANCASTER-AVE J - A - M0993 - R0999 - S098 - RACFI | P88: Incident-ServiceRestored | Q88: contacted user at callback number user said the issue has been resolved hence resolving as per users confirmation | S88: Agreement | T88: Unable to confirm delivery | U88: =VLOOKUP(T88,'Standard Type of Issue'!$B$1:$C$332,2,0) -> Unable to confirm delivery
A89: INCTEC1614288 | B89: 46114.576 | C89: 4 - Low | D89: Closed | E89: Phone | F89: FALSE | G89: RACFI-RACPAD | H89: User called in for unable to confirm the customer delivery Store number: 00515 - COVINA - A - M0296 - R0999 - S098 - RACFI Coworker name and ID: Sandivel Chaves 156200 Customer name and number: Manuel Taylor - 542101 Computer name: 00515-B6678Y3 IP address: 10.102.2.47 Issue description: User called in for unable to confirm the customer delivery Steps taken to arrive at problem: Time of occurrence (Recreate the issue and notate the time if needed): Screen shot required: YES | I89: RACPad Support | J89: monisha d | K89: RACPAD - other | M89: PRB0044979 | O89: 00515 - COVINA - A - M0993 - R0999 - S098 - RACFI | P89: Incident-App-DataFixDeployed | Q89: Incident INCTEC1614288 closed based on closure of change CHG0051406. | S89: Agreement | T89: Unable to confirm delivery | U89: =VLOOKUP(T89,'Standard Type of Issue'!$B$1:$C$332,2,0) -> Unable to confirm delivery
A90: INCTEC1614776 | B90: 46115.77 | C90: 4 - Low | D90: Closed | E90: Phone | F90: FALSE | G90: RACPAD | H90: User called in for unable to confirm the agreement Store number: 01778 - GREENVILLE - A - M0167 - R0007 - S08 - RACUSA Coworker name and ID: Corris Cannonier 79293 Customer name and number: Khatara Johnson - 25391130 Agreement: 8173260036 Computer name: 01778-7WSQZB3 IP address: 10.106.241.42 Issue description: User called in for unable to confirm the agreement Steps taken to arrive at problem: Time of occurrence (Recreate the issue and notate the time if needed): Screen shot required: YES | I90: RACPad Support | J90: Abhishek TV | K90: RACPAD - Agreement | M90: PRB0044979 | O90: 01778 - GREENVILLE - A - M0167 - R0007 - S08 - RACUSA | P90: Incident-ServiceRestored | Q90: Called the store and spoke with CW She checked and confirmed that the issue has been resolved Hence closing the ticket | S90: Agreement | T90: Unable to confirm delivery | U90: =VLOOKUP(T90,'Standard Type of Issue'!$B$1:$C$332,2,0) -> Unable to confirm delivery
A91: INCTEC1614949 | B91: 46116.559 | C91: 4 - Low | D91: Closed | E91: Self Service | F91: FALSE | G91: RACFI-RACPAD - Customer | Customer - Other | | H91: unable to confirm delivery for a non special items Customer ID: MARCO SORIANO - 111788814 Customer Name: MARCO SORIANO - 111788814 Date and Time Issue Was Occured: 2026-04-04 13:23:45 | I91: RACPad Support | J91: Aditi Nayak | K91: RACPAD - Agreement | M91: PRB0044979 | O91: 01068 - HUNTINGTON PARK - A - M0993 - R0999 - S098 - RACFI | P91: Incident-App-DataFixDeployed | Q91: Delivery is confirmed for the agreements 8174717130 and 8174594249. Hence closing the ticket as request is fulfilled. | S91: Agreement | T91: Unable to confirm delivery | U91: =VLOOKUP(T91,'Standard Type of Issue'!$B$1:$C$332,2,0) -> Unable to confirm delivery
A92: INCTEC1622476 | B92: 46139.416 | C92: 4 - Low | D92: Closed | E92: Phone | F92: FALSE | G92: Racpad Customer- unable to confirm delivery for customer | H92: CW Name: Wondrietta DixonCrockett CW Emp ID: 232558 Location:02593 Computer Name 2NN31D3 Customer Name: Robert Lang Customer ID: 114098069 Agreement Number:8174827932 Description: unable to confirm delivery for customer | I92: RACPad Support | J92: Abhishek TV | K92: RACPAD - Customer | M92: PRB0044979 | O92: 02593 - GREENWOOD-W PARK AVE - A - M0497 - R0039 - S07 - RACUSA | P92: Incident-App-DataFixDeployed | Q92: Steps taken for resolution: Delivery has been confirmed for the agreement #8174827932 as per the request. Screenshot is attached for reference. Category: Agreement Delivery confirmation | S92: Agreement | T92: Unable to confirm delivery | U92: =VLOOKUP(T92,'Standard Type of Issue'!$B$1:$C$332,2,0) -> Unable to confirm delivery
A93: INCTEC1618935 | B93: 46128.556 | C93: 4 - Low | D93: Closed | E93: Self Service | F93: FALSE | G93: RACPAD - Inventory | Inventory - Other | | H93: This is the second or third ticket on this issue. This item will not confirm delivery Inventory Number: 9999221672563 Date and Time Issue Was Occured: 2026-04-16 13:20:26 | I93: RACPad Support | J93: Pratik Singar | K93: RACPAD - Agreement | M93: PRB0044979 | O93: 05538 - CLERMONT-HWY 50 - A - M0132 - R0024 - S08 - RACUSA | P93: Incident-App-DataFixDeployed | Q93: We have confirmed the delivery for the agreement . Appointment status updated to Completed for the agreement. Please refer attachment | S93: Agreement | T93: Unable to confirm delivery | U93: =VLOOKUP(T93,'Standard Type of Issue'!$B$1:$C$332,2,0) -> Unable to confirm delivery
A94: INCTEC1623121 | B94: 46140.575 | C94: 4 - Low | D94: Closed | E94: Self Service | F94: FALSE | G94: RACPAD - Agreement | Delivery Confirmation | | H94: cant confirm Agreement Number: 8175403368 Customer ID: 2155753 Customer Name: 8175403368 Date and Time Issue Was Occured: 2026-04-28 13:42:05 | I94: RACPad Support | J94: Abhishek TV | K94: RACPAD - Agreement | M94: PRB0044979 | O94: 01655 - WALKER-TS - A - M0118 - R0020 - S08 - RACUSA | P94: Incident-App-DataFixDeployed | Q94: Steps taken for resolution: Confirmed the delivery for the agreement: 8175403368 as requested by the store. Justin Domanski confirmed that the issue is resolved. Screenshots are attached for reference. Category: Delivery confirmation | S94: Agreement | T94: Unable to confirm delivery | U94: =VLOOKUP(T94,'Standard Type of Issue'!$B$1:$C$332,2,0) -> Unable to confirm delivery
A95: INCTEC1620302 | B95: 46132.601 | C95: 4 - Low | D95: Closed | E95: Self Service | F95: FALSE | G95: RACPAD - Agreement | Delivery Confirmation | | H95: When trying to confirm her carry out, an error message pops up "No active customers tied to the agreement". Please advise. Agreement Number: 8175371509 Customer ID: 19331800 Customer Name: Danielle Kaokai | I95: RACPad Support | J95: Tejas Acharya | K95: RACPAD - Agreement | M95: PRB0044979 | O95: 01315 - WAHIAWA - A - M0267 - R0050 - S07 - RACUSA | P95: Incident-App-DataFixDeployed | Q95: Steps taken for resolution: Delivery has been confirmed for agreement #8175371509 from backend. Category: Racpad Agreement | S95: Agreement | T95: Unable to confirm delivery | U95: =VLOOKUP(T95,'Standard Type of Issue'!$B$1:$C$332,2,0) -> Unable to confirm delivery
A96: INCTEC1621987 | B96: 46136.703 | C96: 4 - Low | D96: Closed | E96: Self Service | F96: FALSE | G96: RACPAD - Agreement | RAC Exchange | | H96: Customers are currently unable to complete the payoff process for RAC exchange transactions. When attempting to initiate or finalize a payoff, the system does not allow the transaction to go through. Additionally, users are unable to set or confirm delivery after initiating the payoff. This issue prevents completion of the exchange process, as the system blocks both the payoff confirmation and delivery scheduling steps. As a result, customers are unable to finalize their agreements, leading to delays and potential dissatisfaction. Agreement Number: 8175406103 Customer ID: 108904043 Customer Name: AARON BARKHIMER Date and Time Issue Was Occured: 04-24-2026 16:49:50 | I96: RACPad Support | J96: Tejas Acharya | K96: RACPAD - Agreement | M96: PRB0044979 | O96: 00055 - - A - M0542 - R0080 - S08 - RACUSA | P96: Incident-App-DataFixDeployed | Q96: Steps taken for resolution: Delivery has been confirmed for Agreement#8175406103 from backend. Category: Racpad Agreement | S96: Agreement | T96: Unable to confirm delivery | U96: =VLOOKUP(T96,'Standard Type of Issue'!$B$1:$C$332,2,0) -> Unable to confirm delivery
A97: INCTEC1622206 | B97: 46137.595 | C97: 4 - Low | D97: Closed | E97: Self Service | F97: FALSE | G97: RACPAD - Agreement | Delivery Confirmation | | H97: Getting error message when trying to confirm, message is " agreement not tied to active customer" Agreement Number: 8175420349 Customer ID: 1296337 Customer Name: ANNA GONZABA Date and Time Issue Was Occured: 2026-04-25 14:15:16 | I97: RACPad Support | J97: Tejas Acharya | K97: RACPAD - Agreement | M97: PRB0044979 | O97: 00619 - SAN AN-DEPOT SOUTH - A - M0064 - R0079 - S07 - RACUSA | P97: Incident-App-DataFixDeployed | Q97: Steps taken for resolution: Delivery has been confirmed for agreement #8175420349 from backend Category: Racpad Agreement | S97: Agreement | T97: Unable to confirm delivery | U97: =VLOOKUP(T97,'Standard Type of Issue'!$B$1:$C$332,2,0) -> Unable to confirm delivery
A98: INCTEC1618519 | B98: 46127.498 | C98: 4 - Low | D98: Closed | E98: Phone | F98: FALSE | G98: RACFI-Unable to activate/void agreement for a special order | H98: Store number: 07168 Coworker name and ID: Christina Cardenas 6020344 Customer name and number: LEON SNYDER- 6231189 Agreement #: 8175214275 Issue description: >Not able to void agreement >CW is tried voiding by reversing the payment that too is not working | I98: RACPad Support | J98: Sushmitha Sannidhi | K98: RACPAD - Agreement | M98: PRB0045088 | O98: 07168 - - A - M0540 - R0993 - S093 - RACFI | P98: Incident-App-DataFixDeployed | Q98: Agreement #8175214275 is voided for the customer Leon Snyder (6231189) and inventory status of item #9999222416674 is updated to "Rent Ready" as per the request. Please refer the attached screenshots. Team, we follow a two-strike policy where we try to get in touch with the store or the coworker via an email or by call for confirmation. We were not able to get in touch with the coworker even after repeated calls and emails. Hence, we believe the issue is resolved. If the issue persists, please raise a new incident. Don't re-open this incident so that we can help you better. Also please refer the email sent for more information. | S98: Payment | T98: Amount Mismatch Error on Initial Payment for Customer Order Agreement | U98: =VLOOKUP(T98,'Standard Type of Issue'!$B$1:$C$332,2,0) -> Payment Error
... A102: INCTEC1621818 | B102: 46136.483 | C102: 4 - Low | D102: Resolved | E102: Phone | F102: TRUE | G102: RACPAD Payment issue | H102: Co-worker name: Roberto Medellin Employee ID: 368659 Store: 02260 Customer name: Valerie Pena Customer ID: 115154337 Agreement #: 8175384083 issue: CW mentioned unable to take payment of the customer order. Getting Error. Need help with this. | I102: RACPad Support | J102: Aditi Agarwal | K102: RACPAD - Payment | M102: PRB0045088 | O102: 02260 - LAREDO - SAN DAVIO RD. - A - M0055 - R0079 - S07 - RACUSA | P102: Incident-NoIssueFound | Q102: Called the CW and confirmed that the issue has been resolved. Thus, proceeding to close the ticket. | S102: Payment | T102: Amount Mismatch Error on Initial Payment for Customer Order Agreement | U102: =VLOOKUP(T102,'Standard Type of Issue'!$B$1:$C$332,2,0) -> Payment Error
A103: INCTEC1618245 | B103: 46126.758 | C103: 4 - Low | D103: Awaiting User Info | E103: Self Service | F103: TRUE | G103: RACPAD - Cash Management | Final Drop | | H103: Daily reflect $10 drop however drop receipt reflect no deposit. ================================================================= Co-worker name: Victor CentenoII Employee ID: 363211 Store: 01201 Issue: CW mentioned in Daily report there is $10 drop. But there is no drop receipt found. Need help with this | I103: RACPad Support | J103: Sushmitha Sannidhi | K103: RACPAD - Cash Management | M103: PRB0045141 | O103: 01201 - CUTLER RIDGE - A - M0155 - R0024 - S08 - RACUSA | S103: Report | T103: Report discrepency | U103: =VLOOKUP(T103,'Standard Type of Issue'!$B$1:$C$332,2,0) -> Report discrepency
A104: INCTEC1614343 | B104: 46114.635 | C104: 4 - Low | D104: Closed | E104: Self Service | F104: FALSE | G104: RACPAD - Payment | NSF | | H104: Customer's payment pulled on 12/20/25 and her bank records show it came out on 12/22/25. Her next payment on 1/26/26 showed an NSF for the prior payment, but her bank statements for the month don't reflect that. She has since paid the payment and charges and paid off. Agreement Number: 8174235443 Customer ID: 110305198 Customer Name: Karen Miller Date and Time Issue Was Occured: 2025-12-20 15:01:04 | I104: RACPad Support | J104: Incharashree KY | K104: RACPAD - Payment | M104: PRB0045145 | O104: 03930 - WASHINGTON-W.CHESTNUT - A - M0544 - R0058 - S08 - RACUSA | P104: Request-Fulfilled | Q104: As previously informed to Fred Groves, the NSF has been removed. For the refund, the store needs to submit a check request. Fred Groves stated that he will attempt to send the check request today and insisted on closing the ticket. Based on his acknowledgment, I am closing the ticket. | S104: Customer | T104: Incorrect Charge back added | U104: =VLOOKUP(T104,'Standard Type of Issue'!$B$1:$C$332,2,0) -> Chargeback
A105: INCTEC1615014 | B105: 46116.728 | C105: 4 - Low | D105: Closed | E105: Self Service | F105: FALSE | G105: RACFI-RACPAD - Payment | CCCB | | H105: Customer has a charge back on the account for $131.90. Customer already paid back the charge back on 8/8/25 - see account to view receipt or see attached receipt. Please delete the chargeback off the customers account Agreement Number: 8172086454 Customer ID: 109241854 Customer Name: Maria Enriquez Date and Time Issue Was Occured: 2025-08-08 12:18:00 | I105: RACPad Support | J105: racha sahithya | K105: RACPAD - Payment | M105: PRB0045145 | O105: 00734 - RIVERSIDE-VAN BUREN - A - M0296 - R0999 - S098 - RACFI | P105: Incident-App-DataFixDeployed | Q105: We have updated the chargeback status as paid for the customer Customer ID: 109241854 Customer Name: Maria Enriquez Received confirmation email from store to close the ticket | S105: Customer | T105: Incorrect Charge back added | U105: =VLOOKUP(T105,'Standard Type of Issue'!$B$1:$C$332,2,0) -> Chargeback
A106: INCTEC1614046 | B106: 46113.959 | C106: 4 - Low | D106: Closed | E106: Email | F106: FALSE | G106: RACPAD technical issues - racpad | H106: ________________________________ From: Christian Sablaya2 <Christian.Sablaya@rentacenter.com> Sent: Thursday, April 2, 2026 3:34 AM To: RACPad Support <RACPadSupport@rentacenter.com> Cc: Christopher Don Javier <christopherdon.javier@concentrix.com>; May Antonette Perez <mayantonette.perez@concentrix.com> Subject: RACPAD technical issues Hi team, Need your assistance to check RACPAD account of one of our agent. See below screenshot error and agent details for ease of reference: Name: Dana Quilantang RAC ID: 364840 Issue: locked out Email: dana.quilantang@rentacenter.com<mailto:dana.quilantang@rentacenter.com> [cid:3bddadd4-1863-4637-a33f-3aa095f182ff] Thanks, Christian Carlo Sablaya | I106: RACPad Support | J106: Vandana K | K106: RACPAD - Store | M106: PRB0045218 | N106: CHG0050123 | O106: H0003 - - Active - FSC | P106: Incident-App-DataFixDeployed | Q106: Steps taken: Racpad access have been granted for Dana Quilantang (#364840). category: Access | S106: Store | T106: Access | U106: =VLOOKUP(T106,'Standard Type of Issue'!$B$1:$C$332,2,0) -> Store Access
A107: INCTEC1614217 | B107: 46114.51 | C107: 4 - Low | D107: Closed | E107: Phone | F107: FALSE | G107: RACFI-unable to access Racpad | H107: CW Name : Brandon Chatmon Emp ID : 356389 Store: 00719 Computer Name:00730-57678Y3 Description : unable to access Racpad | I107: RACPad Support | J107: Abhishek TV | K107: RACPAD - Store | M107: PRB0045218 | O107: 00719 - LANCASTER-AVE J - A - M0993 - R0999 - S098 - RACFI | P107: Incident-App-DataFixDeployed | Q107: Steps taken for resolution: The RACPAD access for Brandon Chatmon (EMP ID: 356389) has been restored for store #00719. Screenshot is attached for reference. Category: RACPAD access | S107: Store | T107: Access | U107: =VLOOKUP(T107,'Standard Type of Issue'!$B$1:$C$332,2,0) -> Store Access
A108: INCTEC1614238 | B108: 46114.527 | C108: 4 - Low | D108: Closed | E108: Self Service | F108: FALSE | G108: RACFI-RACPAD - Store | The application is temporarily unavailable | | H108: I'm sorry but you currently don't have the necessary permissions to access this page. Please contact an administrator if you feel this is an error. (I am receiving this message after i log in) | I108: RACPad Support | J108: Abhishek TV | K108: RACPAD - Store | M108: PRB0045218 | O108: 00719 - LANCASTER-AVE J - A - M0993 - R0999 - S098 - RACFI | P108: Incident-App-DataFixDeployed | Q108: Steps taken for resolution: The RACPAD access for Angelica Contreras (EMP ID: 358477) has been restored for store #00719. Screenshot is attached for reference. Category: RACPAD access | S108: Store | T108: Access | U108: =VLOOKUP(T108,'Standard Type of Issue'!$B$1:$C$332,2,0) -> Store Access
A109: INCTEC1614410 | B109: 46114.975 | C109: 4 - Low | D109: Closed | E109: Email | F109: FALSE | G109: Adding 2 coworkers to 939's Racpad - racpad | H109: ________________________________ From: Mark Bassett <Mark.Bassett@rentacenter.com> Sent: Friday, April 3, 2026 8:59 AM To: Jimmy Hendershot <Jimmy.Hendershot@rentacenter.com>; RACPad Support <RACPadSupport@rentacenter.com> Cc: OperationsSupport <OperationsSupport@Rentacenter.com> Subject: Re: Adding 2 coworkers to 939's Racpad Hello RP Support Please assist with this request. Thank you Mark Sent from my iPhone On Apr 2, 2026, at 6:10 PM, Jimmy Hendershot <Jimmy.Hendershot@rentacenter.com> wrote: ﻿ Good afternoon, I am looking to have 2 team members added or given access to store 939 in addition to their home stores Racpad for next week, if it's possible? Home store is: 942 Want them to have access to: 939 (From 1/4-1/11) Coworkers: * Randy Mckee 182377 * Madison Decker 364554 Thank you in advance, Jim Hendershot District Manager D265 P: 208-914-1970 E: jimmy.hendershot@rentacenter.com [Outlook-oo1mokvp.png] | I109: RACPad Support | J109: Aditi Nayak | K109: RACPAD - Account Management | M109: PRB0045218 | O109: H0003 - - Active - FSC | P109: Incident-App-DataFixDeployed | Q109: As per request, we have provided store 939 access to both CWs - Randy Mckee 182377 Madison Decker 364554 | S109: Store | T109: Access | U109: =VLOOKUP(T109,'Standard Type of Issue'!$B$1:$C$332,2,0) -> Store Access
A110: INCTEC1614939 | B110: 46116.539 | C110: 4 - Low | D110: Closed | E110: Phone | F110: FALSE | G110: RACPAD- | H110: Store number: 03975 Coworker name and ID: Ignacio Armas || 161224 Computer name: 00582-1X7BV93 Issue description: No Store visible in RACPAD Steps taken to arrive at problem: RACPAD | I110: RACPad Support | J110: Pratik Singar | K110: RACPAD - Store | M110: PRB0045218 | O110: 03975 - ORLANDO-OLD WINTER GARDEN - I - M0132 - R0024 - S08 - RACUSA | P110: Common-DuplicateRecord | Q110: Working on same user access issue through duplicate incident INCTEC1614499. Hence resolving incident. | S110: Store | T110: Access | U110: =VLOOKUP(T110,'Standard Type of Issue'!$B$1:$C$332,2,0) -> Store Access
A111: INCTEC1615333 | B111: 46118.418 | C111: 4 - Low | D111: Closed | E111: Phone | F111: FALSE | G111: RACPAD store issue | H111: Co-worker name: Paris Hampton Employee ID: 124938 Store: 03770 Issue: CW called and mentioned need to update store in RACPAD. Current Store number is 03770. | I111: RACPad Support | J111: Prasanth K | K111: RACPAD - Store | M111: PRB0045218 | N111: CHG0051285 | O111: 01706 - ST.LOUIS-BRECH HILLS - A - M0538 - R0039 - S07 - RACUSA | P111: Incident-App-DataFixDeployed | Q111: we have provided the store-03770 access to employee-124938 ,pls follow the attached image for reference | S111: Store | T111: Access | U111: =VLOOKUP(T111,'Standard Type of Issue'!$B$1:$C$332,2,0) -> Store Access
A112: INCTEC1615359 | B112: 46118.445 | C112: 4 - Low | D112: Closed | E112: Phone | F112: FALSE | G112: RACFI-RACPad Showing Incorrect Store – Update Required from 07079 to 07226 | H112: Issue: CW reported that in RACPad, his old store (07079) is still showing, but it needs to be updated to his new store (07226). Employee Name: Troy DeVore Employee ID: 311521 Current Store Showing: 07079 | I112: RACPad Support | J112: Prasanth K | K112: RACPAD - Store | M112: PRB0045218 | N112: CHG0051285 | O112: 07079 - - A - M7009 - R0708 - S712 - RACFI | P112: Incident-App-DataFixDeployed | Q112: we have provided the store-07226 access to employee-311521 pls follow the attached image for reference | S112: Store | T112: Access | U112: =VLOOKUP(T112,'Standard Type of Issue'!$B$1:$C$332,2,0) -> Store Access
A113: INCTEC1615370 | B113: 46118.456 | C113: 4 - Low | D113: Closed | E113: Email | F113: FALSE | G113: RACFI-unable to access Racpad | H113: From: Joe Baum <Joe.Baum@rentacenter.com> Sent: Monday, April 6, 2026 10:44 AM To: Colby Rocker <Colby.Rocker@rentacenter.com> Subject: Employee log in 1920 Good morning, sir, I have employee Dale stocks employee ID 101399. When he logs in, he's assigned to 03828 and I need him to be assigned to me at 01920 if you could please roll up to the correct corresponding party. Thank you! Joseph Baum Store 01920 (315)491-5917 "If you're not on the way, you're in the way" | I113: RACPad Support | J113: monisha d | K113: RACPAD - Store | M113: PRB0045218 | O113: M0444 - - M0444 - R0002 - S07 - RTO | P113: Request-Fulfilled | Q113: The access is already present for the user for the store 01920. hence resolving the incident. | S113: Store | T113: Access | U113: =VLOOKUP(T113,'Standard Type of Issue'!$B$1:$C$332,2,0) -> Store Access
A114: INCTEC1615373 | B114: 46118.459 | C114: 4 - Low | D114: Closed | E114: Phone | F114: FALSE | G114: RACPAD Store issue | H114: Co-worker name: Melissa Plaska Employee Name: 115519 Store: 01694 Issue: CW called and mentioned her manager raised temporary access for Store 04350. but that should be valid till coming Saturday. But her access is not working for store 04350. | I114: RACPad Support | J114: Abhishek TV | K114: RACPAD - Store | M114: PRB0045218 | O114: 01694 - WYOMING(TS) - A - M0118 - R0020 - S08 - RACUSA | P114: Incident-App-DataFixDeployed | Q114: Steps taken for resolution: Melissa Plaska (EMP ID: 115519) has been granted with temporary access for store #04350 as requested. The temporary access will end on 04/13/2026. Screenshot is attached for reference. Category: RACPAD Temporary access | S114: Store | T114: Access | U114: =VLOOKUP(T114,'Standard Type of Issue'!$B$1:$C$332,2,0) -> Store Access
A115: INCTEC1615618 | B115: 46118.909 | C115: 4 - Low | D115: Closed | E115: Email | F115: FALSE | G115: RACPAD access - no stores - Racpad | H115: From: Mike Tesdahl <Mike.Tesdahl@Rentacenter.com> Sent: Tuesday, April 7, 2026 2:53 AM To: INFOSYS RACPAD SUPPORT <INFOSYS_RACPADSUPPORT@upbound.com> Subject: RACPAD access - no stores Hello, I hope you're doing well. I wanted to reach out regarding an issue both my analyst Priya Bandi and I are experiencing with Racpad access. When we log in, we see "No Stores" in the upper right corner, which prevents us from searching for agreements and performing data validation tasks necessary for our work in the data analytics department. Priya is also receiving the error message below in addition to the "No Stores" notification. [cid:image001.png@01DCC5E1.AF88BDC0] Could you please advise us on the correct process to resolve this? If submitting a ticket is the best approach, I'd appreciate guidance on which role we currently hold or which role we should request to ensure we can search and view agreements, payments, and customer information. Both Priya and I need the same access for our analysis and validation responsibilities. Thank you very much for your help. Mike Tesdahl Senior Manager - Data Analytics Rent-A-Center, Inc. (972) 801-1457 Mike.Tesdahl@Rentacenter.com<mailto:Mike.Tesdahl@Rentacenter.com> | I115: RACPad Support | J115: Tasneem Firdose | K115: RACPAD - Store | M115: PRB0045218 | O115: H0003 - - Active - FSC | P115: Incident-App-DataFixDeployed | Q115: Provided operational tab access to Priya Bandi (343802) and Mike Tesdahl (126022) by mirroring Jerry Salazar (163395). Received confirmation mail as well. Please refer attachment. Hence resolving this incident. | S115: Store | T115: Access | U115: =VLOOKUP(T115,'Standard Type of Issue'!$B$1:$C$332,2,0) -> Store Access
A116: INCTEC1616671 | B116: 46121.604 | C116: 4 - Low | D116: Closed | E116: Email | F116: FALSE | G116: Operations Tab access-RACPAD | H116: Thanks, Siva Bhargavi RACPad Production Support +1 6605413327 [Shape Description automatically generated with medium confidence] From: Jerry Salazar <Jerry.Salazar2@rentacenter.com> Sent: Thursday, April 9, 2026 2:10 PM To: RACPad Support <RACPadSupport@rentacenter.com> Subject: Operations Tab access Good afternoon Team Could we please grant access to the Operations Tab in RACPad to Letty Olvera Letty.Olvera@Rentacenter.com<mailto:Letty.Olvera@Rentacenter.com>. (233486) Also, the RACPad access that Adam Vass currently has, could we change it to mirror the access I have (Jerry Salazar 163395) Thank you Jerry Salazar – Manager | Operational Improvements Rent-A-Center | 5501 Headquarters Dr. | Plano, Texas 75024, USA ▬▬▬▬▬▬▬▬▬▬▬▬▬▬▬▬▬▬▬▬▬▬▬▬▬▬▬▬▬▬▬▬▬▬▬▬▬▬▬▬▬▬▬▬▬▬▬▬▬▬▬▬▬▬▬▬▬▬▬▬▬▬▬▬▬▬▬▬▬▬▬▬▬▬▬▬▬▬▬▬▬▬▬▬▬▬▬▬▬▬▬▬▬▬▬▬▬▬▬▬▬▬▬▬▬▬▬ Email: jerry.salazar2@rentacenter.com<mailto:craig.joyner@rentacenter.com> Phone: 972-801-3195 [cid:image001.png@01DCC82A.94487370] | I116: RACPad Support | J116: Pratik Singar | K116: RACPAD - other | M116: PRB0045218 | O116: H0003 - - Active - FSC | P116: Incident-App-DataFixDeployed | Q116: Provided role access (CAM, FSC-RDT, RD ) to user Adam Vass (304526), reflected in RACPAD application. Received confirmation mail as well. Please refer attachment. Hence resolving incident. | S116: Store | T116: Access | U116: =VLOOKUP(T116,'Standard Type of Issue'!$B$1:$C$332,2,0) -> Store Access
A117: INCTEC1617737 | B117: 46125.596 | C117: 4 - Low | D117: Closed | E117: Phone | F117: FALSE | G117: RACPAD TEMP ACCESS | H117: RACPAD TEMP ROLE & STORE ACCESS -Jocelyn Muffley as store manager for store 04598 Who is making the request? (person on the phone): Carlos Crissien Role's Start Date: 04/13/2026 Role's End Date (cannot exceed seven [7] days): 04/19/2026 Coworker Who Needs Role Change Name: Jocelyn Muffley Coworker Who Needs Role Change EID: 103375 Coworker Current Position: Store Manager - In Training Coworker Requested Position: Store Manager Store #: 04598 District #: M0186 Was verbal approval given by the appropriately-authorized person? <Yes> • If yes, provide their first and last name: Carlos Crissien | I117: RACPad Support | J117: Abhishek TV | K117: RACPAD - Store | M117: PRB0045218 | O117: M0186 - N/A - M0186 - R0065 - S08 - RTO | P117: Incident-App-DataFixDeployed | Q117: Steps taken for resolution: Temporary RACPAD access granted for Jocelyn Muffley as Store manager for store 04598 as requested. Screenshot is attached for reference. Category: RACPAD temporary access | S117: Store | T117: Access | U117: =VLOOKUP(T117,'Standard Type of Issue'!$B$1:$C$332,2,0) -> Store Access
A118: INCTEC1618692 | B118: 46128.234 | C118: 4 - Low | D118: Closed | E118: Email | F118: FALSE | G118: REQUEST: Salesforce App & Salesforce Sandbox for CWS Wave 8-RACPAD | H118: From: Shree Narayanaswamy <Shree.Narayanaswamy@upbound.com> Sent: Wednesday, April 15, 2026 6:14 PM To: Celestiene Judeo Gopez <celestienejudeo.gopez@concentrix.com>; Parvesh Mohamed <Parvesh.Mohamed@upbound.com>; Portal Support <portalsupport@rentacenter.com>; Charles Clements <charles.clements@rentacenter.com>; Briana Coffman <briana.coffman@rentacenter.com>; Chris Spott <chris.spott@rentacenter.com>; May Antonette Perez <mayantonette.perez@concentrix.com>; RACPad Support <RACPadSupport@rentacenter.com> Cc: UpboundTQ <PH_QUE_UPAC_upboundtq@concentrix.com> Subject: Re: REQUEST: Salesforce App & Salesforce Sandbox for CWS Wave 8 Hi @RACPad<mailto:RACPadSupport@rentacenter.com> Team, I have checked the DM access in the RACPAD application for the users listed below. Could you please review and assign the appropriate role to the users? Full Name RAC Email Pecenio, Julius Clement Bertos Julius.Pecenio@rentacenter.com<mailto:Julius.Pecenio@rentacenter.com> Mendes, Jesalyn Hantud Jesalyn.Mendez@rentacenter.com<mailto:Jesalyn.Mendez@rentacenter.com> Thanks, Shree Narayanaswamy ________________________________ From: Celestiene Judeo Gopez <celestienejudeo.gopez@concentrix.com<mailto:celestienejudeo.gopez@concentrix.com>> Sent: Wednesday, April 15, 2026 5:55 PM To: Shree Narayanaswamy <Shree.Narayanaswamy@upbound.com<mailto:Shree.Narayanaswamy@upbound.com>>; Parvesh Mohamed <Parvesh.Mohamed@upbound.com<mailto:Parvesh.Mohamed@upbound.com>>; Portal Support <portalsupport@rentacenter.com<mailto:portalsupport@rentacenter.com>>; Charles Clements <charles.clements@rentacenter.com<mailto:charles.clements@rentacenter.com>>; Briana Coffman <briana.coffman@rentacenter.com<mailto:briana.coffman@rentacenter.com>>; Chris Spott <chris.spott@rentacenter.com<mailto:chris.spott@rentacenter.com>>; May Antonette Perez <mayantonette.perez@concentrix.com<mailto:mayantonette.perez@concentrix.com>> Cc: UpboundTQ <PH_QUE_UPAC_upboundtq@concentrix.com<mailto:PH_QUE_UPAC_upboundtq@concentrix.com>> Subject: Re: REQUEST: Salesforce App & Salesforce Sandbox for CWS Wave 8 BE ALERT: The sender of this email is outside of Upbound Group, Inc. Please ensure you recognize the sender prior to clicking on any links or opening attachments. If in doubt, use the Report 'Junk' or 'Phishing' buttons located on your outlook toolbar to report it. Hi @Portal Support<mailto:portalsupport@rentacenter.com> & @Shree Narayanaswamy<mailto:Shree.Narayanaswamy@upbound.com>, Following up this request. Agents below still doesn't have DM access in RACPAD. Thanks Full Name RAC Email Pecenio, Julius Clement Bertos Julius.Pecenio@rentacenter.com<mailto:Julius.Pecenio@rentacenter.com> Mendes, Jesalyn Hantud Jesalyn.Mendez@rentacenter.com<mailto:Jesalyn.Mendez@rentacenter.com> ________________________________ From: Celestiene Judeo Gopez <celestienejudeo.gopez@concentrix.com<mailto:celestienejudeo.gopez@concentrix.com>> Sent: Monday, April 13, 2026 11:04 PM To: Shree Narayanaswamy <Shree.Narayanaswamy@upbound.com<mailto:Shree.Narayanaswamy@upbound.com>>; Parvesh Mohamed <Parvesh.Mohamed@upbound.com<mailto:Parvesh.Mohamed@upbound.com>>; Portal Support <portalsupport@rentacenter.com<mailto:portalsupport@rentacenter.com>>; Charles Clements <charles.clements@rentacenter.com<mailto:charles.clements@rentacenter.com>>; Briana Coffman <briana.coffman@rentacenter.com<mailto:briana.coffman@rentacenter.com>>; Chris Spott <chris.spott@rentacenter.com<mailto:chris.spott@rentacenter.com>>; May Antonette Perez <mayantonette.perez@concentrix.com<mailto:mayantonette.perez@concentrix.com>> Cc: UpboundTQ <PH_QUE_UPAC_upboundtq@concentrix.com<mailto:PH_QUE_UPAC_upboundtq@concentrix.com>> Subject: Re: REQUEST: Salesforce App & Salesforce Sandbox for CWS Wave 8 Hi @Shree Narayanaswamy<mailto:Shree.Narayanaswamy@upbound.com>, I still have 3 agents that doesn't have RACPAD DM access, please see list below. Thanks. Full Name RAC Email Pecenio, Julius Clement Bertos Julius.Pecenio@rentacenter.com<mailto:Julius.Pecenio@rentacenter.com> Mendes, Jesalyn Hantud Jesalyn.Mendez@rentacenter.com<mailto:Jesalyn.Mendez@rentacenter.com> Agustin, Laurence Dela Cruz Laurence.Agustin@rentacenter.com<mailto:Laurence.Agustin@rentacenter.com> ________________________________ From: Shree Narayanaswamy <Shree.Narayanaswamy@upbound.com<mailto:Shree.Narayanaswamy@upbound.com>> Sent: Friday, April 10, 2026 10:15 PM To: Parvesh Mohamed <Parvesh.Mohamed@upbound.com<mailto:Parvesh.Mohamed@upbound.com>>; Portal Support <portalsupport@rentacenter.com<mailto:portalsupport@rentacenter.com>>; Celestiene Judeo Gopez <celestienejudeo.gopez@concentrix.com<mailto:celestienejudeo.gopez@concentrix.com>>; Charles Clements <charles.clements@rentacenter.com<mailto:charles.clements@rentacenter.com>>; Briana Coffman <briana.coffman@rentacenter.com<mailto:briana.coffman@rentacenter.com>>; Chris Spott <chris.spott@rentacenter.com<mailto:chris.spott@rentacenter.com>>; May Antonette Perez <mayantonette.perez@concentrix.com<mailto:mayantonette.perez@concentrix.com>> Cc: UpboundTQ <PH_QUE_UPAC_upboundtq@concentrix.com<mailto:PH_QUE_UPAC_upboundtq@concentrix.com>> Subject: Re: REQUEST: Salesforce App & Salesforce Sandbox for CWS Wave 8 PLEASE BE CAUTIOUS, EXTERNAL EMAIL: This email originated from outside of the organization. Do not click links or open attachments unless you recognize the sender and know the content is safe. Report this email, if suspicious by clicking on "Report Phishing" button available within Outlook for Desktop, Web or Mobile. In case reporting button is not available, please report it to ‘report.phish@concentrix.com’. Hi @Portal Support<mailto:portalsupport@rentacenter.com>, I have provided access to the following applications for the specified users: *Salesforce application *Salesforce Sandbox *EMILY App *RACPAD DM access Thanks, Shree Narayanaswamy ________________________________ From: Parvesh Mohamed <Parvesh.Mohamed@upbound.com<mailto:Parvesh.Mohamed@upbound.com>> Sent: Friday, April 10, 2026 7:12 PM To: Portal Support <portalsupport@rentacenter.com<mailto:portalsupport@rentacenter.com>>; Celestiene Judeo Gopez <celestienejudeo.gopez@concentrix.com<mailto:celestienejudeo.gopez@concentrix.com>>; Charles Clements <charles.clements@rentacenter.com<mailto:charles.clements@rentacenter.com>>; Briana Coffman <briana.coffman@rentacenter.com<mailto:briana.coffman@rentacenter.com>>; Chris Spott <chris.spott@rentacenter.com<mailto:chris.spott@rentacenter.com>>; May Antonette Perez <mayantonette.perez@concentrix.com<mailto:mayantonette.perez@concentrix.com>>; Shree Narayanaswamy <Shree.Narayanaswamy@upbound.com<mailto:Shree.Narayanaswamy@upbound.com>> Cc: UpboundTQ <PH_QUE_UPAC_upboundtq@concentrix.com<mailto:PH_QUE_UPAC_upboundtq@concentrix.com>> Subject: Re: REQUEST: Salesforce App & Salesforce Sandbox for CWS Wave 8 Hi @Shree Narayanaswamy<mailto:Shree.Narayanaswamy@upbound.com>, Could you please check and assist with this request? Thanks, Parvesh Mohamed ________________________________ From: Portal Support <portalsupport@rentacenter.com<mailto:portalsupport@rentacenter.com>> Sent: Friday, April 10, 2026 00:03 To: Celestiene Judeo Gopez <celestienejudeo.gopez@concentrix.com<mailto:celestienejudeo.gopez@concentrix.com>>; Charles Clements <charles.clements@rentacenter.com<mailto:charles.clements@rentacenter.com>>; Briana Coffman <briana.coffman@rentacenter.com<mailto:briana.coffman@rentacenter.com>>; Chris Spott <chris.spott@rentacenter.com<mailto:chris.spott@rentacenter.com>>; May Antonette Perez <mayantonette.perez@concentrix.com<mailto:mayantonette.perez@concentrix.com>>; Parvesh Mohamed <Parvesh.Mohamed@upbound.com<mailto:Parvesh.Mohamed@upbound.com>> Cc: UpboundTQ <PH_QUE_UPAC_upboundtq@concentrix.com<mailto:PH_QUE_UPAC_upboundtq@concentrix.com>> Subject: Re: REQUEST: Salesforce App & Salesforce Sandbox for CWS Wave 8 Hi @Parvesh Mohamed, Could you please help to provide the SF access for the below users in Entra? The users are added in the Salesforce Sandbox. Thanks! Atul ________________________________ From: Celestiene Judeo Gopez <celestienejudeo.gopez@concentrix.com<mailto:celestienejudeo.gopez@concentrix.com>> Sent: Thursday, April 9, 2026 7:15 AM To: Portal Support <portalsupport@rentacenter.com<mailto:portalsupport@rentacenter.com>>; Charles Clements <charles.clements@rentacenter.com<mailto:charles.clements@rentacenter.com>>; Briana Coffman <briana.coffman@rentacenter.com<mailto:briana.coffman@rentacenter.com>>; Chris Spott <chris.spott@rentacenter.com<mailto:chris.spott@rentacenter.com>>; May Antonette Perez <mayantonette.perez@concentrix.com<mailto:mayantonette.perez@concentrix.com>> Cc: UpboundTQ <PH_QUE_UPAC_upboundtq@concentrix.com<mailto:PH_QUE_UPAC_upboundtq@concentrix.com>> Subject: REQUEST: Salesforce App & Salesforce Sandbox for CWS Wave 8 BE ALERT: The sender of this email is outside of Upbound Group, Inc. Please ensure you recognize the sender prior to clicking on any links or opening attachments. If in doubt, use the Report 'Junk' or 'Phishing' buttons located on your outlook toolbar to report it. Hi @Portal Support<mailto:portalsupport@rentacenter.com>, Need help for the agents below to have access to the following tools; *Salesforce application *Salesforce Sandbox *EMILY App *RACPAD DM access You can use this email ID Berna.Campo@rentacenter.com<mailto:Berna.Campo@rentacenter.com> to o Mirror all CWS access for the agents below. Thank you! Full Name RAC Email Pecenio, Julius Clement Bertos Julius.Pecenio@rentacenter.com<mailto:Julius.Pecenio@rentacenter.com> Tan, Orville Andrei Mesana Orville.Tan@rentacenter.com<mailto:Orville.Tan@rentacenter.com> Ramirez, Eden Grace Baltazar Eden.Ramirez@rentacenter.com<mailto:Eden.Ramirez@rentacenter.com> Plana, Chirry Cris Abratiguin Chirry.Plana@rentacenter.com<mailto:Chirry.Plana@rentacenter.com> Catapang, Juliana Andre Cariño Juliana.Catapang@rentacenter.com<mailto:Juliana.Catapang@rentacenter.com> Mendes, Jesalyn Hantud Jesalyn.Mendez@rentacenter.com<mailto:Jesalyn.Mendez@rentacenter.com> Besweng, Engrid Rimando Engrid.Besweng@rentacenter.com<mailto:Engrid.Besweng@rentacenter.com> Benitez, Kent Bryan Ambos Kent.Benitez@rentacenter.com<mailto:Kent.Benitez@rentacenter.com> Macaraig, Al Baldovino Al.Macaraig@rentacenter.com<mailto:Al.Macaraig@rentacenter.com> Agustin, Laurence Dela Cruz Laurence.Agustin@rentacenter.com<mailto:Laurence.Agustin@rentacenter.com> Regards, CJ Celestiene Judeo Gopez | Trainer II [cid:2afedbc4-1a83-414e-9eee-da1975aca6d2][cid:3e367e57-d1d0-4d61-b581-c73dc5a418e9][cid:04f35b4c-bdc2-4433-b140-8be125ac126d] UP Ayala Land TechnoHub, Building F, 2nd FL Quezon City 1121 National Capital Region (Manila) Philippines m: 0969-506-8521 | e: celestienejudeo.gopez@concentrix.com<mailto:celestienejudeo.gopez@concentrix.com> | I118: RACPad Support | J118: monisha d | K118: RACPAD - Store | M118: PRB0045218 | O118: H0003 - - Active - FSC | P118: Incident-App-DataFixDeployed | Q118: As per the request the racpad application access is provide to the users hence resolving this incident. Incident INCTEC1618692 closed based on closure of CHG0051445. | S118: Store | T118: Access | U118: =VLOOKUP(T118,'Standard Type of Issue'!$B$1:$C$332,2,0) -> Store Access
A119: INCTEC1619402 | B119: 46129.548 | C119: 4 - Low | D119: Closed | E119: Phone | F119: FALSE | G119: Racpad - not able to access | H119: Name :Teresa HayesTurner Eid : 21567 Issue : Racpad - not able to access | I119: RACPad Support | J119: Prasanth K | K119: RACPAD - Store | M119: PRB0045218 | N119: CHG0051456 | O119: 00676 - JOLIET-JEFFERSON - A - M0299 - R0039 - S07 - RACUSA | P119: Incident-App-DataFixDeployed | Q119: Store-00676 access has been provided to the employee-21567, pls follow the attached image for reference | S119: Store | T119: Access | U119: =VLOOKUP(T119,'Standard Type of Issue'!$B$1:$C$332,2,0) -> Store Access
...

Sheet Updated Issue wise details_Std
A3: Row Labels | B3: Count of Number
A4: BigPanda | B4: 483
A5: Others - Misc | B5: 141
A6: Customer Login Issue (EXT) | B6: 100 | E6: Amith - Roopesh
A7: Store Access | B7: 97 | D7: 1: Access request - how many SR are created for access 2: Can it be shift left or automated 3: Categories in access request | E7: Nagaraj
A8: Payment reversal | B8: 66 | D8: Categories in Payment reversal | E8: Proc is having issue, due to which automation is on hold | F8: QA Team
A9: Payment Query | B9: 60 | D9: Categories in Payment query | E9: Nikhil/Ashwin
A10: AutoPay | B10: 51 | D10: Will be discussed tomorrow Trailblazer call | E10: Prashanth
A11: Switch Out Issue | B11: 49 | D11: NA
A12: Unable to confirm delivery | B12: 49 | D12: Discussed in Trailblazer call - followup to be done with Seema | E12: Fixed
A13: Payment Error | B13: 38 | D13: NA
A14: Daily task | B14: 38 | D14: Inventory rental Stats overshot cash/non-cash Bad display | E14: If these are SOP based, can we look for automating them
A15: Monitoring | B15: 36 | D15: Threshold revisit and change the monitoring process for INC creation
A16: Cancel the Manual PO | B16: 36 | D16: Automation done through self service portal | E16: Nagaraj
A17: Cancel the RMS PO | B17: 32 | D17: Data fix done for Old RMS POs
A18: Unable to receive the Purchase order | B18: 30 | D18: Single scenario with workaround - done through data fix for now | E18: Nagaraj
A19: Customer Issue | B19: 29 | D19: For any pattern, can we look to create a SOP | E19: Prashanth
A20: 2 way sync | B20: 26 | D20: RCA is progress - will be taken up for automation | E20: Nagaraj
A21: Agreement Issue | B21: 24 | D21: NA
A22: Inventory Issue | B22: 23 | D22: NA
A23: Agreement Void Issue | B23: 20 | D23: NA
A24: DQ-Agreement | B24: 20 | D24: sync DQ automation is already in Place which executed on daily basis | E24: Nagaraj
A25: Account Report Request | B25: 18 | D25: Mostly email request, so team can create SR instead of INC. another option to automate end to end using Business user form | E25: Muneer
A26: Training Issue | B26: 17 | D26: PRB Resolved
A27: Inventory Status Issue | B27: 16
A28: Report discrepency | B28: 15
A29: Agreement Creation Issue | B29: 15
A30: Duplicate ticket | B30: 14
A31: PIN reset | B31: 14 | D31: Enhancement - Already discussed with Seema and dropped email
A32: DQ-Inventory | B32: 9
A33: One Time Issue | B33: 9
A34: Agreement Status | B34: 8
A35: Drop reconciliation | B35: 8
A36: Agreement Transfer Issue | B36: 7
A37: Query | B37: 7
A38: Pricing request | B38: 7
A39: Payment issue | B39: 7
A40: Pricing Issue | B40: 7
A41: Chargeback | B41: 6
A42: Duplicate customers record | B42: 6
A43: Confirm delivery Issue | B43: 6
... A69: Grand Total | B69: 1724

Sheet Issue wise details_old
A1: Team | B1: Type Of Issue | C1: No of Incidents reported | D1: Problem | E1: Remarks | F1: Module
A2: App Support | B2: BigPanda | C2: 483
A3: App Support/DS | B3: Unable to link the agreement(Due to login issue -most are EXT tickets) | C3: 94 | D3: PRB0044676
A4: App Support | B4: Access | C4: 75 | D4: PRB0045218 | F4: Access
A5: App Support | B5: Payment reversal | C5: 58 | D5: PRB0044395 | F5: Payment
A6: App Support | B6: AutoPay | C6: 51 | D6: PRB0046103
A7: App Support | B7: Unable to confirm delivery | C7: 49 | D7: PRB0044979 | F7: Delivery
A8: App Support | B8: Payment not reflecting in RACPAD | C8: 45 | F8: Payment
A9: App Support | B9: Agreement switch-out completed, but inventory remains in "Pending Switch Out" status | C9: 44 | D9: PRB0045906 | F9: Inventory
A10: Data Services | B10: Monitoring | C10: 36
A11: App Support | B11: Cancel the Manual PO | C11: 34 | D11: PRB0045846 | F11: PO Related
A12: App Support | B12: Cancel the RMS PO | C12: 32 | D12: PRB0045373 | F12: PO Related
A13: App Support | B13: Unable to receive the Purchase order | C13: 30 | D13: PRB0046203
A14: Data Services | B14: Daily Task | C14: 29
A15: Data Services | B15: Active Agreement Mismatch | C15: 20
A16: App Support | B16: User having access to old stores in RACPAD | C16: 19 | D16: PRB0046072 | F16: Access
A17: App Support | B17: Amount Mismatch Error on Initial Payment for Customer Order Agreement | C17: 18 | D17: PRB0045088 | F17: Payment
A18: Data Services | B18: 2 way sync | C18: 18
A19: App Support | B19: Level 1 loyalty customer unable to add phone | C19: 17 | D19: PRB0046289 | F19: Add Phone
A20: App Support | B20: Report discrepency | C20: 15 | D20: PRB0044727 | F20: Report
A21: App Support | B21: Duplicate ticket | C21: 14
A22: App Support | B22: PIN Reset | C22: 14 | E22: 5/13: Enhancment request sent - Seema/Divya
A23: App Support | B23: The CW is unable to void the agreements because the Customer Order feature is currently disabled for eclipse RTO Stores. | C23: 12 | D23: PRB0046139
A24: App Support | B24: Generating detailed account report on rental agreements | C24: 11 | D24: PRB0045462 | F24: Report
A25: App Support | B25: Unable to create an agreement | C25: 11 | E25: No issues observed for all the logged incidents
A26: Data Services | B26: Active Inventory Mismatch | C26: 9 | F26: Inventory
A27: App Support | B27: The overridden other charge in the initial payment section is automatically reapplied after completing the agreement | C27: 8 | D27: PRB0046248 | F27: Payment
A28: Data Services | B28: CREATE-INVENTORY-ACTIVITY-LOG | C28: 8 | F28: Inventory
A29: App Support | B29: Unable to proceed with payment | C29: 7 | E29: No issues observed for all the logged incidents | F29: Payment
A30: App Support | B30: Unable to submit Inventory | C30: 7 | E30: No issues observed for all the logged incidents | F30: Inventory
A31: Data Services | B31: Overshort Cash | C31: 7
A32: App Support | B32: Rate Retention for agreements is happening incorrectly. | C32: 6 | D32: PRB0045802
A33: App Support | B33: Duplicate customers record | C33: 6 | D33: PRB0046275
A34: Data Services | B34: Inventory Mismatch | C34: 6 | F34: Inventory
A35: Data Services | B35: Account Report | C35: 6 | F35: Report
A36: App Support | B36: Unable to transfer the agreement | C36: 5 | D36: PRB0045498
A37: App Support | B37: The EPO amount is incorrectly calculated as 0 after the SAC period ends. | C37: 5 | D37: PRB0046266 | F37: PO Related
A38: App Support | B38: Customer charged multiple time | C38: 5
A39: App Support | B39: Customer has not received refund | C39: 5 | F39: Refund
A40: App Support | B40: Unable to void the agreement | C40: 5
A41: App Support | B41: Unable to fetch the data error | C41: 4 | D41: PRB0046080
A42: App Support | B42: Customer address information fields are interchanged when updating address details in RACPAD. | C42: 4 | D42: PRB0046256
A43: App Support | B43: Item not showing up | C43: 4 | D43: PRB0046316
A44: App Support | B44: Issue with inventory status | C44: 4 | D44: PRB0046340 | F44: Inventory
A45: App Support | B45: CUstomer level change request | C45: 4
A46: App Support | B46: Issue with RAC exchange | C46: 4
A47: Data Services | B47: Receipt Mismatch | C47: 4
A48: Data Services | B48: Customer Mismatch | C48: 4
A49: App Support | B49: Payment query | C49: 3 | F49: Payment
A50: App Support | B50: Cannot search customer by name | C50: 3 | D50: PRB0044564
A51: App Support | B51: Unable to update Income Information | C51: 3 | D51: PRB0045695
A52: App Support | B52: Update the agreement status as charged off | C52: 3 | D52: PRB0045894
A53: App Support | B53: Receipt reversal for charged‑off inventory is not nullifying the charge‑off date, causing duplicate charge‑offs. | C53: 3 | D53: PRB0046041 | F53: Receipt Reversal
A54: App Support | B54: Unable to change the inventory status | C54: 3 | D54: PRB0046171 | F54: Inventory
A55: App Support | B55: Agreement showing incorrect Same‑As‑Cash (SAC) date. | C55: 3 | D55: PRB0046258
A56: App Support | B56: Drop Reconciliation discrepancy caused by incorrect manual cash entry. | C56: 3 | D56: PRB0046262
A57: App Support | B57: EPO payment incorrectly processed as rental payment, leaving agreement open and customer marked past due. | C57: 3 | D57: PRB0046265 | F57: Payment
A58: App Support | B58: Inventory tagged to an active agreement is incorrectly showing as Rent Ready instead of On Rent. | C58: 3 | D58: PRB0046279 | F58: Inventory
A59: App Support | B59: Agreement price shows more | C59: 3 | D59: PRB0046294 | F59: Price
A60: App Support | B60: Error in RmsReserveOrderService | C60: 3
A61: App Support | B61: Update the rate and term request | C61: 3
A62: App Support | B62: Increase in payment amount | C62: 3 | F62: Payment
A63: App Support | B63: Publish the pricing | C63: 3 | F63: Price
A64: App Support | B64: Inventory Audit issue | C64: 3 | F64: Inventory
A65: App Support | B65: Unable to reverse PO | C65: 3 | F65: PO Related
A66: App Support | B66: DE shows declined | C66: 3
A67: App Support | B67: Unable to chargeoff account using the suspense amount. | C67: 3
A68: App Support | B68: Store action item is showing pending delivery confirmation even for the return appointment | C68: 2 | D68: PRB0044671 | F68: Delivery
A69: App Support | B69: Incorrect Charge back added | C69: 2 | D69: PRB0045145
A70: App Support | B70: Remove the reference | C70: 2 | D70: PRB0045246
A71: App Support | B71: LDW Cancellation Issue with manually received tires. | C71: 2 | D71: PRB0045449
A72: App Support | B72: Incorrect amount due | C72: 2 | D72: PRB0045572
A73: App Support | B73: Negative TRTO and SAC after multiple term reductions | C73: 2 | D73: PRB0045840
A74: App Support | B74: Chargeback request | C74: 2 | D74: PRB0046124
A75: App Support | B75: Remove the item from service | C75: 2 | D75: PRB0046136
A76: App Support | B76: Referral reward issue | C76: 2 | D76: PRB0046177
A77: App Support | B77: Processing fee override fails when promo code is applied | C77: 2 | D77: PRB0046248
A78: App Support | B78: LDW tax getting added eventhough LDW is 0 | C78: 2 | D78: PRB0046296
A79: App Support | B79: Documents are disappearing after being uploaded in the Residence and Income page of the customer profile. | C79: 2 | D79: PRB0046314
A80: App Support | B80: Add the item back to inventory | C80: 2 | D80: PRB0046329 | F80: Inventory
A81: App Support | B81: Void the agreement as store is getting closed | C81: 2 | D81: PRB0046335
A82: App Support | B82: Screen not loading | C82: 2
A83: App Support | B83: Add missing CW to salesperson dropdown | C83: 2
A84: App Support | B84: Uploaded documents missing | C84: 2
A85: App Support | B85: Unable to perform drop reconciliation | C85: 2
A86: App Support | B86: Customer address and phone have changed | C86: 2 | F86: Add Phone
A87: App Support | B87: Payment getting refunded | C87: 2 | F87: Payment
A88: App Support | B88: Query | C88: 2
A89: App Support | B89: Incorrect sales tax | C89: 2
A90: App Support | B90: Transfer club account to different store | C90: 2
A91: App Support | B91: Query on amount calculation | C91: 2
A92: App Support | B92: Customer showing in past due incorrectly | C92: 2
A93: App Support | B93: Inventory scanning issue | C93: 2 | F93: Inventory
A94: App Support | B94: Unable to process customer Refund | C94: 2 | F94: Refund
A95: App Support | B95: cannot complete agreement | C95: 2
A96: App Support | B96: Unable to send text messages | C96: 2
A97: App Support | B97: Card Payment Failure | C97: 2 | F97: Payment
A98: App Support | B98: Incorrect due date | C98: 2
A99: App Support | B99: Trying to active the special order for a customer but getting error as Transaction has been failed. | C99: 2
A100: App Support | B100: Level 1 customer unable to add phone | C100: 2 | F100: Add Phone
...

Sheet Standard Type of Issue
B1: Type Of Issue | C1: Std Type of Issue
A2: 1 | B2: BigPanda | C2: BigPanda
A3: 2 | B3: Unable to link the agreement | C3: Customer Login Issue (EXT)
B4: Login issue | C4: Customer Login Issue (EXT)
A5: 3 | B5: Access | C5: Store Access
A6: 4 | B6: Payment reversal | C6: Payment reversal
A7: 5 | B7: AutoPay | C7: AutoPay
B8: Autopay | C8: AutoPay
A9: 6 | B9: Unable to confirm delivery | C9: Unable to confirm delivery
A10: 7 | B10: Payment not reflecting in RACPAD | C10: Payment Query
A11: 8 | B11: Agreement switch-out completed, but inventory remains in "Pending Switch Out" status | C11: Switch Out Issue
A12: 9 | B12: Monitoring | C12: Monitoring
A13: 10 | B13: Cancel the Manual PO | C13: Cancel the Manual PO
A14: 11 | B14: Cancel the RMS PO | C14: Cancel the RMS PO
A15: 12 | B15: Unable to receive the Purchase order | C15: Unable to receive the Purchase order
A16: 13 | B16: Daily Task | C16: Daily task
A17: 14 | B17: Active Agreement Mismatch | C17: DQ-Agreement
A18: 15 | B18: User having access to old stores in RACPAD | C18: Store Access
A19: 16 | B19: Amount Mismatch Error on Initial Payment for Customer Order Agreement | C19: Payment Error
A20: 17 | B20: 2 way sync | C20: 2 way sync
... A23: 20 | B23: Duplicate ticket | C23: Duplicate ticket
A24: 21 | B24: PIN Reset | C24: PIN reset | D24: PRB WIP
A25: 22 | B25: The CW is unable to void the agreements because the Customer Order feature is currently disabled for eclipse RTO Stores. | C25: Agreement Void Issue
A26: 23 | B26: Generating detailed account report on rental agreements | C26: Account Report Request | D26: Crystal
A27: 24 | B27: Unable to create an agreement | C27: Agreement Creation Issue
A28: 25 | B28: Active Inventory Mismatch | C28: DQ-Inventory
A29: 26 | B29: The overridden other charge in the initial payment section is automatically reapplied after completing the agreement | C29: Payment Error
A30: 27 | B30: CREATE-INVENTORY-ACTIVITY-LOG | C30: 2 way sync
A31: 28 | B31: Unable to proceed with payment | C31: Payment Error
A32: 29 | B32: Unable to submit Inventory | C32: One Time Issue
A33: 30 | B33: Overshort Cash | C33: Daily task
A34: 31 | B34: Rate Retention for agreements is happening incorrectly. | C34: Agreement Issue
A35: 32 | B35: Duplicate customers record | C35: Duplicate customers record
A36: 33 | B36: Inventory Mismatch | C36: Inventory Mismatch
A37: 34 | B37: Account Report | C37: Account Report Request
A38: 35 | B38: Unable to transfer the agreement | C38: Agreement Transfer Issue
... A61: 58 | B61: Agreement price shows more | C61: Agreement Issue
A62: 59 | B62: Error in RmsReserveOrderService
A63: 60 | B63: Update the rate and term request
A64: 61 | B64: Increase in payment amount | C64: Payment Query
A65: 62 | B65: Publish the pricing | C65: Pricing request
A66: 63 | B66: Inventory Audit issue | C66: Inventory Issue
A67: 64 | B67: Unable to reverse PO | C67: Unable to reverse PO
A68: 65 | B68: DE shows declined
A69: 66 | B69: Unable to chargeoff account using the suspense amount. | C69: Chargeoff
A70: 67 | B70: Store action item is showing pending delivery confirmation even for the return appointment | C70: Confirm delivery Issue
A71: 68 | B71: Incorrect Charge back added | C71: Chargeback
A72: 69 | B72: Remove the reference
A73: 70 | B73: LDW Cancellation Issue with manually received tires.
A74: 71 | B74: Incorrect amount due
A75: 72 | B75: Negative TRTO and SAC after multiple term reductions
A76: 73 | B76: Chargeback request | C76: Chargeback
A77: 74 | B77: Remove the item from service | C77: Inventory Issue
A78: 75 | B78: Referral reward issue
A79: 76 | B79: Processing fee override fails when promo code is applied | C79: Promo issue
A80: 77 | B80: LDW tax getting added eventhough LDW is 0
A81: 78 | B81: Documents are disappearing after being uploaded in the Residence and Income page of the customer profile.
A82: 79 | B82: Add the item back to inventory | C82: Inventory Issue
A83: 80 | B83: Void the agreement as store is getting closed | C83: Agreement Void Issue
A84: 81 | B84: Screen not loading | C84: One Time Issue
A85: 82 | B85: Add missing CW to salesperson dropdown
A86: 83 | B86: Uploaded documents missing
A87: 84 | B87: Unable to perform drop reconciliation | C87: Drop reconciliation
A88: 85 | B88: Customer address and phone have changed | C88: Customer Issue
A89: 86 | B89: Payment getting refunded | C89: Payment reversal
A90: 87 | B90: Query | C90: Query
A91: 88 | B91: Incorrect sales tax | C91: Tax Issue
A92: 89 | B92: Transfer club account to different store
A93: 90 | B93: Query on amount calculation | C93: Query
A94: 91 | B94: Customer showing in past due incorrectly | C94: Customer Issue
A95: 92 | B95: Inventory scanning issue
A96: 93 | B96: Unable to process customer Refund | C96: Payment issue
A97: 94 | B97: cannot complete agreement | C97: Agreement Issue
A98: 95 | B98: Unable to send text messages
A99: 96 | B99: Card Payment Failure | C99: Payment Error
A100: 97 | B100: Incorrect due date
A101: 98 | B101: Trying to active the special order for a customer but getting error as Transaction has been failed.
A102: 99 | B102: Level 1 customer unable to add phone | C102: Customer Issue
A103: 100 | B103: Remove the skip/Hard
A104: 101 | B104: Price change request | C104: Pricing request
A105: 102 | B105: Audit missing
A106: 103 | B106: The agreement shows as Active even though it is PIF. | C106: Agreement Status
A107: 104 | B107: Unable to finalize audit
A108: 105 | B108: Inventory transfer | C108: Inventory Transfer Issue
A109: 106 | B109: Store Access | C109: Store Access
A110: 107 | B110: Month End Reporting | C110: EOM
A111: 108 | B111: EOY Inventory Report | C111: EOM
A112: 109 | B112: Manual PO Cancel | C112: Cancel the Manual PO
A113: 110 | B113: Bad Display | C113: Daily task
A114: 111 | B114: Incorrect Negative Balance for Customers
A115: 112 | B115: Agreement description is showing incorrect after switch out cancellation. | C115: Agreement Status
A116: 113 | B116: Remove item from clearance
A117: 114 | B117: Mismatch In Daily Report Manager Route Counts. | C117: Daily Report Issue
A118: 115 | B118: Data Mismatch on End date of agreement | C118: Agreement Issue
A119: 116 | B119: Incorrect pricing | C119: Pricing Issue
A120: 117 | B120: Request to change the promo name | C120: Promo request
A121: 118 | B121: Customer language preference not reflected in system‑generated messages
A122: 119 | B122: Need help with changing Status from Charged off to RENT READY.
A123: 120 | B123: Cost discrepancy in RACPAD for LG washer & dryer models due to differing vendor cost values causing incorrect cost posting and system misalignment.
A124: 121 | B124: Store CW has requested the addition of a Txt2Pay option on the Account Management screen.
...
