Workbook

Sheet Dump
A1: Number | B1: Created | C1: Priority | D1: Status | E1: Short Description | F1: Description | G1: Assignment Group | H1: Assigned to | I1: Action | J1: Parent | K1: Problem | L1: Caused by Change | M1: Module | N1: Type of Issue | O1: One time /Reccuring/Not an issue | R1: 1139
A2: INCTEC1591872 | B2: 46054.027 | C2: 3 - Moderate | D2: Closed | E2: BigPanda Incident: cloud2gcdb - Ok | F2: Incident Summary: -------------------------------------------------------- AI-Generated Incident Analysis Resolved: cloud2gcdb Lambda POST-PAYMENT Event Processing Errors Cleared in prod2 On Feb 1, 2026, at 06:34:16 UTC, 8 'Ok' alerts for 'cloud2gcdb' in 'prod2' (stores 08528, 08614, 08724, 08510, 08610) reported resolved errors in the Lambda 'Cloud2GcdbSubscriptionFilter' during POST-PAYMENT event processing. No current impact; all issues have cleared. At 06:34:16 UTC on Feb 1, 2026, 8 'Ok' alerts were generated for 'cloud2gcdb' in 'prod2', referencing errors in the Lambda 'Cloud2GcdbSubscriptionFilter' while processing POST-PAYMENT events for various stores. The simultaneous 'Ok' status indicates prior errors have been resolved, with no ongoing impact. AWS Lambda functions, such as 'Cloud2GcdbSubscriptionFilter', process events (here, POST-PAYMENT) and can log errors if processing fails. CloudWatch Logs (CWL) and custom log aggregators like Logz.io generate alerts when error patterns are detected. The 'Ok' status means the error condition has cleared—likely after transient issues (e.g., data, connectivity, or downstream service hiccups) were resolved. The identical timestamps suggest a batch resolution or system recovery, not ongoing or sequential failures. The absence of critical/warning alerts and the 'Ok' incident status confirm the system is healthy. No service desk tickets or historical actions suggest no user impact or escalation. | G2: RACPad Support | H2: dazel dsouza | M2: BigPanda | N2: BigPanda | R2: 336
A3: INCTEC1591879 | B3: 46054.106 | C3: 3 - Moderate | D3: Closed | E3: BigPanda Incident: sfcc - Ok (Flapping) | F3: Incident Summary: -------------------------------------------------------- AI-Generated Incident Analysis Critical Data Integrity Failure Impacting Inventory Event Processing in prod2 Lambdas On Sunday, Feb 1, 2026, at 08:27:12 UTC, two warning alerts from 'sfcc-store-inventory-delta-events' Lambda in 'prod2' reported 500 errors due to missing inventory data. At 08:29:14 UTC, a critical alert from 'tcpaeventsubscribe' Lambda indicated a related server error. Three alerts (1 critical, 2 warning) highlight a production-impacting data integrity issue affecting inventory event processing. At 08:27:12 UTC, two warning alerts from 'sfcc-store-inventory-delta-events' Lambda reported 500 errors due to missing 'Inventory' and 'InventoryPrice' data. At 08:29:14 UTC, a critical alert from 'tcpaeventsubscribe' Lambda reported a 500 error in 'ProcessTcpaEventsEntdbService'. The sequence suggests that missing or malformed inventory data in upstream events led to failures in both services, with the issue escalating to a critical state in the downstream 'tcpaeventsubscribe' Lambda. AWS Lambda failures and cascading errors were caused by malformed or incomplete inventory event data, highlighting how upstream data issues can propagate and disrupt downstream services in event-driven architectures. | G3: RACPad Support | H3: dazel dsouza | M3: BigPanda | N3: BigPanda | R3: =R1-R2 -> 803
A4: INCTEC1591881 | B4: 46054.119 | C4: 3 - Moderate | D4: Closed | E4: BigPanda Incident: sfcc - Ok | F4: Incident Summary: -------------------------------------------------------- AI-Generated Incident Analysis Warning: Application Errors in prod2-sfcc-store-inventory-delta-events Lambda Due to Missing Inventory Data (Flapping) On Feb 1, 2026, at 08:27 UTC, two Warning alerts for 'prod2-sfcc-store-inventory-delta-events-lambda-PublishStoreInventoryUpdatestoSFCCSubscriptionFilter' in prod2 signaled repeated 500 errors due to missing Inventory and InventoryPrice fields. The incident is flapping, with 2 warnings and 1 ok alert, affecting the sfcc-store-inventory-delta-events application. At 08:27:12 UTC on Feb 1, 2026, two Warning alerts were triggered for 'prod2-sfcc-store-inventory-delta-events-lambda-PublishStoreInventoryUpdatestoSFCCSubscriptionFilter' in prod2, both with statusCode 500 and error: 'Inventory and InventoryPrice is required'. This indicates the root cause is missing required fields in event payloads for this Lambda function. The Ok alert at 08:29:14 UTC is for a different application and is not causal. AWS Lambda functions process events and require specific payload fields to execute business logic. The error 'Inventory and InventoryPrice is required' with statusCode 500 means the Lambda could not process events due to missing data, resulting in application-level failures. HTTP 500 errors indicate server-side issues, not client or network faults. The simultaneous occurrence of two identical warnings for the same Lambda and error message at 08:27:12 UTC confirms a systemic issue with event payloads, not a transient or isolated error. The incident is flapping, suggesting intermittent resolution or repeated failures, possibly as upstream systems intermittently provide or omit required fields. The Ok alert at 08:29:14 UTC is for a different Lambda and application, with a different error, and does not contribute to the root cause. No user tickets or historical actions are present, so the analysis relies solely on alert evidence. | G4: RACPad Support | H4: dazel dsouza | M4: BigPanda | N4: BigPanda
A5: INCTEC1591882 | B5: 46054.123 | C5: 3 - Moderate | D5: Closed | E5: BigPanda Incident: customer - Warning | F5: Incident Summary: -------------------------------------------------------- | G5: RACPad Support | M5: BigPanda | N5: BigPanda
A6: INCTEC1591883 | B6: 46054.124 | C6: 3 - Moderate | D6: Closed | E6: BigPanda Incident: customer - Ok | F6: Incident Summary: -------------------------------------------------------- AI-Generated Incident Analysis Warning: 'customer' Application Database Update Error (Unique Constraint Violation) in prod2 AWS On Sunday, Feb 1, 2026, at 12:37:09 AM UTC, a warning alert was generated for the 'customer' application in the 'prod2' AWS environment. The incident involves a failed database update due to a unique constraint violation in the 'racadm.phone' table, affecting customer record processing. Only one warning alert was observed. At 12:37:09 AM UTC on Feb 1, 2026, the 'customer' application in the 'prod2' AWS environment triggered a warning due to a failed database update. The root cause is a unique constraint violation (PostgreSQL error 23505) on the 'racadm.phone' table, indicating an attempt to insert or update a record with a key that already exists. PostgreSQL enforces unique constraints to prevent duplicate records based on specified key columns. Error code 23505 occurs when an INSERT or UPDATE operation violates this rule. In this incident, the application attempted to update the 'racadm.phone' table with a key (customer_id, phone_type_id, phone_number, active, primary_flag) that already exists, resulting in a failed operation. This typically points to either a logic flaw in the application (e.g., not checking for existing records before updating) or a data integrity issue. The alert's stack trace and error code confirm the database rejected the operation, and the timing shows this was a single, isolated event. No evidence suggests a monitoring or infrastructure issue; the problem is rooted in application/database interaction. | G6: RACPad Support | M6: BigPanda | N6: BigPanda
A7: INCTEC1591888 | B7: 46054.171 | C7: 4 - Low | D7: Closed | E7: BigPanda Incident: managestoreconfigdbevents - Critical | F7: Incident Summary: -------------------------------------------------------- AI-Generated Incident Analysis Warning: sfcc-store-delta-events Lambda Failing on Invalid Event Objects in Production (prod2) From 02:06:14 to 02:56:15 UTC on Jan 29, 2026, 110 warning alerts were triggered for 'sfcc-store-delta-events' in prod2. The Lambda 'PublishStoreUpdatestoSFCCSubscriptionFilter' failed repeatedly with 500 errors due to invalid event objects (missing 'storeNumber'), impacting backend event processing in Production. Between 02:06:14 and 02:56:15 UTC on January 29, 2026, 110 warning alerts were generated for the Lambda 'prod2-sfcc-store-delta-events-lambda-PublishStoreUpdatestoSFCCSubscriptionFilter'. Each alert shows a 500 error due to 'Invalid Event Object' with 'storeNumber' as 'undefined', indicating repeated ingestion of malformed or incomplete event data. AWS Lambda functions process event-driven data, often triggered by upstream services or event buses. A 500 error with 'Invalid Event Object' and 'storeNumber: undefined' means the function received events missing required fields. This points to either an upstream system emitting malformed events or a misconfiguration in event schema validation. The regular, persistent timing (every 5-6 minutes) and identical error context across all alerts confirm a systemic data quality or integration issue, not a transient or infrastructure problem. The absence of critical alerts and the uniformity of the error further support that the Lambda is functioning but unable to process invalid input, not failing due to resource or runtime errors. No user tickets or historical actions suggest this is a backend integration/data pipeline issue, not a user-facing outage. | G7: RACPad Support | H7: Sreenu Yeturi | I7: RACPAD - Store | M7: BigPanda | N7: BigPanda
A8: INCTEC1591937 | B8: 46054.445 | C8: 3 - Moderate | D8: Closed | E8: BigPanda Incident: cloud2gcdb - Ok | F8: Incident Summary: -------------------------------------------------------- AI-Generated Incident Analysis Resolved: Transient Event Processing Errors in prod2-cloud2gcdb Lambda (Production) On Feb 1, 2026, between 16:36 and 16:57 UTC, 20 resolved alerts indicated transient errors in the 'cloud2gcdb' Lambda (prod2). All alerts are Ok, with no ongoing impact. Affected system: prod2-cloud2gcdb-lambda-Cloud2GcdbSubscriptionFilter in Production. No user tickets or persistent issues detected. Between 16:36:14 and 16:57:09 UTC on Feb 1, 2026, 20 alerts reported errors in processing POST-PAYMENT and one UPDATE-AGREEMENT event in the 'cloud2gcdb' Lambda function in prod2. All alerts are now Ok, indicating the errors were transient and have self-resolved. No ongoing issues are present. AWS Lambda functions (here, 'prod2-cloud2gcdb-lambda-Cloud2GcdbSubscriptionFilter') process events asynchronously. Errors in event processing (e.g., POST-PAYMENT) can trigger alerts if exceptions occur. The clustered alert times suggest a brief spike in errors, possibly due to a transient upstream data or service issue. Since all alerts are Ok, the Lambda resumed normal operation, likely after automatic retries or resolution of the upstream problem. No evidence of persistent faults, infrastructure issues, or user impact is present. The absence of flapping and the Ok status confirm system stability. | G8: RACPad Support | H8: dazel dsouza | M8: BigPanda | N8: BigPanda
A9: INCTEC1591940 | B9: 46054.452 | C9: 3 - Moderate | D9: Closed | E9: BigPanda Incident: processpayment - Ok | F9: Incident Summary: -------------------------------------------------------- AI-Generated Incident Analysis Resolved: processpayment Lambda (prod2/AWS) - Previous Cash App Service 500 Errors On Feb 1, 2026, at 16:45:09 UTC, six Ok alerts signaled recovery for the prod2-processpayment-lambda-ChargePaymentSubscriptionFilter in AWS (prod2). The incident involved prior Cash App Service 500 errors (PAYMENT_FAILURE) in the processpayment application. All systems are now operational; no user impact remains. At 16:45:09 UTC on Feb 1, 2026, six Ok alerts were generated for the prod2-processpayment-lambda-ChargePaymentSubscriptionFilter in AWS. These alerts indicate recovery from prior Cash App Service 500 Internal Server Errors (PAYMENT_FAILURE). The root cause was a transient error in the processpayment lambda, now resolved. HTTP 500 errors in serverless payment processing (AWS Lambda) typically signal unhandled exceptions or downstream service failures. The processpayment lambda likely encountered a temporary issue with the Cash App Service, resulting in PAYMENT_FAILURE. Monitoring systems (logzio_custom) detected the error and, upon resolution, generated Ok alerts. The simultaneous Ok status across all alerts at the same timestamp confirms the service has recovered. No new errors or warnings are present, and the incident status is Ok, indicating no ongoing impact. The absence of flapping and tickets further supports that the issue was transient and is now resolved. | G9: RACPad Support | H9: dazel dsouza | M9: BigPanda | N9: BigPanda
A10: INCTEC1591952 | B10: 46054.489 | C10: 3 - Moderate | D10: Closed | E10: BigPanda Incident: cloud2gcdb - Ok | F10: Incident Summary: -------------------------------------------------------- AI-Generated Incident Analysis Resolved: cloud2gcdb Lambda Event Processing Errors in prod2 Across Multiple Stores On Feb 1, 2026, from 16:36 to 17:38 UTC, 30 Ok-status alerts indicated previously resolved errors in the 'cloud2gcdb' Lambda function (prod2) affecting multiple FIELD SYSTEMS stores. No current impact remains; all systems are operational. No user tickets or ongoing issues were detected. Between 16:36:14 and 17:38:14 UTC on Feb 1, 2026, 30 alerts reported errors processing 'POST-PAYMENT' and one 'UPDATE-AGREEMENT' event in the 'cloud2gcdb' Lambda function across multiple stores in 'prod2'. All alerts are now Ok, indicating the underlying issue was transient and has been resolved. The alerts originated from AWS Lambda (as inferred from 'prod2-cloud2gcdb-lambda-Cloud2GcdbSubscriptionFilter') processing events via CloudWatch Logs. Errors in event processing (e.g., POST-PAYMENT) can result from transient issues such as downstream service unavailability, malformed payloads, or temporary resource constraints. The clustering of alerts at three distinct times suggests batch processing or retries. Since all alerts are now Ok, the Lambda function has resumed normal operation, indicating the root cause was likely a temporary external dependency or data issue, not a persistent code or infrastructure fault. No evidence of systemic or ongoing failure is present. | G10: RACPad Support | H10: Vandana K | M10: BigPanda | N10: BigPanda
A11: INCTEC1591957 | B11: 46054.518 | C11: 3 - Moderate | D11: Closed | E11: BigPanda Incident: processpayment - Ok | F11: Incident Summary: -------------------------------------------------------- AI-Generated Incident Analysis Resolved Transient 500 Errors in processpayment, customer, and deliveryreceipt Applications (prod2/AWS) On Feb 1, 2026, nine Ok-status alerts were generated for processpayment, customer, and deliveryreceipt apps in prod2 (AWS). Earlier, these services experienced transient 500 errors (payment, data, SQL issues), but all were resolved before alerting. No ongoing impact, no user tickets, and all systems are currently healthy. Between 16:45:09Z and 18:20:13Z on Feb 1, 2026, multiple applications in prod2 (AWS) experienced transient 500 errors: processpayment (Cash App Service internal errors), customer (duplicate Okta ID), and deliveryreceipt (UploadReceiptsService SQL error). All issues resolved before alerting, as indicated by Ok status at alert times. HTTP 500 errors indicate server-side failures. For processpayment, the error 'PP_CASHAPP_500' suggests a downstream dependency (Cash App Service) failed during payment capture, likely due to transient backend or integration issues. The customer alert points to a data integrity issue (duplicate Okta ID), which can cause application logic failures. The deliveryreceipt error references a SQL syntax error (code 42601), likely from malformed queries or unexpected input. All alerts are from AWS-hosted services in prod2, using Lambda and ECS, and were detected via CloudWatch Logs. The Ok status at alert time means automated recovery or transient resolution occurred, possibly via retries, code fixes, or data correction. No evidence of persistent or systemic failure, and no user tickets suggest limited or no end-user impact. The sequence and timing show independent, short-lived issues across services, not a single root cause. | G11: RACPad Support | H11: Vandana K | M11: BigPanda | N11: BigPanda
A12: INCTEC1591960 | B12: 46054.53 | C12: 3 - Moderate | D12: Closed | E12: BigPanda Incident: cloud2gcdb - Ok | F12: Incident Summary: -------------------------------------------------------- AI-Generated Incident Analysis Resolved: cloud2gcdb Lambda Event Processing Errors Cleared in prod2 (FIELD SYSTEMS) From 18:38:14 to 20:38:10 UTC on Feb 1, 2026, 30 Ok alerts were generated for the prod2-cloud2gcdb-lambda-Cloud2GcdbSubscriptionFilter in the prod2 environment (FIELD SYSTEMS). All alerts indicate resolution of prior event processing errors. No active issues remain, and no user tickets were correlated. Systems are operating normally. Between 18:38:14 and 20:38:10 UTC on Feb 1, 2026, 30 Ok alerts were generated for the prod2-cloud2gcdb-lambda-Cloud2GcdbSubscriptionFilter in the prod2 environment. These Ok alerts indicate that previously detected errors in event processing (POST-PAYMENT, UPDATE-CUSTOMER) have been resolved. No active root cause remains. In AWS Lambda-based event-driven systems, monitoring tools like logzio_custom ingest CloudWatch Logs and generate alerts for error patterns. Ok alerts signify that error conditions (e.g., failed POST-PAYMENT/UPDATE-CUSTOMER events) have cleared. The absence of critical/warning/unknown alerts and the Ok status across all 30 alerts confirm system recovery. The incident's Ok status supersedes individual alert statuses, indicating full resolution. The time sequencing shows a return to normalcy, with no evidence of ongoing or recurring issues. This pattern is typical in serverless architectures, where transient errors are detected, remediated, and then cleared, triggering Ok notifications. | G12: RACPad Support | H12: Vandana K | M12: BigPanda | N12: BigPanda
A13: INCTEC1591962 | B13: 46054.539 | C13: 3 - Moderate | D13: Closed | E13: BigPanda Incident: sfcc - Ok | F13: Incident Summary: -------------------------------------------------------- AI-Generated Incident Analysis Warning: Application Errors in prod2-sfcc-store-inventory-delta-events Lambda Due to Missing Inventory Data (Flapping) On Feb 1, 2026, at 08:27 UTC, two Warning alerts for 'prod2-sfcc-store-inventory-delta-events-lambda-PublishStoreInventoryUpdatestoSFCCSubscriptionFilter' in prod2 signaled repeated 500 errors due to missing Inventory and InventoryPrice fields. The incident is flapping, with 2 warnings and 1 ok alert, affecting the sfcc-store-inventory-delta-events application. At 08:27:12 UTC on Feb 1, 2026, two Warning alerts were triggered for 'prod2-sfcc-store-inventory-delta-events-lambda-PublishStoreInventoryUpdatestoSFCCSubscriptionFilter' in prod2, both with statusCode 500 and error: 'Inventory and InventoryPrice is required'. This indicates the root cause is missing required fields in event payloads for this Lambda function. The Ok alert at 08:29:14 UTC is for a different application and is not causal. AWS Lambda functions process events and require specific payload fields to execute business logic. The error 'Inventory and InventoryPrice is required' with statusCode 500 means the Lambda could not process events due to missing data, resulting in application-level failures. HTTP 500 errors indicate server-side issues, not client or network faults. The simultaneous occurrence of two identical warnings for the same Lambda and error message at 08:27:12 UTC confirms a systemic issue with event payloads, not a transient or isolated error. The incident is flapping, suggesting intermittent resolution or repeated failures, possibly as upstream systems intermittently provide or omit required fields. The Ok alert at 08:29:14 UTC is for a different Lambda and application, with a different error, and does not contribute to the root cause. No user tickets or historical actions are present, so the analysis relies solely on alert evidence. | G13: RACPad Support | H13: Vandana K | M13: BigPanda | N13: BigPanda
A14: INCTEC1591978 | B14: 46054.62 | C14: 3 - Moderate | D14: Closed | E14: BigPanda Incident: campaignstatistics - Ok | F14: Incident Summary: -------------------------------------------------------- AI-Generated Incident Analysis Resolved Data Integrity Error in campaignstatistics Application (prod2/AWS) On Feb 1, 2026, at 20:48:10 UTC, two Ok alerts signaled resolution of a prior data integrity error in the 'campaignstatistics' application (prod2, AWS). The issue involved a missing customer_id causing database errors in Lambda processes. No ongoing impact; incident is resolved. Total alerts: 2 Ok. At 20:48:10 UTC on Feb 1, 2026, two Ok alerts were generated for the 'campaignstatistics' application in prod2/AWS. Both referenced prior 500 errors due to a PostgreSQL foreign key violation (missing customer_id in 'customer' table). The root cause was a transient data integrity issue, now resolved, affecting related Lambda processes. PostgreSQL error 23503 indicates a foreign key violation, meaning a referenced customer_id was missing in the 'customer' table when inserting/updating 'account_management_activity'. This enforces referential integrity, preventing orphaned records. The alerts' Ok status and identical timestamps show the application recovered after the transient data issue was resolved, likely by correcting the missing customer or adjusting the data flow. The use of AWS Lambda functions suggests event-driven processing, where such errors can occur if upstream data is incomplete or delayed. No ongoing alerts or tickets indicate the issue was self-healing or remediated promptly. | G14: RACPad Support | H14: Divya P2 | M14: BigPanda | N14: BigPanda
A15: INCTEC1591981 | B15: 46054.655 | C15: 3 - Moderate | D15: Closed | E15: BigPanda Incident: cloud2gcdb - Ok | F15: Incident Summary: -------------------------------------------------------- AI-Generated Incident Analysis Resolved: Transient POST-PAYMENT Processing Errors in prod2-cloud2gcdb-lambda-Cloud2GcdbSubscriptionFilter (Production) On Feb 1, 2026, between 21:38 and 22:38 UTC, 20 Ok-status alerts reported and resolved errors in POST-PAYMENT event processing by the prod2-cloud2gcdb-lambda-Cloud2GcdbSubscriptionFilter function in the prod2 environment. No ongoing issues or user impact remain. All alerts are cleared. Between 21:38:10 and 22:38:12 UTC on Feb 1, 2026, 20 alerts reported errors processing POST-PAYMENT events in the prod2-cloud2gcdb-lambda-Cloud2GcdbSubscriptionFilter function across multiple stores. All alerts are now Ok, indicating the errors were transient and have been resolved. No ongoing impact is present. AWS Lambda functions, such as prod2-cloud2gcdb-lambda-Cloud2GcdbSubscriptionFilter, process events asynchronously. Errors in event processing (e.g., POST-PAYMENT) can trigger alerts if exceptions occur. The Ok status means the function recovered or the error condition cleared. The 1-hour gap between alert groups suggests a batch or periodic process. No critical or warning alerts remain, confirming resolution. The absence of flapping and the Ok incident status further support that the issue was transient and not systemic. No service desk tickets or historical actions indicate user impact, so the root cause was likely a temporary processing anomaly, now cleared. | G15: RACPad Support | H15: Vandana K | M15: BigPanda | N15: BigPanda
A16: INCTEC1591999 | B16: 46054.739 | C16: 3 - Moderate | D16: Closed | E16: BigPanda Incident: cloud2gcdb - Ok | F16: Incident Summary: -------------------------------------------------------- AI-Generated Incident Analysis Resolved: cloud2gcdb Lambda POST-PAYMENT Event Processing Errors Cleared in prod2 On February 1, 2026, at 23:38:11 UTC, 10 Ok alerts indicated resolution of prior errors in the prod2-cloud2gcdb-lambda-Cloud2GcdbSubscriptionFilter function processing POST-PAYMENT events for FIELD SYSTEMS in the prod2 environment. No ongoing issues or user impact detected; all systems are now normal. At 2026-02-01T23:38:11.000Z, 10 alerts (all Ok) reported previously detected errors in the prod2-cloud2gcdb-lambda-Cloud2GcdbSubscriptionFilter function while processing POST-PAYMENT events across multiple stores. The Ok status and identical timestamps confirm the underlying issue was resolved before this incident snapshot. AWS Lambda functions, like prod2-cloud2gcdb-lambda-Cloud2GcdbSubscriptionFilter, process events (here, POST-PAYMENT) and can emit errors if processing fails. CloudWatch Logs (cwl) and logzio_custom monitor these errors, generating alerts. The Ok status means the error condition cleared—likely via code fix, input correction, or transient issue resolution. Simultaneous Ok alerts across stores indicate a systemic issue was resolved, not isolated to a single store. No critical/warning alerts or ongoing errors support that the Lambda function is now operating normally. The absence of flapping and tickets further confirms stability. Thus, the root cause was a resolved, short-lived error in Lambda event processing. | G16: RACPad Support | H16: Vandana K | M16: BigPanda | N16: BigPanda
A17: INCTEC1592007 | B17: 46054.78 | C17: 3 - Moderate | D17: Closed | E17: BigPanda Incident: cloud2gcdb - Ok | F17: Incident Summary: -------------------------------------------------------- AI-Generated Incident Analysis Resolved: Transient POST-PAYMENT Processing Errors in cloud2gcdb Lambda (prod2 Environment) From Feb 1, 2026, 23:38 UTC to Feb 2, 2026, 00:38 UTC, 20 resolved alerts reported POST-PAYMENT event processing errors in the 'cloud2gcdb' Lambda ('prod2-cloud2gcdb-lambda-Cloud2GcdbSubscriptionFilter') in the 'prod2' environment. All alerts are Ok; no ongoing impact. No user tickets or flapping detected. Between 23:38:11 UTC and 00:38:11 UTC (Feb 1–2, 2026), 20 alerts reported errors processing POST-PAYMENT events in the 'prod2-cloud2gcdb-lambda-Cloud2GcdbSubscriptionFilter' Lambda for 'cloud2gcdb' in 'prod2'. All alerts are now Ok, indicating the errors were transient and self-resolved. No ongoing issues detected. AWS Lambda functions process events asynchronously; errors can occur due to transient issues (e.g., downstream service latency, temporary data inconsistencies, or resource contention). The alerts, all referencing POST-PAYMENT event errors, suggest a brief disruption. Since all alerts are now Ok and no new errors are reported, the Lambda or its dependencies recovered automatically, consistent with cloud-native error handling and retry mechanisms. The lack of critical or warning alerts, and the absence of flapping, further supports that the incident was self-healing and did not require manual intervention. | G17: RACPad Support | H17: Vandana K | M17: BigPanda | N17: BigPanda
A18: INCTEC1592010 | B18: 46054.784 | C18: 3 - Moderate | D18: Closed | E18: BigPanda Incident: processpayment - Ok (Flapping) | F18: Incident Summary: -------------------------------------------------------- AI-Generated Incident Analysis Resolved Transient 500 Errors in processpayment, customer, and deliveryreceipt Applications (prod2/AWS) On Feb 1, 2026, nine Ok-status alerts were generated for processpayment, customer, and deliveryreceipt apps in prod2 (AWS). Earlier, these services experienced transient 500 errors (payment, data, SQL issues), but all were resolved before alerting. No ongoing impact, no user tickets, and all systems are currently healthy. Between 16:45:09Z and 18:20:13Z on Feb 1, 2026, multiple applications in prod2 (AWS) experienced transient 500 errors: processpayment (Cash App Service internal errors), customer (duplicate Okta ID), and deliveryreceipt (UploadReceiptsService SQL error). All issues resolved before alerting, as indicated by Ok status at alert times. HTTP 500 errors indicate server-side failures. For processpayment, the error 'PP_CASHAPP_500' suggests a downstream dependency (Cash App Service) failed during payment capture, likely due to transient backend or integration issues. The customer alert points to a data integrity issue (duplicate Okta ID), which can cause application logic failures. The deliveryreceipt error references a SQL syntax error (code 42601), likely from malformed queries or unexpected input. All alerts are from AWS-hosted services in prod2, using Lambda and ECS, and were detected via CloudWatch Logs. The Ok status at alert time means automated recovery or transient resolution occurred, possibly via retries, code fixes, or data correction. No evidence of persistent or systemic failure, and no user tickets suggest limited or no end-user impact. The sequence and timing show independent, short-lived issues across services, not a single root cause. | G18: RACPad Support | H18: Vandana K | M18: BigPanda | N18: BigPanda
A19: INCTEC1592020 | B19: 46054.822 | C19: 3 - Moderate | D19: Closed | E19: BigPanda Incident: cloud2gcdb - Ok | F19: Incident Summary: -------------------------------------------------------- AI-Generated Incident Analysis Resolved: cloud2gcdb Lambda Event Processing Errors Cleared in prod2 Across Multiple Stores From Feb 1, 2026, 23:38 UTC to Feb 2, 2026, 01:38 UTC, 30 Ok-status alerts were generated for 'cloud2gcdb' in 'prod2', referencing Lambda 'Cloud2GcdbSubscriptionFilter' errors across multiple stores. All issues have cleared, with no ongoing impact. No user tickets or flapping detected. Between 23:38:11 UTC on Feb 1, 2026, and 01:38:08 UTC on Feb 2, 2026, 30 Ok-status alerts were generated for 'cloud2gcdb' in 'prod2', referencing errors in the Lambda 'Cloud2GcdbSubscriptionFilter' across multiple stores. All alerts indicate the issue has cleared; no active errors remain. The root cause was likely a transient error in event processing by the Lambda, now resolved. AWS Lambda functions like 'Cloud2GcdbSubscriptionFilter' process events (here, POST-PAYMENT) and can fail due to transient issues (e.g., downstream service unavailability, malformed events, or temporary resource constraints). The alerts, sourced from CloudWatch Logs, show error messages but all have status Ok, meaning the monitoring system detected the error condition was resolved before the incident closed. The clustering of alert times suggests a batch of errors occurred, but the absence of critical/warning/unknown alerts and the final Ok status confirm recovery. The distributed nature (multiple store_numbers) implies either a systemic but short-lived issue or a batch of problematic events. No evidence points to persistent or underlying infrastructure faults. The lack of flapping and the Ok status across all alerts further support that the Lambda's error state was transient and has been remediated, either automatically or via a fix. | G19: RACPad Support | H19: Vandana K | M19: BigPanda | N19: BigPanda
... A24: INCTEC1592041 | B24: 46054.977 | C24: 3 - Moderate | D24: Closed | E24: BigPanda Incident: cloud2gcdb - Ok | F24: Incident Summary: -------------------------------------------------------- AI-Generated Incident Analysis Resolved: cloud2gcdb Lambda POST-PAYMENT Event Processing Errors Cleared in prod2 On Monday, February 2, 2026, at 5:21:07 AM UTC, four 'Ok' alerts for the 'cloud2gcdb' Lambda in 'prod2' (stores 08569, 08687, 08717) indicated resolution of prior POST-PAYMENT event processing errors. All alerts cleared simultaneously, confirming the application has returned to normal operation. No further action is required. At 05:21:07 UTC on February 2, 2026, four 'Ok' alerts were generated for the 'cloud2gcdb' Lambda function in 'prod2', each referencing prior errors processing POST-PAYMENT events for different stores. The simultaneous 'Ok' status indicates that earlier errors were resolved and normal processing resumed. No ongoing issues remain. AWS Lambda functions process events asynchronously, with errors often logged to CloudWatch Logs. The 'cwl' alerts here, all marked 'Ok' at the same timestamp, suggest that previous POST-PAYMENT event processing errors were detected and have since cleared. The Lambda's recovery is reflected by the 'Ok' status, indicating successful subsequent executions. No new errors or warnings are present, and the incident status confirms resolution. The use of CloudWatch Logs for alerting is standard in serverless architectures, and the simultaneous clearance across multiple stores implies a systemic, but transient, issue—possibly a brief service or dependency disruption that self-resolved. The absence of correlated tickets or ongoing alerts further supports that the root cause was a temporary error in the Lambda's event processing, now remediated. | G24: RACPad Support | H24: Divya P2 | M24: BigPanda | N24: BigPanda
A25: INCTEC1592055 | B25: 46055.066 | C25: 4 - Low | D25: Closed | E25: RE: LEVEL 0 Customer - Junia Sohs - 3074150-RACPAD | F25: From: Katherine Fang <Katherine.Fang@Rentacenter.com> Sent: Saturday, January 31, 2026 3:53 AM To: RACPad Support <RACPadSupport@rentacenter.com> Cc: Seema Rani <Seema.Rani@Rentacenter.com>; Caroline Zhu <Caroline.Zhu@Rentacenter.com>; OperationsSupport <OperationsSupport@Rentacenter.com> Subject: LEVEL 0 Customer - Junia Sohs - 3074150 Hi RACPAD team, We have a customer who is a Level 0 customer but is unable to create a phone agreement. Could you please check this on your end? Thank you! Katherine From: OperationsSupport <OperationsSupport@Rentacenter.com<mailto:OperationsSupport@Rentacenter.com>> Sent: Friday, January 30, 2026 10:31 AM To: Caroline Zhu <Caroline.Zhu@Rentacenter.com<mailto:Caroline.Zhu@Rentacenter.com>>; Katherine Fang <Katherine.Fang@Rentacenter.com<mailto:Katherine.Fang@Rentacenter.com>> Subject: FW: LEVEL 0 Customer - Junia Sohs - 3074150 Based on the expiration date of the DE, it looks like the customer is level 0, but can't add a phone. Can you look at this customer? Mark Bassett Sr. Mgr. Ops Support From: Store 00684 <Store.00684@rentacenter.com<mailto:Store.00684@rentacenter.com>> Sent: Thursday, January 29, 2026 4:27 PM To: OperationsSupport <OperationsSupport@Rentacenter.com<mailto:OperationsSupport@Rentacenter.com>> Cc: Brian Stewart <Brian.Stewart@rentacenter.com<mailto:Brian.Stewart@rentacenter.com>> Subject: Re: LEVEL 0 Customer In the bottom right circled in red is what it says just now when I tried to special order it. ________________________________ From: OperationsSupport <OperationsSupport@Rentacenter.com<mailto:OperationsSupport@Rentacenter.com>> Sent: Thursday, January 29, 2026 1:18 PM To: Store 00684 <Store.00684@rentacenter.com<mailto:Store.00684@rentacenter.com>> Cc: Brian Stewart <Brian.Stewart@rentacenter.com<mailto:Brian.Stewart@rentacenter.com>> Subject: RE: LEVEL 0 Customer Customer record shows to be a level 0 in RACPAD based on the DE expiration of 03-29-2026. Mark Bassett Sr. Mgr. Ops Support From: Store 00684 <Store.00684@rentacenter.com<mailto:Store.00684@rentacenter.com>> Sent: Thursday, January 29, 2026 4:09 PM To: OperationsSupport <OperationsSupport@Rentacenter.com<mailto:OperationsSupport@Rentacenter.com>> Cc: Brian Stewart <Brian.Stewart@rentacenter.com<mailto:Brian.Stewart@rentacenter.com>> Subject: LEVEL 0 Customer Good afternoon, I am trying to rent this customer a iPhone 17 Pro-Max Silver 256gb Model# NW00107 in Sales force it shows she is Level-0 But when I try and customer special order it in Rac-Pad it says customer is not eligible, can you help me get this customer's phone ordered by updating her profile in Rac-Pad to match what it shows in Sales Force ? Rent-A-Center 00684 4240 Old Seward Highway Ste 24 Anchorage, AK 99503 907-290-5252 | G25: RACPad Support | H25: Jitheesha Thankachan | I25: RACPAD - other | M25: Customer | N25: Customer level change request
A26: INCTEC1592060 | B26: 46055.106 | C26: 3 - Moderate | D26: Closed | E26: BigPanda Incident: sfcc - Ok | F26: Incident Summary: -------------------------------------------------------- AI-Generated Incident Analysis Resolved: Server-Side Errors in prod2 Affecting sfcc-store-inventory-delta-events and tcpaeventsubscribe On February 2, 2026, three server-side errors were detected in the 'prod2' environment: two in 'sfcc-store-inventory-delta-events' and one in 'tcpaeventsubscribe', all related to AWS Lambda functions. Errors were due to missing required data or processing failures. All alerts are now resolved, and services are operating normally. Between 08:27:07 and 08:44:13 UTC on February 2, 2026, three server-side errors (HTTP 500) were detected in the 'prod2' environment. Two alerts for 'sfcc-store-inventory-delta-events' lambda reported missing 'Inventory' and 'InventoryPrice' fields, preventing event processing. The third alert for 'tcpaeventsubscribe' lambda indicated a processing error in 'ProcessTcpaEventsEntdbService'. All alerts are now resolved, indicating the underlying data or service issues were transient or remediated. The root cause was missing or malformed event data for the first two alerts and a processing failure for the third, all within the same production environment. Multiple AWS Lambda functions in a shared environment experienced temporary HTTP 500 errors due to incomplete event data, likely from a systemic upstream issue, but the problem resolved quickly without user impact. | G26: RACPad Support | H26: Divya P2 | M26: BigPanda | N26: BigPanda
A27: INCTEC1592088 | B27: 46055.312 | C27: 4 - Low | D27: Closed | E27: RACPAD - Cash Management | Drop Reconciliation | | F27: Drop Reconciliation is not coming up for 01/31/26 to complete. EMP name :Henry Goodman2 EMP ID : 104228 | G27: RACPad Support | H27: Syeda Asfiya | I27: RACPAD - Cash Management | M27: Cash Management | N27: Drop reconciliation issue
A28: INCTEC1592104 | B28: 46055.333 | C28: 3 - Moderate | D28: Closed | E28: BigPanda Incident: sfcc-store-inventory-delta-events - Ok | F28: Incident Summary: -------------------------------------------------------- AI-Generated Incident Analysis Resolved Server Errors in AWS Lambda Functions for sfcc-store-inventory-delta-events and tcpaeventsubscribe (prod2) On February 2, 2026, three server error alerts (all now resolved) were detected in AWS Lambda functions for 'sfcc-store-inventory-delta-events' and 'tcpaeventsubscribe' in the 'prod2' environment. Errors involved missing required data and processing failures. No ongoing issues or user impact are present. Between 08:27:07 and 08:44:13 UTC on February 2, 2026, three server error alerts (statusCode 500) were triggered for AWS Lambda functions in the 'prod2' environment. Two alerts for 'sfcc-store-inventory-delta-events' indicated missing 'Inventory and InventoryPrice' data, while one for 'tcpaeventsubscribe' showed a processing error. All issues are now resolved. HTTP 500 errors in AWS Lambda functions typically indicate unhandled exceptions or failed dependencies. The 'sfcc-store-inventory-delta-events' alerts show missing required fields ('Inventory' and 'InventoryPrice'), suggesting upstream data validation or integration issues. The 'tcpaeventsubscribe' alert references a processing error, likely due to similar data or service dependencies. Both functions are event-driven, relying on correct input payloads and downstream service availability. The close timing and shared environment suggest a transient data or integration issue, now resolved as all alerts are 'Ok'. No evidence of persistent or systemic failure is present, and no user tickets corroborate ongoing impact. | G28: RACPad Support | H28: Vandana K | M28: BigPanda | N28: BigPanda
A29: INCTEC1592117 | B29: 46055.352 | C29: 4 - Low | D29: Closed | E29: Getting 4 digits PIN code error while trying to make payment in RacPad. | F29: User name- Shaquile VelezLaureano Emp Id- 100929 Contact number- (939) 312-3754 Email id- Store-04067 Issue- Getting 4 digits PIN code error while trying to make payment in RacPad. | G29: RACPad Support | H29: Sreenivasa Ks | I29: RACPAD - Payment | M29: Admin | N29: PIN reset
A30: INCTEC1592127 | B30: 46055.369 | C30: 4 - Low | D30: Closed | E30: RACPAD - Cash Management | Drop Reconciliation | | F30: tried to do drop reconciliation showing my drop a eod drop and another store drop all combined with my drop. | G30: RACPad Support | H30: Syeda Asfiya | I30: RACPAD - Cash Management | M30: Cash Management | N30: Drop reconciliation issue
A31: INCTEC1592453 | B31: 46055.742 | C31: 4 - Low | D31: Closed | E31: RACPAD - Payment | Customer Refund | | F31: Customer Name: JOHNATHAN JERNIGAN Last 4 of Card Used: 6737 Exact Amount of Refund: 393.93 Exact Date of Refund: 08/29/2025,10/01/2025,10/08/2025,10/15/2025,10/22/2025,10/29/2025,11/05/2025,11/12/2025,11/19/2025,11/26/2025,12/03/2025, 12/10/2025,12/17/2025,12/24/2025,12/31/2025,01/07/2026,01/14/2026,01/21/2026 Agreement or Receipt #: 8173153532 Detailed Description of Issue: CUSTOMER SAID HE DID NOT RECEIVE MERCHANDISE ============================================================================================================================ Co-worker name: Ashley Hatcher Employee ID: 134725 Store: 00850 Customer name: Jonathan Jernigan Customer ID: 113332362 Receipt #: 455652295, 455018278, 454355868, 453705584, 452976660, 452356408, 451677108, 450991160, 450277754, 449551804, 448897633, 448216822, 447581320, 446844403, 446200269, 445541589, 444878965, 444111102, 440856084 Total Amount Needs to be refunded: $267.12 Issue: CW mentioned merchandise is not received by the customer but the amount is getting dedicated from the customer. Need this amount refunded to the customer. Need help with this. | G31: RACPad Support | H31: shruthika c | I31: RACPAD - Payment | K31: PRB0044395 | M31: Payment | N31: Customer refund | O31: Reccurring
A32: INCTEC1592154 | B32: 46055.405 | C32: 3 - Moderate | D32: Closed | E32: BigPanda Incident: customer - Ok | F32: Incident Summary: -------------------------------------------------------- AI-Generated Incident Analysis Resolved: Transient Backend and Database Errors Across Multiple AWS Production Services On Feb 2, 2026, 15 alerts (all Ok) were generated for AWS-hosted prod2 services, including customer, agreementcreate, processpayment, and others. Alerts referenced prior backend/database errors and network issues, but all services have since recovered. No flapping or open issues remain. No user tickets correlated. Between 15:37 and 17:32 UTC on Feb 2, 2026, multiple AWS-hosted production services (customer, postcommitment, agreementcreate, etc.) experienced transient errors (HTTP 500/400, DB errors, connection resets). All alerts now report Ok, indicating the underlying issues—likely temporary backend/database or integration failures—have been resolved. The alerts show a pattern of transient backend failures: HTTP 500/400 errors, database constraint violations (e.g., missing customer_id, varchar overflows), and network errors (ECONNRESET). These are typical in distributed cloud-native architectures where microservices interact with databases and external APIs. The errors' resolution (all Ok) suggests either a temporary outage or a successful remediation (e.g., DB failover, service restart, or network recovery). The diversity of affected services and error types points to a shared infrastructure or integration point (e.g., database cluster, network segment, or API gateway) as the likely root cause. No ongoing symptoms or flapping are present, confirming stability. | G32: RACPad Support | H32: Vandana K | M32: BigPanda | N32: BigPanda
A33: INCTEC1592612 | B33: 46056.379 | C33: 4 - Low | D33: Closed | E33: RACPAD - Payment | Customer Refund | | F33: Customer Name: Clyde Haines Last 4 of Card Used: cash Exact Amount of Refund: 99.39 Exact Date of Refund: 02/03/2026 Agreement or Receipt #: 455817650 Detailed Description of Issue: Was supposed to be put in as a money order, MO# 22-114535080 which has been put on suspense on the account until the $99.36 payment is removed | G33: RACPad Support | H33: shruthika c | I33: RACPAD - Payment | K33: PRB0044395 | M33: Payment | N33: Customer refund
A34: INCTEC1592172 | B34: 46055.418 | C34: 4 - Low | D34: Closed | E34: RACPAD - Customer | Customer - Other | | F34: Funds pulled from customer's account 2 times. There is no receipt showing on customer's account. Customer ID: 01-31-2026 Customer Name: 114654331 Date and Time Issue Was Occured: 2026-01-31 10:00:27 | G34: RACPad Support | H34: dazel dsouza | I34: RACPAD - Customer | M34: Payment | N34: Customer charged multiple times
A35: INCTEC1592182 | B35: 46055.43 | C35: 3 - Moderate | D35: Closed | E35: BigPanda Incident: cloud2gcdb - Ok | F35: Incident Summary: -------------------------------------------------------- AI-Generated Incident Analysis Resolved: cloud2gcdb Lambda Event Processing Errors Cleared in prod2 Environment On Feb 2, 2026, 29 Ok alerts were generated for the 'cloud2gcdb' application (Lambda: prod2-cloud2gcdb-lambda-Cloud2GcdbSubscriptionFilter) in the 'prod2' environment, across multiple stores. All previously detected errors in event processing have been resolved. No active issues remain. Between 16:13:13 and 17:40:10 UTC on Feb 2, 2026, 29 Ok-status alerts were generated for 'prod2-cloud2gcdb-lambda-Cloud2GcdbSubscriptionFilter' in the 'cloud2gcdb' app. These Ok alerts indicate that prior errors in processing various event types across multiple stores have been resolved. No active or causal issues remain. AWS Lambda functions, such as 'prod2-cloud2gcdb-lambda-Cloud2GcdbSubscriptionFilter', process events (e.g., POST-PAYMENT) and can emit errors if downstream systems or data are unavailable or malformed. The Ok status of all alerts, clustered at three timestamps, suggests that previous errors (likely due to transient issues in event processing or dependencies) have cleared. The monitoring system (logzio_custom via CloudWatch Logs) detected the return to normal operation, generating Ok alerts. No new errors or warnings are present, and the incident status is Ok, confirming resolution. The absence of flapping and service desk tickets further supports that the Lambda function and its integrations are now stable. | G35: RACPad Support | H35: Vandana K | M35: BigPanda | N35: BigPanda
A36: INCTEC1592188 | B36: 46055.437 | C36: 4 - Low | D36: Closed | E36: RACPAD - Agreement | Unable to create an Agreement | | F36: Trying to write agreement, keeps telling me that "Invalid inventoryID or inventroyID is not associated with store" Agreement Number: 00000000000 Customer ID: 111648466 Customer Name: Brandon Estep Date and Time Issue Was Occured: 2026-02-02 10:19:07 Store number: 02156 - MORRISTOWN-2171 AJ HWY - A - M0202 - R0070 - S08 - RACUSA Coworker name and ID: Jordan Musslewhite 350817 Customer name and number: Brandon Estep 111648466 Computer name: 02156-3CM31D3 IP address: 10.108.107.44 Issue description: Trying to write agreement, keeps telling me that "Invalid inventoryID or inventroyID is not associated with store" Steps taken to arrive at problem: Time of occurrence (Recreate the issue and notate the time if needed): 2026-02-02 10:19:07 Screen shot required: YES | G36: RACPad Support | H36: atulashok shinde | I36: RACPAD - Agreement | M36: Inventory | N36: Invalid inventoryId error
A37: INCTEC1592199 | B37: 46055.444 | C37: 4 - Low | D37: Closed | E37: RacPad | Autopay Issue | F37: customers not receiving enrollement auto pay text | G37: RACPad Support | H37: Jitheesha Thankachan | I37: RACPAD - other | M37: Customer | N37: AutoPay
A38: INCTEC1592210 | B38: 46055.45 | C38: 4 - Low | D38: Closed | E38: Racpad and other Apps was working very slow | F38: Issue : Racpad and Apps was working very slow its just loading EMP name : Britney Richardson EMP ID : 164935 Store Number : 02895 Router ID : MX68CW_NA Computer Name : 02895-7QNCID3 IP Address: 10.111.78.60 | G38: RACPad Support | H38: muniraja p | I38: Store Network | M38: Store | N38: RACPAD slowness
A39: INCTEC1592214 | B39: 46055.452 | C39: 4 - Low | D39: Closed | E39: RACPAD - Payment | CCCB | | F39: Customer stated that She has checked with her back and there has been no charge backs on her account that every payment has gone through. Customer will bring in her Bank statements for last two months Agreement Number: 479680609 Customer ID: 6061344 Customer Name: Steven Peacock Date and Time Issue Was Occured: 2025-12-18 10:47:37 | G39: RACPad Support | H39: Hemanth Mangalore | I39: RACPAD - Payment | M39: Payment | N39: CCCB related query
A40: INCTEC1592231 | B40: 46055.464 | C40: 4 - Low | D40: Closed | E40: RACPAD-cash Box Issue | F40: Store number: 01201 Coworker name and ID: Victor CentenoII || 363211 Customer name and number: - Computer name: 01201-DX7BV93 Issue description: issue with Deposit amount or cash Box RACPAD Steps taken to arrive at problem: RACPAD | G40: RACPad Support | H40: shweta wadhwa | I40: RACPAD - Cash Management | M40: Cash Management | N40: Cash box issue
A41: INCTEC1592753 | B41: 46056.534 | C41: 4 - Low | D41: Closed | E41: RACPAD - Payment | Customer Refund | | F41: Customer Name: Makwayah Shepperson Last 4 of Card Used: 4424 Exact Amount of Refund: $129.17 Exact Date of Refund: 02/03/2026 Agreement or Receipt #: 455771395 Detailed Description of Issue: This customer placed an order for a Midnight Madness sectional with us. We attempted the delivery today and found the sectional didn't fit in the customer's home. The customer then found an item that she was interested in that would fit in the home and we decided to do a RAC exchange for the product since she had put $129.17 down at the start of the original agreement. We scheduled the carryout for the new couch with her and then she called back later and requested to cancel the order and requested a full refund since she hadn't actually received any products. I attempted to preform the refund however it only allowed me to refund the club membership payment not the rental amount so I didn't complete that refund. I attached a copy of the original receipt. Please assist. Thank you in advance for any assistance in this matter! | G41: RACPad Support | H41: Abhishek TV | I41: RACPAD - Payment | K41: PRB0044395 | M41: Payment | N41: Customer refund | O41: Reccurring
A42: INCTEC1592238 | B42: 46055.468 | C42: 4 - Low | D42: Closed | E42: RACPAD - Agreement | Agreement - Other | | F42: Customer order, order came in, i went to activate it, the accept payment button is greyed out and i can not move on from it. Agreement Number: 8174528433 Customer ID: 100016228355 Customer Name: Jerry Watson Date and Time Issue Was Occured: 2026-01-29 11:13:21 | G42: RACPad Support | H42: atulashok shinde | I42: RACPAD - Agreement | M42: Agreement | N42: Accept Payment button greyed out
A43: INCTEC1592253 | B43: 46055.485 | C43: 4 - Low | D43: Closed | E43: Racpad Customer | F43: CW need a report that shows customer contact number that is recently changed on racpad | G43: RACPad Support | H43: dazel dsouza | I43: RACPAD - Customer | M43: Customer | N43: Data request
A44: INCTEC1592257 | B44: 46055.487 | C44: 3 - Moderate | D44: Closed | E44: BigPanda Incident: campaignstatistics - Ok | F44: Incident Summary: -------------------------------------------------------- AI-Generated Incident Analysis Resolved: campaignstatistics Lambda Foreign Key Violation in prod2 (AWS) On February 2, 2026, at 17:36:15 UTC, two alerts for the 'campaignstatistics' application in the 'prod2' AWS environment reported a previously resolved database error. The issue involved a foreign key violation in a Lambda function, but the system is now healthy. No user tickets or ongoing impact detected. At 17:36:15 UTC on February 2, 2026, two alerts reported a resolved state for the 'campaignstatistics' application in 'prod2' (AWS). The underlying issue was a database foreign key violation (PostgreSQL error 23503) in the 'ProcessCampaignStatsService' Lambda, caused by a missing 'customer_id' in the 'customer' table. The alerts indicate the error condition has cleared. PostgreSQL error 23503 signals a foreign key violation, meaning an operation tried to reference a non-existent 'customer_id' in the 'customer' table. This is enforced by relational database integrity constraints. The Lambda function 'ProcessCampaignStatsSubscriptionFilter' likely attempted to insert or update 'account_management_activity' with a 'customer_id' not present in 'customer', triggering a 500 error. The alerts, both marked 'Ok', confirm the error condition was transient and has since resolved, suggesting either the missing customer was added or the process was corrected. No flapping or ongoing issues are present, and no user tickets indicate broader impact. | G44: RACPad Support | H44: Vandana K | M44: BigPanda | N44: BigPanda
A45: INCTEC1592266 | B45: 46055.499 | C45: 3 - Moderate | D45: Closed | E45: BigPanda Incident: htinventorytransfer - Critical | F45: Incident Summary: -------------------------------------------------------- AI-Generated Incident Analysis Critical: htinventorytransfer Lambda 500 Errors Across Multiple Stores in prod2 AWS A critical incident occurred in prod2 (AWS) from 17:53:08Z to 19:45:17Z, with 6 critical and 20 warning alerts, mainly impacting the 'htinventorytransfer' Lambda across multiple stores. All affected invocations failed with HTTP 500 errors, indicating a backend or dependency outage. Other apps had isolated errors. No flapping observed. Between 17:53:08Z and 19:45:17Z on Feb 2, 2026, the 'htinventorytransfer' Lambda (prod2, AWS) generated repeated critical and warning alerts for multiple stores, all with HTTP 500 errors ('unable to retrieve transfer list!'). This pattern, across stores and times, indicates a systemic backend or dependency failure, not isolated to a single store or invocation. AWS Lambda functions, like 'htinventorytransfer', act as stateless compute triggered by events, often querying backend services or databases. HTTP 500 errors mean the function executed but encountered an unhandled exception, typically from a failed dependency (e.g., database, API). The repeated, multi-store 500s over nearly 2 hours suggest a persistent backend outage or misconfiguration, not transient or input-specific issues. The absence of flapping and the presence of both critical and warning alerts across different stores and times reinforce that the root cause is a shared backend service or resource, not the Lambda code itself. Other applications show isolated errors, but only htinventorytransfer exhibits widespread, sustained failures, supporting a backend dependency as the root cause. | G45: RACPad Support | H45: Vandana K | M45: BigPanda | N45: BigPanda
A46: INCTEC1592276 | B46: 46055.506 | C46: 4 - Low | D46: Work Started | E46: RACPAD - Store | DAP Events | | F46: Store number: 02356 Coworker name and ID: Chris Clow 238050 Issue description: > We cannot access the customer survey in the DAP. >The page has rolled back to one of its previous version UI(refer attached SS) when clicked on any Event >The page does not have the customer survey button | G46: RACPad Support | H46: Aditi Agarwal | I46: RACPAD - Store | M46: Store | N46: Unable to access customer survey
A47: INCTEC1592290 | B47: 46055.532 | C47: 3 - Moderate | D47: Closed | E47: BigPanda Incident: cloud2gcdb - Ok | F47: Incident Summary: -------------------------------------------------------- AI-Generated Incident Analysis Resolved Transient Event Processing Errors in cloud2gcdb Application (Production) From 18:40:13 to 20:05:10 UTC on Feb 2, 2026, 29 resolved alerts indicated transient errors in the 'cloud2gcdb' application (prod2-cloud2gcdb-lambda-Cloud2GcdbSubscriptionFilter) in the Production environment. All alerts are now Ok, with no ongoing impact. No user tickets or persistent issues were identified. Between 18:40:13 and 20:05:10 UTC on Feb 2, 2026, 29 alerts reported errors in processing 'POST-PAYMENT', 'UPDATE-AGREEMENT', and 'UPDATE-CUSTOMER' events in the 'cloud2gcdb' application (prod2-cloud2gcdb-lambda-Cloud2GcdbSubscriptionFilter). All alerts are now Ok, indicating the underlying issue was transient and has been resolved. No evidence of persistent or systemic failure. AWS Lambda functions (here, prod2-cloud2gcdb-lambda-Cloud2GcdbSubscriptionFilter) process event-driven workloads. Errors in processing events like 'POST-PAYMENT' can arise from transient issues such as temporary downstream service unavailability, malformed event payloads, or brief resource contention. The rapid succession and subsequent resolution of all alerts (status Ok) suggest that the Lambda function or its dependencies experienced a short-lived disruption, which self-corrected or was remediated automatically (e.g., via retries or infrastructure healing). The absence of critical or warning alerts, and the lack of ongoing issues, further supports that this was a resolved, non-persistent incident. No user-reported tickets or historical actions indicate broader impact or required manual intervention. | G47: RACPad Support | H47: Vandana K | M47: BigPanda | N47: BigPanda
A48: INCTEC1592305 | B48: 46055.541 | C48: 4 - Low | D48: Closed | E48: Recover Item on to Inventory - Store 895 | F48: Julie, We were able to recover the stand of a TV/Stand package that was charged off recently for a Skip/Stolen account under the name Christopher Miner. The item number is: 9999219943149 Serial number :64" Cayberry Black RV: $160.54. Are you able to help us recover this in the system so that we are able to resell it? Your assistance is greatly appreciated! Thank you, Katie Moeller Store Manager Rent A Center #00895 605-343-3600 | G48: RACPad Support | H48: Sreenivasa Ks | I48: RACPAD - Inventory | M48: Inventory | N48: Recover the inventory
A49: INCTEC1592315 | B49: 46055.546 | C49: 4 - Low | D49: Closed | E49: For some reason I am having issues receiving in a item? | F49: PO # 16303477 Model # D388D1 Serial # 672618368776 For some reason it is telling me unable to receive in? Thank You, Store 02729 | G49: RACPad Support | H49: yash zadap | I49: RACPAD - Store | M49: Inventory | N49: Unable to receive the purchase order
A50: INCTEC1592329 | B50: 46055.556 | C50: 4 - Low | D50: Closed | E50: Racpad || Agreement is not showing | F50: Issue : The Customer Does not shoe the active agreement in the Racpad but she does have 2 agreement Customer name: Jewell Amy Customer ID: 111315501 Agreement number: 8174274509 Agreement number: 8171773546 | G50: RACPad Support | H50: Vishal Shukla | I50: RACPAD - Agreement | M50: Agreement | N50: Agreement not showing
A51: INCTEC1592332 | B51: 46055.558 | C51: 4 - Low | D51: Closed | E51: RACPAD - Agreement | Customer Order | | F51: When processing payment to start agreement on this customer order we are met with an error screen and advised to submit ticket to resolve issue. Agreement Number: 8174658355 Customer ID: 1621050 Customer Name: ERNEST TILLERY Date and Time Issue Was Occured: 2026-02-02 13:20:22 | G51: RACPad Support | H51: atulashok shinde | I51: RACPAD - Agreement | M51: Payment | N51: There was an error processing your request popup
A52: INCTEC1592337 | B52: 46055.561 | C52: 4 - Low | D52: Closed | E52: RACFI-RACPAD - other | RACPAD AltPay | | F52: Auto Pay is not sending the customers number to them | G52: RACPad Support | H52: Jitheesha Thankachan | I52: RACPAD - other | M52: Customer | N52: AutoPay
A53: INCTEC1592794 | B53: 46056.591 | C53: 4 - Low | D53: Closed | E53: RACPAD | F53: User called in for unable to do refund Store number: 03946 - ROXBURY-WASHINGTON - A - M0028 - R0002 - S07 - RACUSA Coworker name and ID: Jahaira Sanchez 198199 Customer name and number: Shaniqua Williams 114901040 Agreement: 8174567481 Receipt: 454764922 Computer name: 03946-HMP31D3 IP address: 10.115.105.58 Issue description: User called in for unable to do refund Steps taken to arrive at problem: Time of occurrence (Recreate the issue and notate the time if needed): Screen shot required: YES | G53: RACPad Support | H53: racha sahithya | I53: RACPAD - Payment | K53: PRB0044395 | M53: Payment | N53: Customer refund | O53: Reccurring
A54: INCTEC1592894 | B54: 46056.72 | C54: 4 - Low | D54: Closed | E54: RACFI-RACPAD - Payment | Customer Refund | | F54: unable to refund customer web deposit Agreement Number: 455793271, 455793271 Customer ID: RASHIDA BELL (114933658) Customer Name: RASHIDA BELL Date and Time Issue Was Occured: 2026-02-03 17:15:58 | G54: RACPad Support | H54: shruthika c | I54: RACPAD - Payment | K54: PRB0044395 | M54: Payment | N54: Customer refund
A55: INCTEC1593605 | B55: 46058.547 | C55: 4 - Low | D55: Closed | E55: RACPAD - Payment | Customer Refund | | F55: Customer needs refund for the last payment but the items were already taken down. Agreement Number: William Hooker Customer ID: 02/03/2026 Customer Name: 110823116 Date and Time Issue Was Occured: 2026-02-05 13:07:31 | G55: RACPad Support | H55: Lalit RameshTurkar | I55: RACPAD - Payment | K55: PRB0044395 | M55: Payment | N55: Customer refund | O55: Reccurring
A56: INCTEC1592358 | B56: 46055.589 | C56: 4 - Low | D56: Closed | E56: RACPAD - Inventory | Unable to receive PO | | F56: Can not receive P.O. 16299152 Inventory Number: 3:00pm Date and Time Issue Was Occured: 2026-02-02 14:06:33 | G56: RACPad Support | H56: dazel dsouza | I56: RACPAD - Inventory | M56: Inventory | N56: Unable to receive the purchase order
A57: INCTEC1592360 | B57: 46055.59 | C57: 3 - Moderate | D57: Closed | E57: BigPanda Incident: agreementdocument - Ok | F57: Incident Summary: -------------------------------------------------------- AI-Generated Incident Analysis Resolved: Transient Backend Errors Across Multiple Production Applications (prod2) From 20:04:13 to 21:49:13 UTC on Feb 2, 2026, 13 alerts reported transient backend/server errors across multiple production applications (agreementdocument, appointment, survey, accountmanagement, customer, RMS) in the prod2 environment (AWS, Colo - Cyrus). All alerts are now Ok, with no ongoing impact or flapping. Between 20:04:13 and 21:49:13 UTC on Feb 2, 2026, multiple production services (agreementdocument, appointment, survey, accountmanagement, customer, RMS) experienced transient backend/server errors (HTTP 500/400, DB constraint violations). All alerts are now Ok, indicating the issues were resolved. No single root cause identified; errors were distributed and cleared. The alerts show transient errors in AWS Lambda and ECS-based microservices, with HTTP 500/400 codes and DB constraint violations. In distributed cloud architectures, such errors often result from temporary backend, database, or integration issues. The lack of ongoing alerts and the Ok status for all indicate self-recovery or successful remediation. No evidence links these errors to a single systemic failure; rather, they reflect independent, resolved incidents typical in complex, service-oriented environments. The absence of flapping and user tickets further supports that these were isolated, short-lived backend issues. | G57: RACPad Support | H57: Vandana K | M57: BigPanda | N57: BigPanda
A58: INCTEC1592369 | B58: 46055.612 | C58: 4 - Low | D58: Closed | E58: L #: 661100 SHORT | F58: 12/10/225 Ortiz Colon, Yannir receipt 00058244 card: 0989 amount $207.03 12/12/25 Ramkhalawan, Rajesh receipt 00058254 card: 6946 amount: $255.77 12/13/25 Rosa Ortiz, Carmen receipt 00058259 card: 6410 amount $99.70 Lopez Cabrera, Celeste receipt 00058262 card: 3617 amount $155.89 12/15/25 Cruz Villalba Ginelisse receipt 00058265/00058264 card:8400 amount $182.11 | G58: RACPad Support | H58: Hemanth Mangalore | I58: RACPAD - Customer | M58: Other | N58: Not a RACPAD issue
A59: INCTEC1592375 | B59: 46055.617 | C59: 4 - Low | D59: Closed | E59: RACPAD - Payment | Customer Refund | | F59: Customer Name: Leona Lolohea Last 4 of Card Used: 1162 Exact Amount of Refund: 198.17 Exact Date of Refund: Agreement or Receipt #: Detailed Description of Issue: customer want's refund on Coa on account $198.17 | G59: RACPad Support | H59: Ashwini Shetty | I59: RACPAD - Payment | M59: Payment | N59: Customer refund
A60: INCTEC1592379 | B60: 46055.62 | C60: 4 - Low | D60: Closed | E60: RACFI-Racpad || Agreement || Customer Order | F60: Issue: Not able to create a Agreement for the customer order Customer Name: ARMANDO CRUZ Customer ID: 4629063 Model Number: NW00107 | G60: RACPad Support | H60: atulashok shinde | I60: RACPAD - Agreement | M60: Agreement | N60: Error in RmsReserveOrderService
A61: INCTEC1592387 | B61: 46055.632 | C61: 3 - Moderate | D61: Closed | E61: BigPanda Incident: cloud2gcdb - Ok | F61: Incident Summary: -------------------------------------------------------- AI-Generated Incident Analysis Resolved: cloud2gcdb Lambda Event Processing Errors Across Multiple Stores (prod2) On Feb 2, 2026, between 21:05 and 22:05 UTC, 20 resolved alerts reported transient errors in processing POST-PAYMENT and UPDATE-AGREEMENT events by the prod2-cloud2gcdb-lambda-Cloud2GcdbSubscriptionFilter in the prod2 (Production) environment, affecting multiple stores. All issues are now resolved; no ongoing impact. Between 21:05:08 and 22:05:14 UTC on Feb 2, 2026, 20 alerts reported errors in processing POST-PAYMENT and UPDATE-AGREEMENT events by the prod2-cloud2gcdb-lambda-Cloud2GcdbSubscriptionFilter. All alerts are now Ok, indicating the errors were transient and have been resolved. No ongoing root cause remains. AWS Lambda functions process events asynchronously; errors in event processing (e.g., POST-PAYMENT) are logged to CloudWatch and can trigger alerts. The cwl (CloudWatch Logs) alerts here indicate that the Lambda function encountered errors for specific events across multiple stores. However, all alerts have status Ok, meaning the system either retried and succeeded or the underlying issue was fixed. The absence of critical/warning alerts and the Ok incident status confirm resolution. No evidence suggests persistent infrastructure or application faults. The incident reflects transient, self-resolving errors typical in distributed event-driven architectures, where retries or automated remediation restore normal operation. | G61: RACPad Support | H61: Vandana K | M61: BigPanda | N61: BigPanda
A62: INCTEC1592398 | B62: 46055.647 | C62: 4 - Low | D62: Closed | E62: RACPAD - Pricing | Pricing Uploads | | F62: Trying tochange a RMS # to 4 months same as cash. It is not updating the item and the customer is only geting 90 days same as cash. PMS # 200050363 put on agreement 8174704905 | G62: RACPad Support | H62: muniraja p | I62: RACPAD - Pricing | M62: Operations | N62: SAC configuration
A63: INCTEC1592401 | B63: 46055.651 | C63: 4 - Low | D63: Closed | E63: RACPAD - Customer | Customer - Other | | F63: CUSTOMER UNABLE TO ACCESS ONLINE ACCOUNT Customer ID: 5265665 Customer Name: KEWAN HOLDER Date and Time Issue Was Occured: 2026-02-02 15:36:41 | G63: RACPad Support | H63: Vishal Shukla | I63: RACPAD - Customer | M63: Access | N63: Access
A64: INCTEC1592402 | B64: 46055.651 | C64: 4 - Low | D64: Closed | E64: Issue with Autopay and IntelliCheck | F64: Store number: 01952 Coworker name and ID: Ric Kollin 219483 Customer name and number: Jaiontre Hall 310566 Issue description: >Customer is not getting Autopay link or the Intellicheck link from Racpad >Customer did receive the message for digital code for agreement verification >But the customer is not receiving Autopay and IntelliCheck link text message | G64: RACPad Support | H64: Ashwini Shetty | I64: RACPAD - Payment | M64: Customer | N64: AutoPay
A65: INCTEC1592405 | B65: 46055.66 | C65: 4 - Low | D65: Closed | E65: identity link not working | F65: Store number: 01952 Coworker name and ID: Ric Kollin 219483 Customer name and number: MAry Abraham 2808796 Issue description: Customer received the link but is unable to open it. CW confirmed that clicking the link does not trigger any action | G65: RACPad Support | H65: Spoorthi GS | I65: RACPAD - Customer | M65: Customer | N65: Identity link not working
A66: INCTEC1592406 | B66: 46055.662 | C66: 4 - Low | D66: Closed | E66: identity link not working | F66: Store number: 01952 Coworker name and ID: Ric Kollin 219483 Customer name and number: James Bruning 2806005 Issue description: Customer received the link but is unable to open it. CW confirmed that clicking the link does not trigger any action | G66: RACPad Support | H66: Spoorthi GS | I66: RACPAD - Customer | M66: Customer | N66: Identity link not working
A67: INCTEC1592407 | B67: 46055.665 | C67: 4 - Low | D67: Closed | E67: RACPAD-Unable to Create Agreement in RACPAD | F67: Store number: 03546 Coworker name and ID: Elizabeth Swanson || 328543 Customer name and number: Gerald Bromagem || 110300988 Computer name: 03546-6PMC1D3 Issue description: Unable to Create Agreement in RACPAD Steps taken to arrive at problem: RACPAD-CUSTOMER-Agreement | G67: RACPad Support | H67: Syeda Asfiya | I67: RACPAD - Customer | M67: Agreement | N67: Unable to create an Agreement
A68: INCTEC1592409 | B68: 46055.666 | C68: 4 - Low | D68: Closed | E68: identity link not working | F68: Store number: 01952 Coworker name and ID: Ric Kollin 219483 Customer name and number: Vernon Roberts 2808273 Issue description: Customer received the link but is unable to open it. CW confirmed that clicking the link does not trigger any action | G68: RACPad Support | H68: Manish Rawat | I68: RACPAD - Customer | M68: Customer | N68: Identity link not working
A69: INCTEC1592412 | B69: 46055.668 | C69: 4 - Low | D69: Closed | E69: identity link not working | F69: Store number: 01952 Coworker name and ID: Ric Kollin 219483 Customer name and number: Jaiontre Hall 310566 Issue description: Customer received the link but is unable to open it. CW confirmed that clicking the link does not trigger any action | G69: RACPad Support | H69: Spoorthi GS | I69: RACPAD - Customer | M69: Customer | N69: Identity link not working
A70: INCTEC1592415 | B70: 46055.669 | C70: 4 - Low | D70: Closed | E70: identity link not working | F70: Store number: 01952 Coworker name and ID: Ric Kollin 219483 Customer name and number: Jenny Lanier 114950572 Issue description: Customer received the link but is unable to open it. CW confirmed that clicking the link does not trigger any action | G70: RACPad Support | H70: Spoorthi GS | I70: RACPAD - Customer | M70: Customer | N70: Identity link not working
A71: INCTEC1592417 | B71: 46055.67 | C71: 4 - Low | D71: Awaiting User Info | E71: identity link not working | F71: Store number: 01952 Coworker name and ID: Ric Kollin 219483 Customers name and number: 1. Trevor Mccallin 2807684 (330 598 3128) 2. MAry Abraham 2808796 (330 907 2053) 3. James Bruning 2806005 (234 499 6435) 4. Jaiontre Hall 310566 (231 419 6155) 5. Jenny Lanier 114950572 (234 419 6155) Issue description: Customer received the link but is unable to open it. CW confirmed that clicking the link does not trigger any action | G71: RACPad Support | H71: Spoorthi GS | I71: RACPAD - Customer | M71: Customer | N71: Identity link not working
A72: INCTEC1592420 | B72: 46055.674 | C72: 4 - Low | D72: Closed | E72: RACPAD - Account Management | Account Management - Other | | F72: Customer is on legal hold. We cannot explain why she has a great payment history has been with us since the 80s or 90s and we cannot write an agreement for her. She has a back rent amount of about 270 dollars but that's never resulted in a skip/stolen mark before. Please help us resolve thank you. Customer ID: 4636077 Customer Name: Carol Fengolio Date and Time Issue Was Occured: 2026-01-30 16:07:36 | G72: RACPad Support | H72: yash zadap | I72: RACPAD - Account Management | M72: Customer | N72: Remove Legal hold
A73: INCTEC1592421 | B73: 46055.674 | C73: 3 - Moderate | D73: Closed | E73: BigPanda Incident: processpayment - Ok | F73: Incident Summary: -------------------------------------------------------- AI-Generated Incident Analysis Critical: AWS prod2 htinventorytransfer Lambda Outage Causing Transfer List Retrieval Failures Across Multiple Stores On Feb 2, 2026, from 22:33 to 23:52 UTC, a critical incident affected 'htinventorytransfer' in AWS prod2. 8 critical, 21 warning, and 24 ok alerts were generated, mainly due to persistent 500 errors in the Lambda function across multiple stores. Other applications showed minor issues, but the main impact was on inventory transfer operations. Between 22:33:17 and 23:52:09 UTC on Feb 2, 2026, repeated critical and warning alerts for 'prod2-htinventorytransfer-lambda-GetHtTransferSubscriptionFilter' in AWS prod2 show persistent 500 errors ('unable to retrieve transfer list!') across multiple stores. This indicates a systemic failure in the htinventorytransfer Lambda function, likely due to a backend or configuration issue. AWS Lambda functions are stateless, event-driven compute services. The 'htinventorytransfer' Lambda repeatedly returned HTTP 500 errors, a generic server-side failure, across many stores and over multiple invocations. This suggests the issue is not isolated to a single event or input, but systemic—possibly due to a failed dependency (e.g., database, API), misconfiguration, or code regression. The error persisted for nearly 2 hours, with no evidence of recovery or flapping, and affected multiple stores, ruling out transient or localized issues. Other applications had warning/ok alerts, but only htinventorytransfer had sustained criticals, confirming it as the root cause. The Lambda's inability to retrieve transfer lists points to a failure in its core logic or its dependencies, such as a database outage, network partition, or permission/configuration error. The consistent error message and broad impact support this conclusion. | G73: RACPad Support | H73: Vandana K | M73: BigPanda | N73: BigPanda
A74: INCTEC1592424 | B74: 46055.68 | C74: 4 - Low | D74: Closed | E74: RACPAD - Store | RACPAD Store issue | | F74: Typed up 1 Agreement and notice in my daily report, it showed we used over $1,200 in promo free time but, we only used 12 day's of free time which only should of been $55 and some change we did use the trifecta promo code. Employee : Phillip Hernandez Store : 02198 Customer : Rosalinda Silva Agreement : 8174702800 Receipt : 456273350 Promo code used : TRIFECTA Description : The Store used the free time only for 12 days and it should be only $55 but in the racpd daily report it is showing $1204.55 | G74: RACPad Support | H74: Rashmitha Shetty | I74: RACPAD - Store | M74: Report | N74: Report issues
A75: INCTEC1593731 | B75: 46058.7 | C75: 4 - Low | D75: Closed | E75: RACFI-RACPAD - Payment | Customer Refund | | F75: Customer Name: Nichole Ramos Last 4 of Card Used: 0811 Exact Amount of Refund: $116.18 Exact Date of Refund: 2/5/26 Agreement or Receipt #: Receipt :456410092 Detailed Description of Issue: payment was supposed to have been extended to the 20th, was pull on 2/4/26 | G75: RACPad Support | H75: racha sahithya | I75: RACPAD - Payment | K75: PRB0044395 | M75: Payment | N75: Customer refund
A76: INCTEC1592430 | B76: 46055.689 | C76: 4 - Low | D76: Closed | E76: RACPAD Account management issue | F76: Co-worker name: Kathleen Morocco Employee ID: 87901 Store: 02141 Customer Name: Kelly Patridge Customer ID: 1074459288 Issue: CW mentioned in account management for this customer she is unable to check customer phone number and text option for SMS is also missing. Need help with this. | G76: RACPad Support | H76: yash zadap | I76: RACPAD - Account Management | M76: Account Management | N76: Missing text option
A77: INCTEC1595050 | B77: 46062.7 | C77: 4 - Low | D77: Closed | E77: RACFI-Racpad - Refund issue | F77: When trying to process a refund to a customer it gives an error as not eligible | G77: RACPad Support | H77: Tejas Acharya | I77: RACPAD - Payment | K77: PRB0044395 | M77: Payment | N77: Customer refund | O77: Reccurring
A78: INCTEC1592437 | B78: 46055.704 | C78: 4 - Low | D78: Closed | E78: RACPAD - Customer | Unable to update customer | | F78: unable to save phone number and debit card information Customer ID: 109600283 Customer Name: Kelly Miranda Date and Time Issue Was Occured: 2026-02-02 16:51:37 | G78: RACPad Support | H78: Manish Rawat | I78: RACPAD - Customer | M78: Customer | N78: Unable to save customer phone number
A79: INCTEC1595055 | B79: 46062.705 | C79: 4 - Low | D79: Resolved | E79: Need to revert Receipt and remove Autopay on Customer's account | F79: Store number: 02141 Coworker name and ID: Kathleen Morocco 87901 Customer name and number: Dayssy Lara 113905594 Agreement #: 8174652703 8173179687 Benefit Plus#: 100015678635 Card: 1640 Receipt: 456701191, 455316724 and 454674090 Issue description: >Need to revert Receipt: 456701191, 455316724 and 454674090 back to card ending with 1640 >This card actually belongs to another customer with same first name >Store will work with Dayssy Lara 113905594 to get the due payments after the money are refunded >Need to remove above agreement and benefit plus account from Autopay too so store can remove the card from customer Dayssy Lara's account >Some CW has put his card on this user's profile and CW cannot remove the card from user's profile as above agreement and benefit plus are on Autopay | G79: RACPad Support | H79: Hemanth Mangalore | I79: RACPAD - Payment | K79: PRB0044395 | M79: Payment | N79: reverse receipt
A80: INCTEC1592440 | B80: 46055.716 | C80: 3 - Moderate | D80: Closed | E80: BigPanda Incident: cloud2gcdb - Ok | F80: Incident Summary: -------------------------------------------------------- AI-Generated Incident Analysis Resolved Lambda Event Processing Errors for cloud2gcdb in prod2 Environment From Feb 2, 2026, 23:05 UTC to Feb 3, 2026, 00:05 UTC, 20 Ok alerts indicated resolved errors in the 'cloud2gcdb' Lambda (prod2-cloud2gcdb-lambda-Cloud2GcdbSubscriptionFilter) across multiple stores in the prod2 environment. No active issues remain; all systems are operating normally. Between 23:05:15 UTC (Feb 2, 2026) and 00:05:10 UTC (Feb 3, 2026), 20 alerts reported errors in processing POST-PAYMENT events via the 'prod2-cloud2gcdb-lambda-Cloud2GcdbSubscriptionFilter' Lambda. All alerts are now Ok, indicating the underlying issue was transient and has been resolved. No current errors are present. AWS Lambda functions process events asynchronously; errors in event processing (e.g., POST-PAYMENT) can trigger alerts if failures occur, often due to downstream service issues, malformed data, or resource constraints. The alerts' Ok status means the Lambda resumed normal operation. The clustered timestamps suggest a brief, distributed issue, now cleared, with no evidence of persistent or systemic failure. | G80: RACPad Support | H80: Vandana K | M80: BigPanda | N80: BigPanda
A81: INCTEC1595696 | B81: 46064.507 | C81: 4 - Low | D81: Resolved | E81: RACPAD payment issue | F81: CW wants to reverse the payment, ,when she tried to reverse it getting error : 'No eligible payment found for this customer to reverse Customer Name: Rochelle Phillips Customer ID:114948623 Agreement Number: 8174685767 Receipt- 455911510 Date and Time issue was occurred: Description of issue: | G81: RACPad Support | H81: Vandana K | I81: RACPAD - Agreement | K81: PRB0044395 | M81: Payment | N81: Customer refund | O81: Reccurring
A82: INCTEC1592460 | B82: 46055.763 | C82: 4 - Low | D82: Closed | E82: RACPAD - Inventory | Acima PO Receiving | | F82: Item needs to cleared from my idle inventory po list. Item didnt arrive or accepted. Inventory Number: M1223231396 Date and Time Issue Was Occured: 2025-11-26 18:17:47 | G82: RACPad Support | H82: ankita singh | I82: RACPAD - Inventory | M82: Inventory | N82: Clear from idle inventory PO list
A83: INCTEC1592461 | B83: 46055.765 | C83: 4 - Low | D83: Closed | E83: RACPAD - Inventory | Acima PO Receiving | | F83: Needs to be cleared from my inventory, item was not delivered or received at this location. Inventory Number: M1224789516 Date and Time Issue Was Occured: 2025-11-17 18:20:36 | G83: RACPad Support | H83: ankita singh | I83: RACPAD - Inventory | M83: Inventory | N83: Cancel the Manual PO | O83: Reccurring
A84: INCTEC1595975 | B84: 46065.416 | C84: 4 - Low | D84: Closed | E84: RACPAD - Payment | WL Deposit | | F84: It will not issue his refund, it's been over 2 weeks. It does nothing when we hit the refund button. Agreement Number: N/A Customer ID: 110560403 Customer Name: Joshua Woodard Date and Time Issue Was Occured: 2026-01-24 09:52:26 | G84: RACPad Support | H84: Rashmitha Shetty | I84: RACPAD - Payment | K84: PRB0044395 | M84: Payment | N84: Customer refund
A85: INCTEC1592464 | B85: 46055.767 | C85: 4 - Low | D85: Closed | E85: Enable/Disable the Customer Order module in RACPad for Eclipse RTO S098_R0999. | F85: Enable/Disable the Customer Order module in RACPad for Eclipse RTO S098_R0999 as per below schedule. End date the current rule and assign the same rule after 2:00PM CST on Tuesday 2/3/26. | G85: RACPad Support | H85: Siva Bhargavi | I85: RACPAD - other | M85: Admin | N85: Config changes
A86: INCTEC1592468 | B86: 46055.77 | C86: 3 - Moderate | D86: Closed | E86: BigPanda Incident: htinventorytransfer - Ok | F86: Incident Summary: -------------------------------------------------------- AI-Generated Incident Analysis On February 2, 2026, from 16:02 to 16:54 UTC, 14 Ok alerts were generated for 'htinventorytransfer' in AWS prod2, indicating recovery from prior Lambda failures (HTTP 500 errors) affecting multiple stores. All systems are now operational, with no ongoing impact. No user tickets or flapping detected. Alert Summary: 0 Critical, 0 Warning, 14 Resolved -------------------------------------------------------- Alert: 1 / 14 Status: Ok Source: api.logzio_custom Check: Cloud(TS) Services BigPanda Alerts Application: htinventorytransfer Description: Outbound Message: {"body":{"errors":[{"code":"500","message":"unable to retrieve transfer list!"},"stackTrace":""},"headers":{"Access-Control-Allow-Origin":"*","requestId":"fab4b70b-db03-47ba-9be6-4f13717f89b1","userId":"368511","clientId":"RACPAD","correlationId":"839a64fd-3f1e-40ad-a0db-840f798534f2","storeNumber":"00122"},"statusCode":500} Alert: 2 / 14 Status: Ok Source: api.logzio_custom Check: Cloud(TS) Services BigPanda Alerts Application: htinventorytransfer Description: Outbound Message: {"body":{"errors":[{"code":"500","message":"unable to retrieve transfer list!"}],"stackTrace":""},"headers":{"Access-Control-Allow-Origin":"*","requestId":"d4ea609d-5e7d-466e-8c9d-95c814562384","userId":"129411","clientId":"RACPAD","correlationId":"b8218712-7f52-4131-8801-4b713b900327","storeNumber":"00521"},"statusCode":500} Alert: 3 / 14 Status: Ok Source: api.logzio_custom Check: Cloud(TS) Services BigPanda Alerts Application: htinventorytransfer Description: Outbound Message: {"body":{"errors":[{"code":"500","message":"unable to retrieve transfer list!"}],"stackTrace":""},"headers":{"Access-Control-Allow-Origin":"*","requestId":"e7b4cec3-f041-466c-baba-4b1ac3c69b60","userId":"346387","clientId":"RACPAD","correlationId":"1d31ef0b-03d9-48f6-8105-c7b3f4a1daf9","storeNumber":"03833"},"statusCode":500} Alert: 4 / 14 Status: Ok Source: api.logzio_custom Check: Cloud(TS) Services BigPanda Alerts Application: htinventorytransfer Description: Outbound Message: {"body":{"errors":[{"code":"500","message":"unable to retrieve transfer list!"}],"stackTrace":""},"headers":{"Access-Control-Allow-Origin":"*","requestId":"fb3e771a-8842-4a23-ba79-b8d4757ddd49","userId":"346387","clientId":"RACPAD","correlationId":"007fa2cf-afd3-4eab-a7c5-c144ad338011","storeNumber":"03833"},"statusCode":500} Alert: 5 / 14 Status: Ok Source: api.logzio_custom Check: Cloud(TS) Services BigPanda Alerts Application: htinventorytransfer Description: Outbound Message: {"body":{"errors":[{"code":"500","message":"unable to retrieve transfer list!"}],"stackTrace":""},"headers":{"Access-Control-Allow-Origin":"*","requestId":"73946a19-7484-464b-8544-8fcee7ad6925","userId":"346387","clientId":"RACPAD","correlationId":"8c865af6-584e-4422-9cc8-39ac0ca08d65","storeNumber":"03833"},"statusCode":500} Alert: 6 / 14 Status: Ok Source: api.logzio_custom Check: Cloud(TS) Services BigPanda Alerts Application: htinventorytransfer Description: Outbound Message: {"body":{"errors":[{"code":"500","message":"unable to retrieve transfer list!"}],"stackTrace":""},"headers":{"Access-Control-Allow-Origin":"*","requestId":"1a638bb2-ac13-40ac-afef-ffad148e5457","userId":"346387","clientId":"RACPAD","correlationId":"bfdd90a2-ffa6-46c9-a1b9-ad02c57cf3c5","storeNumber":"03833"},"statusCode":500} Alert: 7 / 14 Status: Ok Source: api.logzio_custom Check: Cloud(TS) Services BigPanda Alerts Application: htinventorytransfer Description: Outbound Message: {"body":{"errors":[{"code":"500","message":"unable to retrieve transfer list!"}],"stackTrace":""},"headers":{"Access-Control-Allow-Origin":"*","requestId":"3861d837-3828-48fa-a2ec-5dad409ff722","userId":"346387","clientId":"RACPAD","correlationId":"99ea6ca6-5ad2-4e1f-b34e-3c568275f4f1","storeNumber":"03833"},"statusCode":500} Alert: 8 / 14 Status: Ok Source: api.logzio_custom Check: Cloud(TS) Services BigPanda Alerts Application: htinventorytransfer Description: Outbound Message: {"body":{"errors":[{"code":"500","message":"unable to retrieve transfer list!"},"stackTrace":""},"headers":{"Access-Control-Allow-Origin":"*","requestId":"426684c1-8261-4fcd-a9a6-61c09ff71495","userId":"346387","clientId":"RACPAD","correlationId":"5064c29a-7941-46e9-b727-4fa4fe048ac3","storeNumber":"03833"},"statusCode":500} Alert: 9 / 14 Status: Ok Source: api.logzio_custom Check: Cloud(TS) Services BigPanda Alerts Application: htinventorytransfer Description: Outbound Message: {"body":{"errors":[{"code":"500","message":"unable to retrieve transfer list!"},"stackTrace":""},"headers":{"Access-Control-Allow-Origin":"*","requestId":"b12ba953-40a5-459f-8ecb-42bea0dd96f2","userId":"346387","clientId":"RACPAD","correlationId":"693395b9-5217-4a74-befe-fe146f04d30b","storeNumber":"03833"},"statusCode":500} Alert: 10 / 14 Status: Ok Source: api.logzio_custom Check: Cloud(TS) Services BigPanda Alerts Application: htinventorytransfer Description: Outbound Message: {"body":{"errors":[{"code":"500","message":"unable to retrieve transfer list!"}],"stackTrace":""},"headers":{"Access-Control-Allow-Origin":"*","requestId":"426684c1-8261-4fcd-a9a6-61c09ff71495","userId":"346387","clientId":"RACPAD","correlationId":"5064c29a-7941-46e9-b727-4fa4fe048ac3","storeNumber":"03833"},"statusCode":500} Maximum alert count reached. Additional alerts will not be appended to the description. Visit BigPanda to further investigate the incident or submit a request to your ServiceNow Admin to increase threshold. Maximum Alert Count Configured:10 / Total Alert Count:14 -------------------------------------------------------- Incident Link: https://a.bigpanda.io/v2/incident/698140152f00001700a446ce Incident Timeline Link: https://a.bigpanda.io/v2/incident/698140152f00001700a446ce?timeline=true Incident Preview Link: http://bigp.io/9f590f7174ecc993 | G86: RACPad Support | H86: Vandana K | M86: BigPanda | N86: BigPanda
A87: INCTEC1596127 | B87: 46065.575 | C87: 4 - Low | D87: Closed | E87: RACPAD - Payment | Customer Refund | | F87: Customer would like a refund because the TV was broken in the box and is not available for reorder Agreement Number: 8174621955 Customer ID: 107386699 Customer Name: Alonzaya White Date and Time Issue Was Occured: 2026-01-31 12:44:43 | G87: RACPad Support | H87: shruthika c | I87: RACPAD - Payment | K87: PRB0044395 | M87: Payment | N87: Customer refund
A88: INCTEC1592471 | B88: 46055.773 | C88: 3 - Moderate | D88: Closed | E88: BigPanda Incident: htinventorytransfer - Critical | F88: Incident Summary: -------------------------------------------------------- AI-Generated Incident Analysis Critical: htinventorytransfer Lambda Transfer List Failures in AWS/prod2 Impacting Multiple Stores A critical incident occurred in the prod2 AWS environment, affecting the 'htinventorytransfer' Lambda ('GetHtTransferSubscriptionFilter') with 6 critical and 17 warning alerts from 17:53:08 to 19:45:17 UTC on Feb 2, 2026. Multiple stores were unable to retrieve transfer lists due to persistent backend 500 errors. Other applications had only minor or resolved issues. Between 17:53:08 and 19:45:17 UTC on Feb 2, 2026, the 'htinventorytransfer' Lambda ('GetHtTransferSubscriptionFilter') in AWS/prod2 failed with repeated HTTP 500 errors ('unable to retrieve transfer list!') across multiple store_numbers. This indicates a systemic backend or service dependency failure, not isolated to a single store or transient event. Lambda functions in AWS often serve as stateless compute for backend APIs. The repeated 500 errors from 'GetHtTransferSubscriptionFilter' across many stores and over nearly 2 hours suggest a persistent failure in the service or its dependencies (e.g., database, downstream API). HTTP 500 is a generic server error, typically indicating unhandled exceptions, resource exhaustion, or dependency outages. The fact that multiple stores are affected simultaneously rules out store-specific issues and points to a shared backend or infrastructure problem. The absence of flapping and the presence of both critical and warning alerts over a sustained period further support a systemic, not transient, root cause. Other applications show only isolated or resolved errors, reinforcing that the main impact is on htinventorytransfer. | G88: RACPad Support | H88: Vandana K | M88: BigPanda | N88: BigPanda
A89: INCTEC1596499 | B89: 46066.528 | C89: 4 - Low | D89: Closed | E89: RACPAD - Payment | Customer Refund | | F89: Customer Name: Jasmine Shaw Customer ID : 114981316 Last 4 of Card Used: 8901 Exact Amount of Refund: $34.17 Exact Date of Refund: 02/13/2025 Agreement # 8174794578 Receipt #: 457176495 Detailed Description of Issue: customer canceled agreement but not properly return w/ customer refund | G89: RACPad Support | H89: racha sahithya | I89: RACPAD - Payment | K89: PRB0044395 | M89: Customer | N89: Refund for cancelled agreement
A90: INCTEC1592475 | B90: 46055.777 | C90: 3 - Moderate | D90: Closed | E90: BigPanda Incident: customer - Ok | F90: Incident Summary: -------------------------------------------------------- AI-Generated Incident Analysis Resolved: Transient Backend and Database Errors Across Multiple AWS Production Services On Feb 2, 2026, 15 alerts (all Ok) were generated for AWS-hosted prod2 services, including customer, agreementcreate, processpayment, and others. Alerts referenced prior backend/database errors and network issues, but all services have since recovered. No flapping or open issues remain. No user tickets correlated. Between 15:37 and 17:32 UTC on Feb 2, 2026, multiple AWS-hosted production services (customer, postcommitment, agreementcreate, etc.) experienced transient errors (HTTP 500/400, DB errors, connection resets). All alerts now report Ok, indicating the underlying issues—likely temporary backend/database or integration failures—have been resolved. The alerts show a pattern of transient backend failures: HTTP 500/400 errors, database constraint violations (e.g., missing customer_id, varchar overflows), and network errors (ECONNRESET). These are typical in distributed cloud-native architectures where microservices interact with databases and external APIs. The errors' resolution (all Ok) suggests either a temporary outage or a successful remediation (e.g., DB failover, service restart, or network recovery). The diversity of affected services and error types points to a shared infrastructure or integration point (e.g., database cluster, network segment, or API gateway) as the likely root cause. No ongoing symptoms or flapping are present, confirming stability. | G90: RACPad Support | H90: Vandana K | M90: BigPanda | N90: BigPanda
A91: INCTEC1592476 | B91: 46055.777 | C91: 3 - Moderate | D91: Closed | E91: BigPanda Incident: htinventorytransfer - Warning | F91: Incident Summary: -------------------------------------------------------- AI-Generated Incident Analysis Warning: Server Errors Impacting Multiple AWS Lambda Applications in prod2 Due to Backend SQL Syntax Error On Tuesday, Feb 3, 2026, at 12:34:16 AM UTC, four warning alerts were triggered for AWS Lambda functions in the 'prod2' environment, affecting 'agreementdocument', 'htinventorytransfer', and 'cashdrop'. All reported HTTP 500 errors, with evidence of a PostgreSQL syntax error, indicating a backend query issue impacting multiple production services. At 12:34:16 AM UTC on Feb 3, 2026, four AWS Lambda functions in the 'prod2' environment (applications: agreementdocument, htinventorytransfer, cashdrop) simultaneously returned HTTP 500 errors. The 'cashdrop' alert's stack trace reveals a PostgreSQL syntax error (code 42601), likely causing failures in dependent services. The root cause appears to be a malformed SQL query in the backend, impacting multiple Lambda-based services. HTTP 500 errors indicate server-side failures, often due to unhandled exceptions or backend issues. The stack trace in the 'cashdrop' alert shows a PostgreSQL syntax error (code 42601), which occurs when a SQL statement is malformed. AWS Lambda functions often interact with databases; a syntax error in a shared or reused query can cause failures across multiple services. The simultaneous timing and similar error patterns across different applications suggest a common backend dependency, likely a database or shared service. The presence of the error in the stack trace, along with the lack of other error types, supports the conclusion that a database query issue is the root cause, not isolated application logic or infrastructure. This aligns with best practices in incident analysis, where backend data layer failures can propagate to multiple microservices, resulting in widespread HTTP 500 errors. | G91: RACPad Support | H91: Vandana K | M91: BigPanda | N91: BigPanda
A92: INCTEC1592477 | B92: 46055.78 | C92: 3 - Moderate | D92: Closed | E92: BigPanda Incident: htinventorytransfer - Ok | F92: Incident Summary: -------------------------------------------------------- AI-Generated Incident Analysis On Feb 2, 2026, 13 resolved alerts reported transient HTTP 500 errors from the 'htinventorytransfer' Lambda (prod2-htinventorytransfer-lambda-GetHtTransferSubscriptionFilter) in AWS prod2, impacting multiple stores. All alerts are now Ok, indicating the issue has cleared and services are stable. No user tickets or ongoing impact. Alert Summary: 0 Critical, 0 Warning, 13 Resolved -------------------------------------------------------- Alert: 1 / 13 Status: Ok Source: api.logzio_custom Check: Cloud(TS) Services BigPanda Alerts Application: htinventorytransfer Description: Outbound Message: {"body":{"errors":[{"code":"500","message":"unable to retrieve transfer list!"}],"stackTrace":""},"headers":{"Access-Control-Allow-Origin":"*","requestId":"4daeadab-9590-46af-be00-cc5df7797d29","userId":"93642","clientId":"RACPAD","correlationId":"b1d1cc1e-26e1-4eb9-b128-6c2adf1b44f3","storeNumber":"01871"},"statusCode":500} Alert: 2 / 13 Status: Ok Source: api.logzio_custom Check: Cloud(TS) Services BigPanda Alerts Application: htinventorytransfer Description: Outbound Message: {"body":{"errors":[{"code":"500","message":"unable to retrieve transfer list!"}],"stackTrace":""},"headers":{"Access-Control-Allow-Origin":"*","requestId":"1617b7f4-41d7-4da6-9504-ef128c8f49e5","userId":"93642","clientId":"RACPAD","correlationId":"00efbf52-c756-4083-80b5-cf422c93fe6a","storeNumber":"01871"},"statusCode":500} Alert: 3 / 13 Status: Ok Source: api.logzio_custom Check: Cloud(TS) Services BigPanda Alerts Application: htinventorytransfer Description: Outbound Message: {"body":{"errors":[{"code":"500","message":"unable to retrieve transfer list!"}],"stackTrace":""},"headers":{"Access-Control-Allow-Origin":"*","requestId":"6722aa12-f348-417a-8602-76688b115c70","userId":"241274","clientId":"RACPAD","correlationId":"418ef2ea-7143-4b79-91d5-2243cba72306","storeNumber":"02468"},"statusCode":500} Alert: 4 / 13 Status: Ok Source: api.logzio_custom Check: Cloud(TS) Services BigPanda Alerts Application: htinventorytransfer Description: Outbound Message: {"body":{"errors":[{"code":"500","message":"unable to retrieve transfer list!"}],"stackTrace":""},"headers":{"Access-Control-Allow-Origin":"*","requestId":"9199a9c1-ffe2-4cc0-a9c7-465af0cd0c3d","userId":"350641","clientId":"RACPAD","correlationId":"4c12096f-8494-4259-83e5-b72621c8e912","storeNumber":"03864"},"statusCode":500} Alert: 5 / 13 Status: Ok Source: api.logzio_custom Check: Cloud(TS) Services BigPanda Alerts Application: htinventorytransfer Description: Outbound Message: {"body":{"errors":[{"code":"500","message":"unable to retrieve transfer list!"},"stackTrace":""},"headers":{"Access-Control-Allow-Origin":"*","requestId":"cb852d1b-9ded-43b2-a0f0-02cbef63884b","userId":"127285","clientId":"RACPAD","correlationId":"634326ee-3dd2-4eab-bd33-f1279460eaea","storeNumber":"01985"},"statusCode":500} Alert: 6 / 13 Status: Ok Source: api.logzio_custom Check: Cloud(TS) Services BigPanda Alerts Application: htinventorytransfer Description: Outbound Message: {"body":{"errors":[{"code":"500","message":"unable to retrieve transfer list!"}],"stackTrace":""},"headers":{"Access-Control-Allow-Origin":"*","requestId":"d922ba08-18b7-44ed-ba6e-634e3788255b","userId":"350641","clientId":"RACPAD","correlationId":"9a6adcc7-cea4-45e0-9d8c-c3fcb86a0ad3","storeNumber":"03864"},"statusCode":500} Alert: 7 / 13 Status: Ok Source: api.logzio_custom Check: Cloud(TS) Services BigPanda Alerts Application: htinventorytransfer Description: Outbound Message: {"body":{"errors":[{"code":"500","message":"unable to retrieve transfer list!"}],"stackTrace":""},"headers":{"Access-Control-Allow-Origin":"*","requestId":"b2528c21-2d46-4aac-b566-3684d04547b6","userId":"127285","clientId":"RACPAD","correlationId":"63f82378-de30-4ad8-9eee-fdfef83f1554","storeNumber":"01985"},"statusCode":500} Alert: 8 / 13 Status: Ok Source: api.logzio_custom Check: Cloud(TS) Services BigPanda Alerts Application: htinventorytransfer Description: Outbound Message: {"body":{"errors":[{"code":"500","message":"unable to retrieve transfer list!"},"stackTrace":""},"headers":{"Access-Control-Allow-Origin":"*","requestId":"b999b3fd-0f12-417a-a78b-3c80e4e1e4ed","userId":"360657","clientId":"RACPAD","correlationId":"54911589-0d57-4db2-85c2-456187709ab8","storeNumber":"00122"},"statusCode":500} Alert: 9 / 13 Status: Ok Source: api.logzio_custom Check: Cloud(TS) Services BigPanda Alerts Application: htinventorytransfer Description: Outbound Message: {"body":{"errors":[{"code":"500","message":"unable to retrieve transfer list!"}],"stackTrace":""},"headers":{"Access-Control-Allow-Origin":"*","requestId":"909c4af8-bd6f-4e17-a5f1-2cb2f04d4b3a","userId":"316057","clientId":"RACPAD","correlationId":"f585e80a-7df3-4930-a1a4-ec5b4bda37bf","storeNumber":"00501"},"statusCode":500} Alert: 10 / 13 Status: Ok Source: api.logzio_custom Check: Cloud(TS) Services BigPanda Alerts Application: htinventorytransfer Description: Outbound Message: {"body":{"errors":[{"code":"500","message":"unable to retrieve transfer list!"}],"stackTrace":""},"headers":{"Access-Control-Allow-Origin":"*","requestId":"19ae0af7-7218-45e7-ad4b-9f81ec286623","userId":"360657","clientId":"RACPAD","correlationId":"ee39ef84-404c-4e65-abfe-b0ad8b8b0c17","storeNumber":"00122"},"statusCode":500} Maximum alert count reached. Additional alerts will not be appended to the description. Visit BigPanda to further investigate the incident or submit a request to your ServiceNow Admin to increase threshold. Maximum Alert Count Configured:10 / Total Alert Count:13 -------------------------------------------------------- Incident Link: https://a.bigpanda.io/v2/incident/6981434e2f00003800a446d4 Incident Timeline Link: https://a.bigpanda.io/v2/incident/6981434e2f00003800a446d4?timeline=true Incident Preview Link: http://bigp.io/dd7a221758c87d4e | G92: RACPad Support | H92: Vandana K | M92: BigPanda | N92: BigPanda
A93: INCTEC1592479 | B93: 46055.785 | C93: 3 - Moderate | D93: Closed | E93: BigPanda Incident: htinventorytransfer - Ok | F93: Incident Summary: -------------------------------------------------------- AI-Generated Incident Analysis From Feb 2, 2026, 22:05 to 23:52 UTC, 25 Ok alerts reported transient HTTP 500 errors in the 'htinventorytransfer' Lambda (AWS prod2), impacting multiple stores. All alerts are now Ok, with no critical or warning statuses. The incident is resolved, and no further action is required. Alert Summary: 0 Critical, 0 Warning, 25 Resolved -------------------------------------------------------- Alert: 1 / 25 Status: Ok Source: api.logzio_custom Check: Cloud(TS) Services BigPanda Alerts Application: htinventorytransfer Description: Outbound Message: {"body":{"errors":[{"code":"500","message":"unable to retrieve transfer list!"}],"stackTrace":""},"headers":{"Access-Control-Allow-Origin":"*","requestId":"5d93d7e0-f734-4e9f-9f29-51d3121593a6","userId":"346506","clientId":"RACPAD","correlationId":"078ae6f8-2937-4e90-83f9-965219e2cd53","storeNumber":"00994"},"statusCode":500} Alert: 2 / 25 Status: Ok Source: api.logzio_custom Check: Cloud(TS) Services BigPanda Alerts Application: htinventorytransfer Description: Outbound Message: {"body":{"errors":[{"code":"500","message":"unable to retrieve transfer list!"},"stackTrace":""},"headers":{"Access-Control-Allow-Origin":"*","requestId":"4fb51cbc-e463-4fd4-812c-3b663d0594d7","userId":"346506","clientId":"RACPAD","correlationId":"8b9a14b3-dbb9-4b72-a59f-877766781375","storeNumber":"00994"},"statusCode":500} Alert: 3 / 25 Status: Ok Source: api.logzio_custom Check: Cloud(TS) Services BigPanda Alerts Application: htinventorytransfer Description: Outbound Message: {"body":{"errors":[{"code":"500","message":"unable to retrieve transfer list!"}],"stackTrace":""},"headers":{"Access-Control-Allow-Origin":"*","requestId":"50b84dec-83cb-44e3-afad-7801c8c6f211","userId":"190720","clientId":"RACPAD","correlationId":"44f951db-5c2c-4d48-b0ee-bf55408374cd","storeNumber":"00135"},"statusCode":500} Alert: 4 / 25 Status: Ok Source: api.logzio_custom Check: Cloud(TS) Services BigPanda Alerts Application: htinventorytransfer Description: Outbound Message: {"body":{"errors":[{"code":"500","message":"unable to retrieve transfer list!"}],"stackTrace":""},"headers":{"Access-Control-Allow-Origin":"*","requestId":"f3e26c74-d0bd-4c8d-a9b6-887ea4821aad","userId":"366396","clientId":"RACPAD","correlationId":"ad8f012c-878a-4fb5-af19-5216a838a54a","storeNumber":"02903"},"statusCode":500} Alert: 5 / 25 Status: Ok Source: api.logzio_custom Check: Cloud(TS) Services BigPanda Alerts Application: htinventorytransfer Description: Outbound Message: {"body":{"errors":[{"code":"500","message":"unable to retrieve transfer list!"}],"stackTrace":""},"headers":{"Access-Control-Allow-Origin":"*","requestId":"60b1f98f-8541-4431-8e0b-cacd620c5d77","userId":"368109","clientId":"RACPAD","correlationId":"454e8181-868d-4299-b271-b142934dd34b","storeNumber":"01042"},"statusCode":500} Alert: 6 / 25 Status: Ok Source: api.logzio_custom Check: Cloud(TS) Services BigPanda Alerts Application: htinventorytransfer Description: Outbound Message: {"body":{"errors":[{"code":"500","message":"unable to retrieve transfer list!"}],"stackTrace":""},"headers":{"Access-Control-Allow-Origin":"*","requestId":"92726f17-b775-4033-9869-dd20bc82d3be","userId":"366396","clientId":"RACPAD","correlationId":"3431ab57-86e2-4008-ad1d-73a657557e16","storeNumber":"02903"},"statusCode":500} Alert: 7 / 25 Status: Ok Source: api.logzio_custom Check: Cloud(TS) Services BigPanda Alerts Application: htinventorytransfer Description: Outbound Message: {"body":{"errors":[{"code":"500","message":"unable to retrieve transfer list!"}],"stackTrace":""},"headers":{"Access-Control-Allow-Origin":"*","requestId":"34b98ab4-d987-4219-83d1-b120501b82f1","userId":"368109","clientId":"RACPAD","correlationId":"d2565e0e-efd6-4b3f-bf6d-46b4bf7059d1","storeNumber":"01042"},"statusCode":500} Alert: 8 / 25 Status: Ok Source: api.logzio_custom Check: Cloud(TS) Services BigPanda Alerts Application: htinventorytransfer Description: Outbound Message: {"body":{"errors":[{"code":"500","message":"unable to retrieve transfer list!"}],"stackTrace":""},"headers":{"Access-Control-Allow-Origin":"*","requestId":"f5cb5218-2931-4f04-9acf-553482e086fa","userId":"362725","clientId":"RACPAD","correlationId":"9f2725e5-402e-442b-84cc-21ed0af69c57","storeNumber":"01278"},"statusCode":500} Alert: 9 / 25 Status: Ok Source: api.logzio_custom Check: Cloud(TS) Services BigPanda Alerts Application: htinventorytransfer Description: Outbound Message: {"body":{"errors":[{"code":"500","message":"unable to retrieve transfer list!"}],"stackTrace":""},"headers":{"Access-Control-Allow-Origin":"*","requestId":"79e3703e-3855-4a97-b700-9c154accbf55","userId":"69243","clientId":"RACPAD","correlationId":"ae82c44d-4435-47c7-876e-3e18bea528a7","storeNumber":"02225"},"statusCode":500} Alert: 10 / 25 Status: Ok Source: api.logzio_custom Check: Cloud(TS) Services BigPanda Alerts Application: htinventorytransfer Description: Outbound Message: {"body":{"errors":[{"code":"500","message":"unable to retrieve transfer list!"},"stackTrace":""},"headers":{"Access-Control-Allow-Origin":"*","requestId":"3dc3b7bd-6b3b-4484-84b0-bd725ff7e5de","userId":"362725","clientId":"RACPAD","correlationId":"f5fcab22-0147-4ecd-b7de-30d59cf59839","storeNumber":"01278"},"statusCode":500} Maximum alert count reached. Additional alerts will not be appended to the description. Visit BigPanda to further investigate the incident or submit a request to your ServiceNow Admin to increase threshold. Maximum Alert Count Configured:10 / Total Alert Count:25 -------------------------------------------------------- Incident Link: https://a.bigpanda.io/v2/incident/698145382f00003c00a446da Incident Timeline Link: https://a.bigpanda.io/v2/incident/698145382f00003c00a446da?timeline=true Incident Preview Link: http://bigp.io/d8c86f38c3f50e05 | G93: RACPad Support | H93: Vandana K | M93: BigPanda | N93: BigPanda
A94: INCTEC1592480 | B94: 46055.786 | C94: 3 - Moderate | D94: Closed | E94: BigPanda Incident: agreementdocument - Ok | F94: Incident Summary: -------------------------------------------------------- AI-Generated Incident Analysis On Tuesday, Feb 3, 2026, at 12:34:16 AM UTC, four AWS Lambda functions supporting 'agreementdocument', 'htinventorytransfer', and 'cashdrop' in the 'prod2' environment recovered from prior HTTP 500 errors. All alerts are now 'Ok', with no ongoing impact. No user tickets or further issues are present. Incident is resolved. Alert Summary: 0 Critical, 0 Warning, 4 Resolved -------------------------------------------------------- Alert: 1 / 4 Status: Ok Source: api.logzio_custom Check: Cloud(TS) Services BigPanda Alerts Application: agreementdocument Description: Outbound Message: {"body":{"errors":[{"code":"500","message":"Error in UpdateSigningService"}],"stackTrace":"{}"},"headers":{"Access-Control-Allow-Origin":"*","requestId":"befc2f98-bde9-4730-8269-c99f636e4db0","userId":"notify-document","clientId":"RACPAD","correlationId":"5082141f-56ea-451b-b5b4-96a87b779be2","storeNumber":"99999"},"statusCode":500} Alert: 2 / 4 Status: Ok Source: api.logzio_custom Check: Cloud(TS) Services BigPanda Alerts Application: htinventorytransfer Description: Outbound Message: {"body":{"errors":[{"code":"500","message":"unable to retrieve transfer list!"}],"stackTrace":""},"headers":{"Access-Control-Allow-Origin":"*","requestId":"c7d890d7-b6e0-4b48-8d9b-10f5134886f0","userId":"106889","clientId":"RACPAD","correlationId":"8990141f-c2bf-4747-81b7-a8da30607415","storeNumber":"01874"},"statusCode":500} Alert: 3 / 4 Status: Ok Source: api.logzio_custom Check: Cloud(TS) Services BigPanda Alerts Application: htinventorytransfer Description: Outbound Message: {"body":{"errors":[{"code":"500","message":"unable to retrieve transfer list!"},"stackTrace":""},"headers":{"Access-Control-Allow-Origin":"*","requestId":"5711b770-de7d-4fc5-a98b-5b9804973a2a","userId":"114649","clientId":"RACPAD","correlationId":"7c9151f9-11b9-4eda-a60f-c4f127a2288f","storeNumber":"02224"},"statusCode":500} Alert: 4 / 4 Status: Ok Source: api.logzio_custom Check: Cloud(TS) Services BigPanda Alerts Application: cashdrop Description: Outbound Message: {"body":{"errors":[{"code":"500","message":"Error in ManageDropService"}],"stackTrace":"{\"length\":99,\"name\":\"error\",\"severity\":\"ERROR\",\"code\":\"42601\",\"position\":\"200\",\"file\":\"scan.l\",\"line\":\"1304\",\"routine\":\"scanner_yyerror\"}"},"headers":{"Access-Control-Allow-Origin":"*","requestId":"402cedd4-c300-4f2a-975d-723ad14a4efd","userId":"104228","clientId":"RACPAD","correlationId":"18f16330-2daf-4c93-a1a8-67b3d7b447b5","storeNumber":"04389"},"statusCode":500} -------------------------------------------------------- Incident Link: https://a.bigpanda.io/v2/incident/698142888e148545883bbc11 Incident Timeline Link: https://a.bigpanda.io/v2/incident/698142888e148545883bbc11?timeline=true Incident Preview Link: http://bigp.io/2d551b0fb11ec2fb | G94: RACPad Support | H94: Vandana K | M94: BigPanda | N94: BigPanda
A95: INCTEC1592481 | B95: 46055.793 | C95: 3 - Moderate | D95: Closed | E95: BigPanda Incident: htinventorytransfer - Warning | F95: Incident Summary: -------------------------------------------------------- AI-Generated Incident Analysis Warning: AWS Lambda 'htinventorytransfer' Transfer List Retrieval Failures Across Multiple Stores On February 3, 2026, at 00:57:17 UTC, six warning alerts were generated for the 'htinventorytransfer' application, specifically the 'prod2-htinventorytransfer-lambda-GetHtTransferSubscriptionFilter' Lambda function in AWS Production. Multiple stores and users were affected by HTTP 500 errors, indicating a backend/API failure preventing transfer list retrieval. At 00:57:17 UTC on February 3, 2026, six simultaneous warning alerts were triggered for the 'prod2-htinventorytransfer-lambda-GetHtTransferSubscriptionFilter' Lambda function in AWS Production. Each alert reported an HTTP 500 error ('unable to retrieve transfer list!') for different users and store numbers, indicating a backend/API failure affecting multiple requests at the same time. The root cause is a backend service/API outage or malfunction that prevented the Lambda function from retrieving transfer lists, not a symptom of another issue. Multiple simultaneous HTTP 500 errors from the same AWS Lambda function across different users and stores indicate a likely backend or API failure, rather than isolated user issues. | G95: RACPad Support | H95: Vandana K | M95: BigPanda | N95: BigPanda
A96: INCTEC1592483 | B96: 46055.799 | C96: 3 - Moderate | D96: Closed | E96: BigPanda Incident: cloud2gcdb - Ok | F96: Incident Summary: -------------------------------------------------------- AI-Generated Incident Analysis Resolved: cloud2gcdb Lambda POST-PAYMENT Event Processing Errors Cleared Across Multiple Stores (prod2) On February 3, 2026, at 01:05:16 UTC, 9 Ok alerts were generated for the cloud2gcdb application’s Lambda function (prod2-cloud2gcdb-lambda-Cloud2GcdbSubscriptionFilter) in the prod2 environment, affecting multiple stores. All alerts indicate prior POST-PAYMENT event processing errors are now resolved. No ongoing impact detected. At 2026-02-03 01:05:16 UTC, 9 Ok alerts were generated for cloud2gcdb's Lambda function (prod2-cloud2gcdb-lambda-Cloud2GcdbSubscriptionFilter) across multiple stores. These Ok alerts indicate that prior errors in processing POST-PAYMENT events were resolved. No active errors remain; the root cause was a transient issue in the Lambda function, now cleared. AWS Lambda functions, such as prod2-cloud2gcdb-lambda-Cloud2GcdbSubscriptionFilter, process events (here, POST-PAYMENT) in a serverless architecture. Errors in event processing can arise from code bugs, data issues, or downstream service failures. The Ok status at the same timestamp for all alerts suggests automated recovery or resolution (e.g., code fix, data correction, or transient external dependency recovery). The uniform timing and resolution across stores indicate a systemic, not isolated, issue—likely a shared resource or configuration affecting the Lambda function. The absence of critical/warning alerts and the Ok incident status confirm the issue is resolved. No user tickets or flapping further support that the incident was transient and is no longer impacting operations. | G96: RACPad Support | H96: Vandana K | M96: BigPanda | N96: BigPanda
A97: INCTEC1592495 | B97: 46055.827 | C97: 3 - Moderate | D97: Closed | E97: BigPanda Incident: htinventorytransfer - Critical | F97: Incident Summary: -------------------------------------------------------- AI-Generated Incident Analysis Critical: htinventorytransfer Lambda Transfer List Failures in AWS/prod2 Impacting Multiple Stores A critical incident occurred in the prod2 AWS environment, affecting the 'htinventorytransfer' Lambda ('GetHtTransferSubscriptionFilter') with 6 critical and 17 warning alerts from 17:53:08 to 19:45:17 UTC on Feb 2, 2026. Multiple stores were unable to retrieve transfer lists due to persistent backend 500 errors. Other applications had only minor or resolved issues. Between 17:53:08 and 19:45:17 UTC on Feb 2, 2026, the 'htinventorytransfer' Lambda ('GetHtTransferSubscriptionFilter') in AWS/prod2 failed with repeated HTTP 500 errors ('unable to retrieve transfer list!') across multiple store_numbers. This indicates a systemic backend or service dependency failure, not isolated to a single store or transient event. Lambda functions in AWS often serve as stateless compute for backend APIs. The repeated 500 errors from 'GetHtTransferSubscriptionFilter' across many stores and over nearly 2 hours suggest a persistent failure in the service or its dependencies (e.g., database, downstream API). HTTP 500 is a generic server error, typically indicating unhandled exceptions, resource exhaustion, or dependency outages. The fact that multiple stores are affected simultaneously rules out store-specific issues and points to a shared backend or infrastructure problem. The absence of flapping and the presence of both critical and warning alerts over a sustained period further support a systemic, not transient, root cause. Other applications show only isolated or resolved errors, reinforcing that the main impact is on htinventorytransfer. | G97: RACPad Support | H97: Vandana K | M97: BigPanda | N97: BigPanda
A98: INCTEC1592496 | B98: 46055.827 | C98: 3 - Moderate | D98: Closed | E98: BigPanda Incident: htinventorytransfer - Warning | F98: Incident Summary: -------------------------------------------------------- AI-Generated Incident Analysis Warning - AWS prod2 htinventorytransfer transfer list failures and customer update error across multiple stores On Feb 3, 2026, between 00:57 and 01:51 UTC, 9 warning alerts were triggered in AWS prod2/Production. 8 relate to 'htinventorytransfer' Lambda failing to retrieve transfer lists (HTTP 500) for multiple stores; 1 is a 'customer' app SQL error. No criticals, no user tickets, no flapping. Impact: degraded inventory transfer and customer update functions. Between 00:57:17 and 01:51:08 UTC on Feb 3, 2026, 8 warning alerts for 'htinventorytransfer' (AWS Lambda) failed with HTTP 500 errors ('unable to retrieve transfer list!') across multiple stores. One 'customer' app alert at 01:51:08 UTC shows a SQL duplicate key error. The primary root cause is repeated backend/API failures in 'htinventorytransfer'. AWS Lambda functions (here, 'prod2-htinventorytransfer-lambda-GetHtTransferSubscriptionFilter') serve as stateless compute for API endpoints. HTTP 500 errors indicate server-side failures, often due to downstream service or data source issues (e.g., database, API, or network). The repeated, simultaneous failures across stores suggest a shared backend dependency (e.g., a database or microservice) was unavailable or malfunctioning, not isolated client or network issues. The 'customer' app's SQL error (code 23505) is a separate, transactional data integrity issue, not directly related to the htinventorytransfer failures, but may indicate broader backend instability. No evidence of monitoring or alerting system malfunction. The incident is not flapping, and all alerts are warnings, indicating degraded but not total service loss. | G98: RACPad Support | H98: Vandana K | M98: BigPanda | N98: BigPanda
A99: INCTEC1592497 | B99: 46055.832 | C99: 3 - Moderate | D99: Closed | E99: BigPanda Incident: htinventorytransfer - Warning | F99: Incident Summary: -------------------------------------------------------- AI-Generated Incident Analysis Warning: Inventory Transfer Retrieval Failures (HTTP 500) in htinventorytransfer Lambda Across Multiple Stores (prod2/AWS) On Feb 3, 2026, between 00:57:17 and 01:51:08 UTC, 8 'Warning' alerts were triggered for 'htinventorytransfer' in the 'prod2' AWS environment. Multiple stores (01022, 02208, 02903, 00726) were unable to retrieve transfer lists due to repeated HTTP 500 errors from the Lambda function, impacting inventory operations. Between 00:57:17 and 01:51:08 UTC on Feb 3, 2026, 8 'Warning' alerts from 'prod2-htinventorytransfer-lambda-GetHtTransferSubscriptionFilter' reported HTTP 500 errors ('unable to retrieve transfer list!') across stores 01022, 02208, 02903, and 00726. The root cause is a failure in this Lambda function or its backend dependency, preventing transfer list retrieval for multiple stores. HTTP 500 errors across multiple stores indicate a systemic backend or Lambda-level failure, likely due to a shared dependency issue rather than isolated store problems. | G99: RACPad Support | H99: Vandana K | M99: BigPanda | N99: BigPanda
A100: INCTEC1592499 | B100: 46055.841 | C100: 3 - Moderate | D100: Closed | E100: BigPanda Incident: cloud2gcdb - Ok | F100: Incident Summary: -------------------------------------------------------- AI-Generated Incident Analysis Resolved: Transient Event Processing Errors in cloud2gcdb Lambda (prod2) Across Multiple Stores From 01:05:16 to 02:09:15 UTC on Feb 3, 2026, 29 Ok-status alerts were generated for the prod2-cloud2gcdb-lambda-Cloud2GcdbSubscriptionFilter Lambda in the prod2 environment, referencing transient errors in processing POST-PAYMENT and UPDATE-AGREEMENT events for cloud2gcdb. All issues are now resolved. Between 01:05:16 and 02:09:15 UTC on Feb 3, 2026, multiple transient errors occurred in the prod2-cloud2gcdb-lambda-Cloud2GcdbSubscriptionFilter Lambda function while processing POST-PAYMENT and UPDATE-AGREEMENT events. All alerts have since cleared (status Ok), indicating the underlying issue was temporary and is now resolved. AWS Lambda functions process events asynchronously, often triggered by upstream services (e.g., API Gateway, SQS, or event streams). Errors like 'Error while processing event POST-PAYMENT' suggest transient failures—possibly due to malformed input, temporary downstream unavailability, or resource contention. The consistent alert object and event types across multiple store numbers indicate a systemic, not localized, issue. However, all alerts are now Ok, meaning the Lambda function has resumed normal operation, and no further errors are being reported. This pattern is typical for transient cloud service disruptions, where self-healing or automatic retries resolve the issue without manual intervention. The absence of critical or warning alerts and the incident's Ok status confirm resolution. | G100: RACPad Support | H100: Vandana K | M100: BigPanda | N100: BigPanda
A101: INCTEC1592500 | B101: 46055.842 | C101: 4 - Low | D101: Closed | E101: RACFI-RACPAD - Inventory | Inventory - Other | | F101: Information in Inventory and Price Tag do not match. Inventory shows "16G" while Price Tag Prints "32G". Information on Inventory Screen is correct. Inventory Number: 9999221066803 Date and Time Issue Was Occured: 2026-02-02 20:07:29 | G101: RACPad Support | H101: ankita singh | I101: RACPAD - Inventory | M101: Inventory | N101: Price tag and inventory price mismatch
A102: INCTEC1592505 | B102: 46055.885 | C102: 3 - Moderate | D102: Closed | E102: BigPanda Incident: cloud2gcdb - Ok | F102: Incident Summary: -------------------------------------------------------- AI-Generated Incident Analysis Resolved: Transient Event Processing Errors in cloud2gcdb Lambda (prod2, Multiple Stores) On Feb 3, 2026, between 03:09:08 and 04:09:11 UTC, 19 alerts reported transient errors in the 'cloud2gcdb' Lambda function ('prod2' environment, multiple stores). All alerts are now 'Ok', indicating self-resolution. No ongoing impact or user-reported issues. Incident is fully resolved. All 19 alerts, spanning 03:09:08 UTC and 04:09:11 UTC on Feb 3, 2026, reported errors in processing 'POST-PAYMENT', 'UPDATE-AGREEMENT', or 'UPDATE-CUSTOMER' events in the 'cloud2gcdb' Lambda function. However, all alerts are now 'Ok', indicating the errors were transient and self-resolved. No persistent or causal issue remains. AWS Lambda functions, like 'prod2-cloud2gcdb-lambda-Cloud2GcdbSubscriptionFilter', process events asynchronously. Transient errors (e.g., network hiccups, temporary downstream unavailability) can cause event processing failures, which monitoring tools log as alerts. The 'Ok' status means the function retried or the underlying issue cleared, restoring normal operation. No evidence of systemic or persistent failure exists, as all alerts self-resolved within an hour. The absence of correlated tickets further supports that the impact was limited and short-lived. | G102: RACPad Support | H102: Vandana K | M102: BigPanda | N102: BigPanda
A103: INCTEC1592524 | B103: 46056.029 | C103: 3 - Moderate | D103: Closed | E103: BigPanda Incident: deliveryreceipt - Ok | F103: Incident Summary: -------------------------------------------------------- AI-Generated Incident Analysis Resolved: deliveryreceipt UploadReceiptsService Error Cleared in prod2 at Store 08580 On Tuesday, Feb 3, 2026, at 6:36:10 AM UTC, two Ok alerts were generated for prod2-deliveryreceipt-lambda-UploadReceiptsSubscriptionFilter (application: deliveryreceipt, environment: prod2, store: 08580). The incident is resolved, with no current impact. Previous errors in UploadReceiptsService have cleared. Both alerts, timestamped Tuesday, Feb 3, 2026, 6:36:10 AM UTC, report status Ok for prod2-deliveryreceipt-lambda-UploadReceiptsSubscriptionFilter. Their descriptions reference a prior 500 error in UploadReceiptsService, but the Ok status and incident status confirm the error condition has cleared. No active issue remains. CloudWatch log-based alerts often trigger on error patterns (e.g., HTTP 500) and resolve when the error ceases. Here, both alerts reference a resolved 500 error in UploadReceiptsService, but their Ok status and matching incident status indicate the system is healthy. The error in the description is historical, not current. No new errors or ongoing symptoms are present, confirming resolution. | G103: RACPad Support | H103: Incharashree KY | M103: BigPanda | N103: BigPanda
A104: INCTEC1592523 | B104: 46056.029 | C104: 3 - Moderate | D104: Closed | E104: BigPanda Incident: customer - Ok | F104: Incident Summary: -------------------------------------------------------- AI-Generated Incident Analysis Resolved: Transient Backend and Database Errors Across Multiple AWS Production Services On Feb 2, 2026, 15 alerts (all Ok) were generated for AWS-hosted prod2 services, including customer, agreementcreate, processpayment, and others. Alerts referenced prior backend/database errors and network issues, but all services have since recovered. No flapping or open issues remain. No user tickets correlated. Between 15:37 and 17:32 UTC on Feb 2, 2026, multiple AWS-hosted production services (customer, postcommitment, agreementcreate, etc.) experienced transient errors (HTTP 500/400, DB errors, connection resets). All alerts now report Ok, indicating the underlying issues—likely temporary backend/database or integration failures—have been resolved. The alerts show a pattern of transient backend failures: HTTP 500/400 errors, database constraint violations (e.g., missing customer_id, varchar overflows), and network errors (ECONNRESET). These are typical in distributed cloud-native architectures where microservices interact with databases and external APIs. The errors' resolution (all Ok) suggests either a temporary outage or a successful remediation (e.g., DB failover, service restart, or network recovery). The diversity of affected services and error types points to a shared infrastructure or integration point (e.g., database cluster, network segment, or API gateway) as the likely root cause. No ongoing symptoms or flapping are present, confirming stability. | G104: RACPad Support | H104: Incharashree KY | M104: BigPanda | N104: BigPanda
...

Sheet Issue wise Summary
A1: Type of Issue | B1: Incidents linked to this issue | C1: Issue Description | D1: One time/Reccurring | E1: Problem associated? | F1: Problem | G1: Automation/Shift Left | H1: Remarks
A2: BigPanda | B2: 731 | C2: Big Panda tickets
A3: Unable to take payments | B3: 64 | C3: Most of these tickets were created due to a worldpay outage | D3: One time
A4: Access | B4: 59 | C4: Access related issues | D4: Recurring | E4: Yes | F4: PRB0045218
A5: Unable to receive the purchase order | B5: 44 | C5: Due to missing prices stores will not be able to receive PO. Once the prices are published this will be resolved. | D5: Recurring
A6: Payment not reflecting in RACPAD | B6: 44 | C6: Customer account will be deducted but the payment will not be refelcted in RACPAD. | D6: Recurring | G6: Shared with LEAP team | H6: Check with ESS team if API is present for accesing IQ portal
A7: AutoPay | B7: 38 | C7: Customers unable to enroll into AutoPay | D7: Recurring | E7: Yes | G7: Shared with LEAP team
A8: Unable to create an Agreement | B8: 33 | C8: Stores were unable to create an agreement due to a Change rollback. | D8: One time
A9: Cancel the Manual PO | B9: 33 | C9: Request to cancel Manual PO | D9: Recurring | E9: Yes | F9: PRB0045846
A10: PIN reset | B10: 25 | C10: Request to Reset CW PIN | D10: Recurring | G10: Need to discuss with Business if the RESET PIN option can be provided to user itself.
A11: Customer refund | B11: 24 | C11: Customer has not received the refund | D11: Recurring | E11: Yes | F11: PRB0044395 | H11: check with Data Services team on this pattern
A12: Agreement switch-out completed, but inventory remains in "Pending Switch Out" status | B12: 21 | C12: Agreement switch-out completed, but inventory remains in "Pending Switch Out" status | D12: Recurring | E12: Yes | F12: PRB0045906
A13: Unable to print service sheet | B13: 21 | C13: Store were unable to print service sheet. This issue was caused due to a release | D13: One time
A14: There was an error processing your request popup | B14: 20 | C14: When taking payments the store will recievie a popup saying there was an error | D14: One time
A15: Customer not eligible for reward error | B15: 18 | C15: Stores were getting an error popup saying "Customer not eligible for reward error" | D15: One time
A16: Unable to confirm delivery | B16: 16 | C16: CW is unable to confirm delivery. This can be due to missing customer contact details. Once updated they will be able to confirm delivery | D16: Recurring | G16: Shift left | H16: Create a problem ticket
A17: Unable to add package items | B17: 15 | C17: Stores were unable to add items to package. This issue was caused due to a release | D17: One time
A18: Level 0 customer cannot order phone | B18: 14 | C18: A customer who is level 0 cannot order a mobile phone | D18: Recurring | G18: FIxed by dev
A19: Error in RmsReserveOrderService | B19: 12 | C19: When adding an item to create an agreement, "Error in RMSReserveOrderService" message pops up. This can be due to the item being Out of stock | D19: Recurring
A20: Unable to fetch the data | B20: 9 | C20: The fields going blank in Account Management screen with the error as "Unable to fetch the data". This is an intermittent issue | D20: Recurring
A21: Drop reconciliation issue | B21: 8 | C21: Drop related issues | D21: Recurring
A22: Cancel the RMS PO | B22: 8 | C22: Request to cancel the RMS PO. | D22: Recurring | E22: Yes | F22: PRB0045373
A23: Report issues | B23: 8 | C23: Report related issues such as data mismatch etc | D23: Recurring
A24: Void the agreement and change the inventory status to idle | B24: 8 | C24: Request to void the agreement and change the inventory status | D24: Recurring
A25: Incorrect due date | B25: 8 | C25: Due date showing incorrect | D25: Recurring
A26: Customer level change request | B26: 7 | C26: Request to change the level of the customer | D26: Recurring | G26: Shift left
A27: Customer charged multiple times | B27: 7
A28: CCCB related query | B28: 6
A29: Identity link not working | B29: 6
A30: NSF related | B30: 6
A31: This feauture is currently not assigned to you | B31: 6
A32: Unable to take item out of service | B32: 5
A33: Unable to add benefit plus | B33: 5
A34: Payment issue | B34: 5
A35: Incorrect charges | B35: 4
A36: Customer level query | B36: 4
A37: Inventory status change request | B37: 4
A38: Receipt reversal | B38: 3
... A94: Promo start date change | B94: 1

Sheet Issue wise details
A1: Type of Issue | B1: No of tickets | C1: Issue Description | D1: One time/Recurring | E1: Problem Associated? | F1: Problem | G1: Automation/Shift Left | H1: Remarks
A2: BigPanda | B2: 731 | C2: =VLOOKUP(A2,'Issue wise Summary'!A:C,3,FALSE) -> Big Panda tickets
A3: Unable to take payments | B3: 64 | C3: =VLOOKUP(A3,'Issue wise Summary'!A:C,3,FALSE) -> Most of these tickets were created due to a worldpay outage | D3: =VLOOKUP(A3,'Issue wise Summary'!A:D,4,FALSE) -> One time
A4: Access | B4: 59 | C4: =VLOOKUP(A4,'Issue wise Summary'!A:C,3,FALSE) -> Access related issues | D4: =VLOOKUP(A4,'Issue wise Summary'!A:D,4,FALSE) -> Recurring | E4: =VLOOKUP(A4,'Issue wise Summary'!A:E,5,FALSE) -> Yes | F4: =VLOOKUP(A4,'Issue wise Summary'!A:F,6,FALSE) -> PRB0045218
A5: Unable to receive the purchase order | B5: 44 | C5: =VLOOKUP(A5,'Issue wise Summary'!A:C,3,FALSE) -> Due to missing prices stores will not be able to receive PO. Once the prices are published this will be resolved. | D5: =VLOOKUP(A5,'Issue wise Summary'!A:D,4,FALSE) -> Recurring
A6: Payment not reflecting in RACPAD | B6: 44 | C6: =VLOOKUP(A6,'Issue wise Summary'!A:C,3,FALSE) -> Customer account will be deducted but the payment will not be refelcted in RACPAD. | D6: =VLOOKUP(A6,'Issue wise Summary'!A:D,4,FALSE) -> Recurring | G6: =VLOOKUP(A6,'Issue wise Summary'!A:G,7,FALSE) -> Shared with LEAP team | H6: =VLOOKUP(A6,'Issue wise Summary'!A:H,8,FALSE) -> Check with ESS team if API is present for accesing IQ portal
A7: AutoPay | B7: 38 | C7: =VLOOKUP(A7,'Issue wise Summary'!A:C,3,FALSE) -> Customers unable to enroll into AutoPay | D7: =VLOOKUP(A7,'Issue wise Summary'!A:D,4,FALSE) -> Recurring | E7: =VLOOKUP(A7,'Issue wise Summary'!A:E,5,FALSE) -> Yes | G7: =VLOOKUP(A7,'Issue wise Summary'!A:G,7,FALSE) -> Shared with LEAP team
A8: Unable to create an Agreement | B8: 33 | C8: =VLOOKUP(A8,'Issue wise Summary'!A:C,3,FALSE) -> Stores were unable to create an agreement due to a Change rollback. | D8: =VLOOKUP(A8,'Issue wise Summary'!A:D,4,FALSE) -> One time
A9: Cancel the Manual PO | B9: 33 | C9: =VLOOKUP(A9,'Issue wise Summary'!A:C,3,FALSE) -> Request to cancel Manual PO | D9: =VLOOKUP(A9,'Issue wise Summary'!A:D,4,FALSE) -> Recurring | E9: =VLOOKUP(A9,'Issue wise Summary'!A:E,5,FALSE) -> Yes | F9: =VLOOKUP(A9,'Issue wise Summary'!A:F,6,FALSE) -> PRB0045846
A10: PIN reset | B10: 25 | C10: =VLOOKUP(A10,'Issue wise Summary'!A:C,3,FALSE) -> Request to Reset CW PIN | D10: =VLOOKUP(A10,'Issue wise Summary'!A:D,4,FALSE) -> Recurring | G10: =VLOOKUP(A10,'Issue wise Summary'!A:G,7,FALSE) -> Need to discuss with Business if the RESET PIN option can be provided to user itself.
A11: Customer refund | B11: 24 | C11: =VLOOKUP(A11,'Issue wise Summary'!A:C,3,FALSE) -> Customer has not received the refund | D11: =VLOOKUP(A11,'Issue wise Summary'!A:D,4,FALSE) -> Recurring | E11: =VLOOKUP(A11,'Issue wise Summary'!A:E,5,FALSE) -> Yes | F11: =VLOOKUP(A11,'Issue wise Summary'!A:F,6,FALSE) -> PRB0044395 | H11: =VLOOKUP(A11,'Issue wise Summary'!A:H,8,FALSE) -> check with Data Services team on this pattern
A12: Void agreement | B12: 24 | C12: Request to void agreement | D12: Recurring
A13: Unable to print service sheet | B13: 21 | C13: =VLOOKUP(A13,'Issue wise Summary'!A:C,3,FALSE) -> Store were unable to print service sheet. This issue was caused due to a release | D13: =VLOOKUP(A13,'Issue wise Summary'!A:D,4,FALSE) -> One time
A14: Agreement switch-out completed, but inventory remains in "Pending Switch Out" status | B14: 21 | C14: =VLOOKUP(A14,'Issue wise Summary'!A:C,3,FALSE) -> Agreement switch-out completed, but inventory remains in "Pending Switch Out" status | D14: =VLOOKUP(A14,'Issue wise Summary'!A:D,4,FALSE) -> Recurring | E14: =VLOOKUP(A14,'Issue wise Summary'!A:E,5,FALSE) -> Yes | F14: =VLOOKUP(A14,'Issue wise Summary'!A:F,6,FALSE) -> PRB0045906
A15: There was an error processing your request popup | B15: 20 | C15: =VLOOKUP(A15,'Issue wise Summary'!A:C,3,FALSE) -> When taking payments the store will recievie a popup saying there was an error | D15: =VLOOKUP(A15,'Issue wise Summary'!A:D,4,FALSE) -> One time
A16: Unable to save customer survey | B16: 19 | C16: Stores unable to save the customer survey | D16: One time
A17: Customer not eligible for reward error | B17: 18 | C17: =VLOOKUP(A17,'Issue wise Summary'!A:C,3,FALSE) -> Stores were getting an error popup saying "Customer not eligible for reward error" | D17: =VLOOKUP(A17,'Issue wise Summary'!A:D,4,FALSE) -> One time
A18: Unable to confirm delivery | B18: 16 | C18: =VLOOKUP(A18,'Issue wise Summary'!A:C,3,FALSE) -> CW is unable to confirm delivery. This can be due to missing customer contact details. Once updated they will be able to confirm delivery | D18: =VLOOKUP(A18,'Issue wise Summary'!A:D,4,FALSE) -> Recurring | H18: =VLOOKUP(A18,'Issue wise Summary'!A:H,8,FALSE) -> Create a problem ticket
A19: Unable to add package items | B19: 15 | C19: =VLOOKUP(A19,'Issue wise Summary'!A:C,3,FALSE) -> Stores were unable to add items to package. This issue was caused due to a release | D19: =VLOOKUP(A19,'Issue wise Summary'!A:D,4,FALSE) -> One time
A20: Level 0 customer cannot order phone | B20: 14 | C20: =VLOOKUP(A20,'Issue wise Summary'!A:C,3,FALSE) -> A customer who is level 0 cannot order a mobile phone | D20: =VLOOKUP(A20,'Issue wise Summary'!A:D,4,FALSE) -> Recurring | G20: =VLOOKUP(A20,'Issue wise Summary'!A:G,7,FALSE) -> FIxed by dev
A21: TRIFECTA code is charging tax | B21: 13 | C21: When using the code TRIFECTA tax was being applied | D21: Recurring | E21: Yes | F21: PRB0046123
A22: Error in RmsReserveOrderService | B22: 12 | C22: =VLOOKUP(A22,'Issue wise Summary'!A:C,3,FALSE) -> When adding an item to create an agreement, "Error in RMSReserveOrderService" message pops up. This can be due to the item being Out of stock | D22: =VLOOKUP(A22,'Issue wise Summary'!A:D,4,FALSE) -> Recurring
A23: PIN not working | B23: 12 | C23: This was a one time issue where CW's PIN was not working | D23: One time
A24: Payment reversal | B24: 11
A25: Wrong SAC | B25: 11
A26: TRIFECTA code missing in dropdown | B26: 11
A27: Report related issues | B27: 10
A28: Unable to fetch the data | B28: 9
A29: Drop reconciliation issue | B29: 8
A30: Report issues | B30: 8
A31: Incorrect due date | B31: 8
A32: Cancel the RMS PO | B32: 8
A33: Unable to add card | B33: 8
A34: Void the agreement and change the inventory status to idle | B34: 8
A35: Customer level change request | B35: 7
... A295: Change the inventory status | B295: 1
