Workbook

Sheet Dump
A1: Number | B1: Priority | C1: Created | D1: Updated | E1: Status | F1: Assigned to | G1: Action | H1: Short Description | I1: Description | J1: Assignment Group | K1: Location | L1: Parent | M1: Caused by Change | N1: Problem | O1: Category | P1: Module | Q1: Type Of Issue | R1: Steps taken to fix
A2: INCTEC1587933 | B2: 4 - Low | C2: 46044.408 | D2: 46051.75 | E2: Closed | F2: Vandana K | G2: RACPAD - other | H2: cannot access RACPad | I2: Employee Kelly Pike, ID#100914 cannot access RACPad | J2: RACPad Support | K2: 03982 - COVINGTON-HWY 278 NE - A - M0136 - R0008 - S07 - RACUSA | N2: PRB0045218 | O2: Incident | P2: Access | Q2: RACPAD Access not available
A3: INCTEC1588121 | B3: 4 - Low | C3: 46044.601 | D3: 46052.542 | E3: Closed | F3: monisha d | G3: RACPAD - Store | H3: Racpad store access 00648 | I3: not allowing me to access anything on racpad Issue : Need a Racpad store access 00648 EMP name : Elijah Bowles EMP ID : 369391 Store number : 00648 | J3: RACPad Support | K3: 00648 - ALTOONA - A - M0288 - R0058 - S08 - RACUSA | M3: CHG0050487 | N3: PRB0045218 | O3: Incident | P3: Access | Q3: RACPAD Access not available
A4: INCTEC1588496 | B4: 4 - Low | C4: 46045.517 | D4: 46052.417 | E4: Closed | F4: Abhishek TV | G4: RACPAD - Store | H4: Racpad store access 04006 | I4: EMP Name : Kaitlyn Crutchfield EMP ID : 324623 Store Number: 04006 Issue: Need a racpad store access of 04006 | J4: RACPad Support | K4: 04006 - GREENVILLE-LAURENS RD - A - M0032 - R0008 - S07 - RACUSA | N4: PRB0045218 | O4: Incident | P4: Access | Q4: RACPAD Access not available
A5: INCTEC1588567 | B5: 4 - Low | C5: 46045.608 | D5: 46052.417 | E5: Closed | F5: Prasanth K | G5: RACPAD - Store | H5: Racpad store access 04159 | I5: Issue: Need a racpad store access of 04159 EMP Name : Quatravious Brown EMP ID : 360579 Store number : 04159 | J5: RACPad Support | K5: 04159 - RIVERA BEACH-BROADWAY - A - M0159 - R0024 - S08 - RACUSA | N5: PRB0045218 | O5: Incident | P5: Access | Q5: RACPAD Access not available
A6: INCTEC1587322 | B6: 4 - Low | C6: 46042.758 | D6: 46054.417 | E6: Closed | F6: Pratik Singar | G6: RACPAD - Store | H6: (No subject) | I6: Good afternoonm , coworker id : 341175 doesn't have access to his racpad , thank you | J6: RACPad Support | K6: 01206 - EAST MIAMI - A - M0158 - R0024 - S08 - RACUSA | N6: PRB0045218 | O6: Incident | P6: Access | Q6: RACPAD Access not available
A7: INCTEC1586770 | B7: 4 - Low | C7: 46041.745 | D7: 46053.458 | E7: Closed | F7: Lalit RameshTurkar | G7: RACPAD - other | H7: 100858@rentacenter.com does not have access to rac pad | I7: 100858@rentacenter.com does not have access to rac pad | J7: RACPad Support | K7: 02309 - PROVO - A - M0234 - R0040 - S07 - RACUSA | N7: PRB0045218 | O7: Incident | P7: Access | Q7: RACPAD Access not available
A8: INCTEC1581790 | B8: 4 - Low | C8: 46029.553 | D8: 46037.25 | E8: Closed | F8: Vandana K | G8: RACPAD - other | H8: access issue | I8: BRADLEY EDWARDS, STORE EMPLOYEE CANNOT LOG IN THE SYSTEM, DOES NOT SHOW AS COWORKER EID: 335567 Name: Bradley Edwards Store: 00822, verified on workday Issue: >CW is not getting store 00822 on racpad, he is still having access to his previous store >CWs needs access to his new assigned store | J8: RACPad Support | K8: 00822 - SAPULPA - A - M0422 - R0080 - S08 - RACUSA | N8: PRB0045218 | O8: Incident | P8: Access | Q8: RACPAD Access not available
A9: INCTEC1590750 | B9: 4 - Low | C9: 46051.451 | D9: 46058.375 | E9: Closed | F9: Abhishek TV | G9: RACPAD - other | H9: Coworker John Keagy (EID 142902) is an employee of 01490. He is a FORMER employee of 01482. He is still able to log into 01482. He has accidentally messed up 01482's final drops twice. Can we please remove his access from 01482? | I9: Coworker John Keagy (EID 142902) is an employee of 01490. He is a FORMER employee of 01482. He is still able to log into 01482. He has accidentally messed up 01482's final drops twice. Can we please remove his access from 01482? | J9: RACPad Support | K9: 01482 - LAWRENCE - A - M0222 - R0080 - S08 - RACUSA | N9: PRB0045218 | O9: Incident | P9: Access | Q9: RACPAD Access not available
A10: INCTEC1588660 | B10: 4 - Low | C10: 46045.787 | D10: 46063.371 | E10: Resolved | F10: Lalit RameshTurkar | G10: RACPAD - Store | H10: Does not have access to RACPad | I10: Does not have access to RACPad Store number: 01021 Coworker name and ID: Ryan Baker Were cache and cookies cleared? Yes Was the computer restarted? Yes Is this happening on one computer or all computers? Example Computer name: 01021-2KT05K3 Computer IP: Steps were taken to arrive at the problem: Time of occurrence (Recreate the issue and notate the time if needed): Screenshot required: YES Required Screenshots: 1 ADP Active Status 1 OKTA Applications 1 of the 'Console' tab 2 for the 'Network' tab (1 of 'current' and 1 of 'menu-and-stores') 1 for the RACPAD screen 1 for the SIMS screen (if applicable) | J10: RACPad Support | K10: 01021 - TUSCALOOSA - A - M0045 - R0070 - S08 - RACUSA | N10: PRB0045218 | O10: Incident | P10: Access | Q10: RACPAD Access not available
A11: INCTEC1587528 | B11: 4 - Low | C11: 46043.427 | D11: 46060.167 | E11: Closed | F11: Sushmitha Sannidhi | G11: Emily | H11: Emily | Emily Metrics | | I11: Emily Metrics unavailable. Says i do not have permission to EMILY . Need access do D0186 stores. 345, 1844, 2838, 647, 2058, 2416, 2723, 3894, 3994, 4598 | J11: RACPad Support | K11: M0186 - N/A - M0186 - R0065 - S08 - RTO | N11: PRB0045218 | O11: Incident | P11: Access | Q11: RACPAD Access not available
A12: INCTEC1588343 | B12: 4 - Low | C12: 46045.344 | D12: 46055.542 | E12: Closed | F12: roopesh pothodi | G12: RACPAD - Store | H12: High Touch-Access | Other | | I12: Brief description of issue RAC PAD not working for Samuel Salley employee #348603 Employee name: Samuel Salley EMPID: 348603 Store: 00830 Call back number: (843) 747-9908 issue: Unable to access RACPAD Detailed issue: >CW reported that she getting an error while trying to access RACPAD. Troubleshooting steps: >Connected through remote. >Verified the same issue from user end. >Tried browser optimization and different browser. >However CW getting the same error (SNIP attached) >Informed CW that will escalate the ticket to the concern Team to check further. | J12: RACPad Support | K12: 00830 - N CHARLESTON-RIVERS - A - M0001 - R0007 - S08 - RACUSA | N12: PRB0045218 | O12: Incident | P12: Access | Q12: RACPAD Access not available
A13: INCTEC1589322 | B13: 4 - Low | C13: 46048.375 | D13: 46051.875 | E13: Closed | F13: praveen panditi | G13: Other | H13: Immediate RACPAD access needed - URGENT | I13: Good morning, We recently had a major ice storm and I need immediate emergency access for RACPAD to be granted to Ron Laney EID 31093 for stores 2974 and 3713. He will need SM access and for as long as we can grant it. Thank You, From: Erik Burgos Soto <erik.burgos@upbound.com> Sent: Monday, January 26, 2026 8:53 AM To: Dustin Hall <Dustin.Hall@rentacenter.com>; Sevicedeskprod <ServiceDeskprod@Rentacenter.com>; ServiceNowSupport <ServiceNowSupport@Rentacenter.com> Cc: Jason Johnson <Jason.Johnson@rentacenter.com> Subject: Re: Immediate RACPAD access needed - URGENT Hello, Thanks for the note, Dustin. The 'ServiceNowSupport@Rentacenter.com' email DL is an unmonitored account for backend system administrators of our ticketing platform. For immediate assistance with active tickets, please contact the Service Desk at 1-800-275-2696. You may also reach them at SupportRequest@Rentacenter.com. Thanks and Best, Erik Burgos ITSM, RPA, ServiceNow, Atlassian Upbound Group, Inc. (UPBD) Service Desk: 1.800.275.2696 > Book time to meet with me From: Dustin Hall <Dustin.Hall@rentacenter.com> Sent: Monday, January 26, 2026 8:48 AM To: Sevicedeskprod <ServiceDeskprod@Rentacenter.com>; ServiceNowSupport <ServiceNowSupport@Rentacenter.com> Cc: Jason Johnson <Jason.Johnson@rentacenter.com> Subject: Immediate RACPAD access needed - URGENT Good morning, We recently had a major ice storm and I need immediate emergency access for RACPAD to be granted to Ron Laney EID 31093 for stores 2974 and 3713. He will need SM access and for as long as we can grant it. Thank You, | J13: RACPad Support | K13: M0497 - - M0497 - R0039 - S07 - RTO | N13: PRB0045218 | O13: Incident | P13: Access | Q13: RACPAD Access not available
A14: INCTEC1581643 | B14: 3 - Moderate | C14: 46029.375 | D14: 46033.75 | E14: Closed | F14: monisha d | G14: RACPAD - Store | H14: Lost access to all her stores in RACPAD. Her stores should mirror Matt Dee, District Manager of District 480 | I14: Lost access to all her stores in RACPAD. Her stores should mirror Matt Dee, District Manager of District 480 | J14: RACPad Support | K14: M0480 - N/A - M0480 - R0007 - S08 - RTO | N14: PRB0045218 | O14: Incident | P14: Access | Q14: RACPAD Access not available
A15: INCTEC1581640 | B15: 3 - Moderate | C15: 46029.371 | D15: 46033.708 | E15: Closed | F15: Vandana K | G15: RACPAD - Store | H15: Lost access to all his stores in RACPAD | I15: Matt Dee has lost access to all his stores in RACPAD. | J15: RACPad Support | K15: M0480 - N/A - M0480 - R0007 - S08 - RTO | N15: PRB0045218 | O15: Incident | P15: Access | Q15: RACPAD Access not available
... A58: INCTEC1584577 | B58: 4 - Low | C58: 46036.514 | D58: 46045.417 | E58: Closed | F58: monisha d | G58: RACPAD - Store | H58: RACPAD - Store | RACPAD - Daily activity planner | | I58: On the goals tab of Daily Activity Planner, 1.the Actual & Variance are incorrect for all employees 2.Kaosoreal Washington should be removed from store 684 he doesn't work in my location 3. please Add Bradley King EID:132307 4. Add Bailey Bennett EID:100717 | J58: RACPad Support | K58: 00684 - ANCHORAGE-OLD SEWARD - A - M0414 - R0050 - S07 - RACUSA | N58: PRB0045218 | O58: Incident | P58: Access | Q58: RACPAD Access not available
A59: INCTEC1589368 | B59: 4 - Low | C59: 46048.435 | D59: 46053.417 | E59: Closed | F59: monisha d | G59: RACPAD - Store | H59: RACPAD - Store | RACPAD Store issue | | I59: I have signed out of everything multiple times and signed back in and it says I am not assigned to a store in RACPad ======================================================================= Co-worker name: Aaron Ingle Employee ID: 223270 Store: 02043 Issue: CW mentioned he is unable to login RACPAD. Getting error message. Need help with this. | J59: RACPad Support | K59: 02043 - 39TH & MACARTHUR - A - M0542 - R0080 - S08 - RACUSA | M59: CHG0050496 | N59: PRB0045218 | O59: Incident | P59: Access | Q59: RACPAD Access not available
A60: INCTEC1585553 | B60: 4 - Low | C60: 46038.56 | D60: 46048.375 | E60: Closed | F60: SatyaMurthy Dharmavarapu | G60: RACPAD - Store | H60: RACPAD - Store | RACPAD Store issue | | I60: I use to work for store 2621 in Brewer Maine and I now work for the store in Bangor Maine and I can still see there information and I was hoping to get that taken off. | J60: RACPad Support | K60: 00925 - BANGOR - A - M0272 - R0065 - S08 - RACUSA | N60: PRB0045218 | O60: Incident | P60: Access | Q60: RACPAD Access not available
A61: INCTEC1590334 | B61: 4 - Low | C61: 46050.449 | D61: 46059.125 | E61: Closed | F61: Vandana K | G61: RACPAD - Store | H61: RACPAD - Store | RACPAD Store issue | | I61: employee treyvon overstreet EID 330256 can still log into the wrong location and is unable to load any reports for store 01880 | J61: RACPad Support | K61: 01880 - AUBURN - A - M0314 - R0002 - S07 - RACUSA | N61: PRB0045218 | O61: Incident | P61: Access | Q61: RACPAD Access not available
A62: INCTEC1581646 | B62: 4 - Low | C62: 46029.378 | D62: 46044.5 | E62: Closed | F62: roopesh pothodi | G62: RACPAD - Store | H62: RACPAD - Store | RACPAD Store issue | | I62: Unable to login on any computer. My store info doesn't show. I've restarted every and tried logging into another profile.. Same results. Employee Name Bryce Robinson EID 369748 Store 02447 | J62: RACPad Support | K62: 02447 - CHESAPEAKE - A - M0007 - R0007 - S08 - RACUSA | N62: PRB0045218 | O62: Incident | P62: Access | Q62: RACPAD Access not available
A63: INCTEC1581425 | B63: 4 - Low | C63: 46028.662 | D63: 46034.375 | E63: Closed | F63: racha sahithya | G63: RACPAD - Store | H63: RACPAD - Store | The application is temporarily unavailable | | I63: Issue Description: CW reported that his RACPad only displays Account Management and is not attached to any store. No other options are available. This issue is not occurring for other coworkers at the same location. Employee Name: David Santiago2 Employee ID: 369651 Store: 04478 | J63: RACPad Support | K63: 04478 - CATSKILL-CATSKILL COMMON - A - M0444 - R0002 - S07 - RACUSA | N63: PRB0045218 | O63: Incident | P63: Access | Q63: RACPAD Access not available
A64: INCTEC1589552 | B64: 4 - Low | C64: 46048.606 | D64: 46054.75 | E64: Closed | F64: dazel dsouza | G64: RACPAD - Account Management | H64: RACPAD - Account Management | Worked History | | I64: A number of accounts have field visits being logged by an associate at another store on customers who are not min but are showing up on my AM activity log. The associate logging the visits is Amarion Lock. I do not know this employee. Customer ID: 00000 Customer Name: Lydia TRUJILLO Date and Time Issue Was Occured: 2026-01-26 14:16:36 | J64: RACPad Support | K64: 01238 - TAMPA-EAST - A - M0543 - R0024 - S08 - RACUSA | N64: PRB0045218 | O64: Incident | P64: Access | Q64: RACPAD Access not available
A65: INCTEC1587341 | B65: 4 - Low | C65: 46042.808 | D65: 46050.208 | E65: Closed | F65: Rashmitha Shetty | G65: RACPAD - Dashboard | H65: RACPAD - Dashboard | Dashboard - Other | | I65: Name: Ryan Looman EID: 361770 Store: 02034 Issue description: getting error messages when logging in. | J65: RACPad Support | K65: 02034 - CLASSEN - A - M0542 - R0080 - S08 - RACUSA | N65: PRB0045218 | O65: Incident | P65: Access | Q65: RACPAD Access not available
A66: INCTEC1590518 | B66: 4 - Low | C66: 46050.751 | D66: 46055.208 | E66: Closed | F66: Vandana K | G66: RACPAD - Dashboard | H66: RACPAD - Dashboard | Dashboard - Other | | I66: issue signing in, image pop up ever time. | J66: RACPad Support | K66: 02034 - CLASSEN - A - M0542 - R0080 - S08 - RACUSA | N66: PRB0045218 | O66: Incident | P66: Access | Q66: RACPAD Access not available
A67: INCTEC1588923 | B67: 4 - Low | C67: 46046.536 | D67: 46054.875 | E67: Closed | F67: monisha d | G67: RACPAD - Dashboard | H67: RACPAD - Dashboard | Dashboard - Other | | I67: Collin Thompson cant not get into racpad at all, it goes to an error screen ================================================================ Co-worker name: Collin Thompson2 Employee ID: 101014 Store: 00974 Issue: CW mentioned he is unable to login RACPAD. Getting error message. Need help with this. | J67: RACPad Support | K67: 00974 - POCATELLO - A - M0333 - R0050 - S07 - RACUSA | M67: CHG0050496 | N67: PRB0045218 | O67: Incident | P67: Access | Q67: RACPAD Access not available
A68: INCTEC1581138 | B68: 4 - Low | C68: 46028.36 | D68: 46034.417 | E68: Closed | F68: roopesh pothodi | G68: RACPAD - Dashboard | H68: RACPAD - Incorrect Store Login in RACPAD | I68: Store number: 00362 Coworker name and ID: Michael Velazquez (365222) Issue description: In RACPAD, Coworker reported being logged into store 00027 instead of the correct store 00362. Screen shot required: YES | J68: RACPad Support | K68: 00362 - CLEVELAND-WEST TOWN - A - M0196 - R0061 - S08 - RACUSA | N68: PRB0045218 | O68: Incident | P68: Access | Q68: RACPAD Access not available
A69: INCTEC1579643 | B69: 4 - Low | C69: 46024.58 | D69: 46033.375 | E69: Closed | F69: roopesh pothodi | G69: RACPAD - other | H69: RACPAD - other | I69: I'm the Store Manager at 4366 and I can't do extension on any customer account and I need to be able to give extension to my good paying customers that need help on ther accounts. Employee name- Charlie Gray Employee id - 188479 Store- 04366 | J69: RACPad Support | K69: 04366 - HATTIESBURG-BROADWAY - A - M0084 - R0008 - S07 - RACUSA | N69: PRB0045218 | O69: Incident | P69: Access | Q69: RACPAD Access not available
A70: INCTEC1588076 | B70: 4 - Low | C70: 46044.54 | D70: 46053.292 | E70: Closed | F70: Tejas Acharya | G70: RACPAD - other | H70: RACPAD - other | RACPAD Owner Config | | I70: Cannot log into Racpad Employee name- Lee Cain Employee id - 361130 Store- 00639 | J70: RACPad Support | K70: 00639 - CEDAR TOWN-MAIN - A - M0045 - R0070 - S08 - RACUSA | N70: PRB0045218 | O70: Incident | P70: Access | Q70: RACPAD Access not available
A71: INCTEC1579907 | B71: 4 - Low | C71: 46025.357 | D71: 46032.5 | E71: Closed | F71: Vandana K | G71: RACPAD - other | H71: RACFI-RACPAD - other | RACPAD Owner Config | | I71: Kirby Smith is not on it and he can't sign in. Employee name: Kirby Smith EMPID: 6020961 Store: 03553 Title: Store Manager-In Training Issue: Unable to access RACPAD app. | J71: RACPad Support | K71: 03553 - WILMINGTON-ROMBACH - A - M0510 - R0997 - S091 - RACFI | N71: PRB0045218 | O71: Incident | P71: Access | Q71: RACPAD access not available
A72: INCTEC1582004 | B72: 4 - Low | C72: 46030.358 | D72: 46038.292 | E72: Closed | F72: Tejas Acharya | G72: RACPAD - other | H72: RACFI-RACPAD - other | RACPAD Owner Config | | I72: When accessing the Racpad page he gts an error : I'm sorry but you currently don't have the necessary permissions to access this page. Please contact an administrator if you feel this is an error. | J72: RACPad Support | K72: 07237 - - A - M7017 - R0708 - S712 - RACFI | N72: PRB0045218 | O72: Incident | P72: Access | Q72: RACPAD access not available
A73: INCTEC1587977 | B73: 4 - Low | C73: 46044.448 | D73: 46053.292 | E73: Closed | F73: Tejas Acharya | G73: RACPAD - other | H73: RACPAD - other | RACPAD Owner Config | | I73: Anthony Warrington EID:100874 can not log into rac pad says admin error | J73: RACPad Support | K73: 00429 - EUSTIS - A - M0132 - R0024 - S08 - RACUSA | N73: PRB0045218 | O73: Incident | P73: Access | Q73: RACPAD Access not available
A74: INCTEC1589842 | B74: 4 - Low | C74: 46049.379 | D74: 46058.75 | E74: Closed | F74: Pratik Singar | G74: RACPAD - other | H74: RACPAD - other | RACPAD Owner Config | | I74: CW Name: Damien LanhamKeister Emp ID:370120 Store:00417 Description of issue: Can't login to RACPAD cw is getting an error | J74: RACPad Support | K74: 00417 - ASHEVILLE-PATTON - A - M0480 - R0007 - S08 - RACUSA | N74: PRB0045218 | O74: Incident | P74: Access | Q74: RACPAD Access not available
A75: INCTEC1589837 | B75: 4 - Low | C75: 46049.377 | D75: 46054.417 | E75: Closed | F75: Abhishek TV | G75: RACPAD - other | H75: RACPAD - other | RACPAD Owner Config | | I75: Will not allow me to login User: Nick Blackwelder EMP ID: 368485 Store: 00417 | J75: RACPad Support | K75: 00417 - ASHEVILLE-PATTON - A - M0480 - R0007 - S08 - RACUSA | N75: PRB0045218 | O75: Incident | P75: Access | Q75: RACPAD Access not available
A76: INCTEC1587619 | B76: 4 - Low | C76: 46043.527 | D76: 46051.333 | E76: Closed | F76: monisha d | G76: RACPAD - other | H76: RACPAD - other | RACPAD Owner Config | | I76: Tony Doll ( owner of Doble Inc.) cannot log into RACPAD. He is getting a message that he does not have permission. Could we please call and get it fixed? This is causing him issues with pricing rentals! ========================================================= Co-worker name: Tony Doll Employee ID: 313296 Store: R0704 Issue: CW mentioned he is unable to login RACPAD. Getting error message. Need help with this. | J76: RACPad Support | K76: R0704 - - R0704 - S707 - FRC | N76: PRB0045218 | O76: Incident | P76: Access | Q76: RACPAD Access not available
A77: INCTEC1581287 | B77: 4 - Low | C77: 46028.487 | D77: 46034.458 | E77: Closed | F77: Tejas Acharya | G77: RACPAD - other | H77: RACPAD - other | RACPAD Owner Config | | I77: RacPad does not show that I am in any store location --------------------------------- Emp name: Freddie WalterGates Emp id: 369688 Store number:02041 Issue: No Stores are assigned to the user in Racpad Error snapshot is attached | J77: RACPad Support | K77: 02041 - PEORIA - A - M0422 - R0080 - S08 - RACUSA | N77: PRB0045218 | O77: Incident | P77: Access | Q77: RACPAD Access not available
A78: INCTEC1587437 | B78: 3 - Moderate | C78: 46043.32 | D78: 46052.542 | E78: Closed | F78: roopesh pothodi | G78: RACPAD - other | H78: RACPAD - other | RACPAD Owner Config | | I78: I cannot get in RACPAD at all. Says I don't have permission. See screen shot. | J78: RACPad Support | K78: R0995 - - R0995 - S095 - FRC | N78: PRB0045218 | O78: Incident | P78: Access | Q78: RACPAD Access not available
A79: INCTEC1583939 | B79: 4 - Low | C79: 46035.317 | D79: 46047.208 | E79: Closed | F79: Sushmitha Sannidhi | G79: RACPAD - Dashboard | H79: RACPAD - Sales Person Tab – Coworker Name Not Visible | I79: Store number: 04495 Coworker name and ID: Nathan Cavers (350093) Issue description: While creating agreement coworker's name is not visible in Sales Person tab to select his name. Screen shot required: YES | J79: RACPad Support | K79: 04495 - MEDINA-MAIN - A - M0434 - R0058 - S08 - RACUSA | N79: PRB0045218 | O79: Incident | P79: Access | Q79: RACPAD Access not available
... A113: INCTEC1585398 | B113: 4 - Low | C113: 46038.414 | D113: 46046.208 | E113: Closed | F113: Tejas Acharya | G113: RACPAD - Dashboard | H113: RACPAD-Login issue | I113: Store number: 02937 Coworker name and ID: James Cook3 || 100777 Computer name: 02937-3PSSH63 Issue description: RACPAD login issue Steps taken to arrive at problem: RACPAD Login Dashboard | J113: RACPad Support | K113: 02937 - CAMP BOWIE BLVD - A - M0060 - R0080 - S08 - RACUSA | N113: PRB0045218 | O113: Incident | P113: Access | Q113: RACPAD Access not available
A114: INCTEC1589518 | B114: 4 - Low | C114: 46048.565 | D114: 46053.417 | E114: Closed | F114: monisha d | G114: RACPAD - Store | H114: store 02329 - Coworker Access | I114: Good Morning, I have an employee who can see several store systems. His employee ID number is 3310009 and he can currently see store 00346 and store 02329 but he is only assigned to store 2329. Can you help me with this? | J114: RACPad Support | K114: 02329 - DENBIGH - A - M0007 - R0007 - S08 - RACUSA | M114: CHG0050496 | N114: PRB0045218 | O114: Incident | P114: Access | Q114: RACPAD Access not available
A115: INCTEC1586040 | B115: 4 - Low | C115: 46039.733 | D115: 46047.208 | E115: Closed | F115: Sushmitha Sannidhi | G115: RACiNET | H115: RACiNET | No access allowed | | I115: No access allowed i keep getting ERROR MESSAGE when trying to open racpad | J115: RACPad Support | K115: 02345 - WINCHESTER - A - M0288 - R0058 - S08 - RACUSA | N115: PRB0045218 | O115: Incident | P115: Access | Q115: RACPAD access not available
A116: INCTEC1580011 | B116: 4 - Low | C116: 46025.566 | D116: 46034.458 | E116: Closed | F116: Sushmitha Sannidhi | G116: Store Network | H116: Store Network | Other | | I116: I can not use my code to do extensions as the store manager. | J116: RACPad Support | K116: 02160 - NASHVILLE-BORDEAUX - A - M0488 - R0070 - S08 - RACUSA | N116: PRB0045218 | O116: Incident | P116: Access | Q116: RACPAD Access not available
A117: INCTEC1584286 | B117: 4 - Low | C117: 46035.697 | D117: 46040.583 | E117: Closed | F117: Abhishek TV | G117: RACPAD Access | H117: Temporary Role AND Location Assignment Request | I117: Who is making the request? (person on the phone): Josh Lopez - RVP Role's Start Date: 01/13/2026 Role's End Date (cannot exceed seven [7] days): 01/19/2026 Coworker Who Needs Role Change Name: Tiffeny Carroll Coworker Who Needs Role Change EID: 304531 Coworker Current Position: Store Manager Coworker Requested Position: District Manager Store #: District #: M0089 Region #: R0040 Was verbal approval given by the appropriately-authorized person? <Yes> • If yes, provide their first and last name: •• If no, send e-mail utilizing template to appropriately-authorized person and copy sent e-mail into Work Notes. | J117: RACPad Support | K117: R0040 - N/A - R0040 - S07 - RTO | N117: PRB0045218 | O117: Request | P117: Access | Q117: RACPAD Access not available
A118: INCTEC1584155 | B118: 4 - Low | C118: 46035.536 | D118: 46041.375 | E118: Closed | F118: Abhishek TV | G118: RACPAD Access | H118: Temporary Role Assignment AND Location Request | I118: Who is making the request? : John Neider Role's Start Date: 01/13/2026 Role's End Date (cannot exceed seven [7] days): 01/21/2026 Coworker Who Needs Role Change Name: Joshua Miller Coworker Who Needs Role Change EID: 142916 Coworker Current Position: District Manager - Interim Coworker Requested Position: District Manager Store #: District #: M0473 Region #: R0002 Was verbal approval given by the appropriately-authorized person? n/a • If yes, provide their first and last name: •• If no, send e-mail utilizing template to appropriately-authorized person and copy sent e-mail into Work Notes. | J118: RACPad Support | K118: R0002 - N/A - R0002 - S07 - FRC | N118: PRB0045218 | O118: Request | P118: Access | Q118: RACPAD Access not available
A119: INCTEC1587113 | B119: 4 - Low | C119: 46042.505 | D119: 46051.333 | E119: Closed | F119: monisha d | G119: RACPAD - other | H119: RACPAD | I119: User called in for new hire 100860 unable to access RACPAD Store number: 01419 - SOUTH CHICAGO HEIGHTS - A - M0299 - R0039 - S07 - RACUSA Coworker name and ID: Lawrence Wilkes 100860 Customer name and number: Computer name: 01419-6R98Z93 IP address: 10.105.138.40 Issue description: User called in for new hire 100860 unable to access RACPAD Steps taken to arrive at problem: Time of occurrence (Recreate the issue and notate the time if needed): Screen shot required: YES | J119: RACPad Support | K119: 01419 - SOUTH CHICAGO HEIGHTS - A - M0299 - R0039 - S07 - RACUSA | N119: PRB0045218 | O119: Incident | P119: Access | Q119: RACPAD access not available
A120: INCTEC1585486 | B120: 4 - Low | C120: 46038.488 | D120: 46045.583 | E120: Closed | F120: shruthika c | G120: RACPAD - Store | H120: RACPad | I120: Issue: CW reported that he is unable to access RACPad. Employee Name: Johnnyrey Sanchez Employee ID: 100775 Store: 04446 | J120: RACPad Support | K120: 04446 - ALBUQUERQUE-4TH ST - A - M0539 - R0011 - S07 - RACUSA | N120: PRB0045218 | O120: Incident | P120: Access | Q120: RACPAD access not available
A121: INCTEC1585624 | B121: 4 - Low | C121: 46038.635 | D121: 46047.375 | E121: Closed | F121: Sushmitha Sannidhi | G121: RACPAD - other | H121: RACPAD- | I121: Employee Martez Porter (325521) does not have access to RacPad. He is a new hire. ----------------------------------------------------------------------------------------------------------------------------------------------- Store number:01643 Coworker name and ID: Martez Porter || 325251 Issue description: RACPAD login issue Steps taken to arrive at problem: RACPAD login | J121: RACPad Support | K121: 01643 - REDFORD-GRAND RIVER - A - M0415 - R0020 - S08 - RACUSA | N121: PRB0045218 | O121: Incident | P121: Access | Q121: RACPAD access not available
A122: INCTEC1581994 | B122: 4 - Low | C122: 46030.34 | D122: 46045.709 | E122: Closed | F122: Lalit RameshTurkar | G122: RACPAD - other | H122: Racpad | I122: Will not let us login to racpad on multiple computers keeps saying we do not have access and to please contact system administrator Issue : IN the Racpad the store is not showing for 2 user EMP Name : James Hillard EMP ID : 309758 Store: 07202 EMP Name: LeNayan Holmes EMP ID: 349924 Store: 07202 | J122: RACPad Support | K122: 07202 - - A - M7025 - R0995 - S095 - RACFI | N122: PRB0045218 | O122: Incident | P122: Access | Q122: RACPAD access not available
A123: INCTEC1580902 | B123: 4 - Low | C123: 46027.668 | D123: 46029.114 | E123: Closed | F123: Prasanth K | G123: RACPAD - Store | H123: RACPAD - Dual Store access | I123: Rehire : Kefier Smith EID # 311517 Shows access to 2 stores (old store 426, home store 885) | J123: RACPad Support | K123: M0340 - N/A - M0340 - R0011 - S07 - RTO | N123: PRB0045218 | O123: Incident | P123: Access | Q123: RACPAD access not available
A124: INCTEC1582079 | B124: 4 - Low | C124: 46030.441 | D124: 46032.489 | E124: Closed | F124: Prasanth K | G124: RACPAD - Reports | H124: RACPAD - Reports | Daily Report | not able to access racpad | I124: Store number:00105 Coworker name and ID: Fernando Roberto | 149679 Computer name: IP address: Issue description: not able to access racpad Steps taken to arrive at problem: Time of occurrence (Recreate the issue and notate the time if needed): Screen shot required: YES | J124: RACPad Support | K124: 00105 - CAGUAS - A - M0139 - R0024 - S08 - RACPR | N124: PRB0045218 | O124: Incident | P124: Access | Q124: RACPAD access not available
A125: INCTEC1587590 | B125: 4 - Low | C125: 46043.499 | D125: 46051.75 | E125: Closed | F125: Vandana K | G125: RACPAD - Store | H125: RACPAD - Store | 1-Way Sync | | I125: Coworkers - Daniel Hernandez of store 32017, Kervin Romero of store 4451, Justin Leiter of store 2558, Timothy Lyons of store 2558 all need to have their racpad access restricted to only their stores. For some reason they have access to multiple locations. | J125: RACPad Support | K125: M0314 - N/A - M0314 - R0002 - S07 - RTO | N125: PRB0045218 | O125: Incident | P125: Access | Q125: RACPAD access not available
A126: INCTEC1588465 | B126: 4 - Low | C126: 46045.488 | D126: 46053.375 | E126: Closed | F126: Prasanth K | G126: RACPAD - Store | H126: RACPAD - Store | Permission issue accessing RACPAD app/page | | I126: Coworker Aaron Ingle does not have access to RACPAD, please reassign his access. ================================================================ Co-worker name: Aaron Ingle Employee ID: 223270 Store: 02043 Issue: CW mentioned he is unable to login RACPAD. Getting error message. Need help with this. | J126: RACPad Support | K126: 02043 - 39TH & MACARTHUR - A - M0542 - R0080 - S08 - RACUSA | N126: PRB0045218 | O126: Incident | P126: Access | Q126: RACPAD access not available
... A140: INCTEC1582277 | B140: 4 - Low | C140: 46030.675 | D140: 46037.375 | E140: Closed | F140: Abhishek TV | G140: RACPAD - Store | H140: RACPAD - Store | Permission issue accessing RACPAD app/page | | I140: Asst. Manager is transfered from Store# 02192 to 02195 but the access is still the old one (02192) | J140: RACPad Support | K140: 02195 - DALLAS - WEBB CHAPEL - A - M0531 - R0080 - S08 - RACUSA | N140: PRB0045218 | O140: Incident | P140: Access | Q140: RACPAD access not available
A141: INCTEC1589006 | B141: 4 - Low | C141: 46046.727 | D141: 46052.542 | E141: Closed | F141: monisha d | G141: RACPAD - Store | H141: RACPAD - Store | Permission issue accessing RACPAD app/page | | I141: my coworkers rodolfo barriga 100675 and cristian torrez cant access rac pad it says "i'm sorry you don't have necessary permission to access this page" Store number: 04977 Coworker name and ID: Ronaldo Mendoza | 362688 Issue description: informed he is facing issue with racpad getting error " "I'm sorry you don't have necessary permission to access this page" Were cache and cookies cleared? Yes Was the computer restarted? Yes Is this happening on one computer or all computers? All Example Computer name: 04977-J7RXP93 Computer IP: 10.119.112.39 Steps were taken to arrive at the problem: MyApps > Racpad Time of occurrence (Recreate the issue and notate the time if needed): Screenshot required: YES Required Screenshots: 1 ADP Active Status 1 OKTA Applications 1 of the 'Console' tab 2 for the 'Network' tab (1 of 'current' and 1 of 'menu-and-stores') 1 for the RACPAD screen 1 for the SIMS screen (if applicable) | J141: RACPad Support | K141: 04977 - - A - M0403 - R0050 - S07 - RACUSA | M141: CHG0050487 | N141: PRB0045218 | O141: Incident | P141: Access | Q141: RACPAD access not available
A142: INCTEC1582570 | B142: 4 - Low | C142: 46031.429 | D142: 46038.375 | E142: Closed | F142: Abhishek TV | G142: RACPAD - Store | H142: RACPAD - Store | Permission issue accessing RACPAD app/page | | I142: Devan Davis- EID 324801 Can not access RacPad | J142: RACPad Support | K142: 04743 - TERRELL-W MOORE AVE - A - M0068 - R0080 - S08 - RACUSA | N142: PRB0045218 | O142: Incident | P142: Access | Q142: RACPAD access not available
A143: INCTEC1585388 | B143: 4 - Low | C143: 46038.405 | D143: 46055.5 | E143: Closed | F143: Lalit RameshTurkar | G143: RACPAD - Store | H143: RACPAD - Store | Permission issue accessing RACPAD app/page | | I143: i cannot log into racpad it tells me i do not have permission to access this page and to contact administrator | J143: RACPad Support | K143: 00456 - JASPER - A - M0045 - R0070 - S08 - RACUSA | N143: PRB0045218 | O143: Incident | P143: Access | Q143: RACPAD access not available
A144: INCTEC1588382 | B144: 4 - Low | C144: 46045.398 | D144: 46052.792 | E144: Closed | F144: monisha d | G144: RACPAD - Store | H144: RACPAD - Store | Permission issue accessing RACPAD app/page | | I144: When Christopher Baisden attempts to access RACPAD we get an error "Please contact an administrator if you feel this is an error When accessing RACPAD Store number: 00801 - COLUMBUS-MORSE - A - M0174 - R0061 - S08 - RACUSA Coworker name and ID: Christopher Baisden 343600 Customer name and number: Computer name: 00801-FTC8Z93 IP address: 10.103.32.63 Issue description: When Christopher Baisden attempts to access RACPAD we get an error "Please contact an administrator if you feel this is an error When accessing RACPAD Steps taken to arrive at problem: Time of occurrence (Recreate the issue and notate the time if needed): Screen shot required: YES | J144: RACPad Support | K144: 00801 - COLUMBUS-MORSE - A - M0173 - R0061 - S08 - RACUSA | N144: PRB0045218 | O144: Incident | P144: Access | Q144: RACPAD access not available
A145: INCTEC1581630 | B145: 4 - Low | C145: 46029.359 | D145: 46034.375 | E145: Closed | F145: Abhishek TV | G145: RACPAD - Store | H145: RACPAD - Store | Permission issue accessing RACPAD app/page | _____________________________________________________________________________ ** Issue with RACPAD from MYAPPS | I145: do not have access to racpad at all -------------------------------------------------------------------------------------------------------------- ** Store number: 02697 Coworker name and ID: Jeanette Pando2 || 332748 Computer name: 02697-DGB8Z93 Issue description: Issue with RACPAD from MYAPPS Steps taken to arrive at problem: Unable to access RACPAD | J145: RACPad Support | K145: 02697 - YUKON-CORNWELL - A - M0542 - R0080 - S08 - RACUSA | N145: PRB0045218 | O145: Incident | P145: Access | Q145: RACPAD access not available
A146: INCTEC1586405 | B146: 4 - Low | C146: 46041.358 | D146: 46047.25 | E146: Closed | F146: Tejas Acharya | G146: RACPAD - Store | H146: RACPAD - Store | RACPAD Store issue | | I146: Justin 366781 can not log in to RacPad Error: It says he does not currently have access to this page. | J146: RACPad Support | K146: 00813 - SPRINGFIELD-LIMESTONE - A - M0173 - R0061 - S08 - RACUSA | N146: PRB0045218 | O146: Incident | P146: Access | Q146: RACPAD access not available
A147: INCTEC1582717 | B147: 4 - Low | C147: 46031.59 | D147: 46040.208 | E147: Closed | F147: Vandana K | G147: RACPAD - Store | H147: RACPAD - Store | RACPAD Store issue | | I147: i currently have access to 2 different stores and ive called in for removal of store 1414 access as it sometimes causes issues with reports and drops | J147: RACPad Support | K147: 01417 - ROCKFORD-S.ROCKFORD - A - M0095 - R0039 - S07 - RACUSA | N147: PRB0045218 | O147: Incident | P147: Access | Q147: RACPAD access not available
A148: INCTEC1581190 | B148: 4 - Low | C148: 46028.411 | D148: 46037.167 | E148: Closed | F148: Rashmitha Shetty | G148: RACPAD - Store | H148: RACPAD - Store | RACPAD Store issue | | I148: I Currently work at store 4612 but still have access to store 4548 | J148: RACPad Support | K148: 04612 - TITUSVILLE-DIAMOND - A - M0417 - R0058 - S08 - RACUSA | N148: PRB0045218 | O148: Incident | P148: Access | Q148: RACPAD access not available
A149: INCTEC1587580 | B149: 4 - Low | C149: 46043.489 | D149: 46048.375 | E149: Closed | F149: Vandana K | G149: RACPAD - Store | H149: RACPAD - Store | The application is temporarily unavailable | | I149: I am the RD for R0708. As of this morning I do not have access to RACPad or any of my 77 stores. Everything else in My Apps (302075) is working correctly. | J149: RACPad Support | K149: R0708 - - R0708 - S712 - FRC | N149: PRB0045218 | O149: Incident | P149: Access | Q149: RACPAD access not available
A150: INCTEC1584944 | B150: 4 - Low | C150: 46037.435 | D150: 46047.583 | E150: Closed | F150: Lalit RameshTurkar | G150: RACPAD - Store | H150: RACPAD - Store | The application is temporarily unavailable | | I150: Not letting me access RACpad | J150: RACPad Support | K150: 04232 - BOURBONNAIS-KENNEDY DR - A - M0509 - R0019 - S08 - RACUSA | N150: PRB0045218 | O150: Incident | P150: Access | Q150: RACPAD access not available
A151: INCTEC1589050 | B151: 4 - Low | C151: 46047.121 | D151: 46051.122 | E151: Closed | F151: Prasanth K | G151: RACPAD - Store | H151: RACPAD - Store | The application is temporarily unavailable | RACPAD - Store | The application is temporarily unavailable | | I151: Employee ID 396232 Can not access racpad | J151: RACPad Support | K151: 01374 - DECATUR - A - M0509 - R0019 - S08 - RACUSA | N151: PRB0045218 | O151: Incident | P151: Access | Q151: RACPAD access not available
A152: INCTEC1585349 | B152: 4 - Low | C152: 46038.364 | D152: 46047.25 | E152: Closed | F152: Tejas Acharya | G152: RACPAD - Store | H152: Racpad - Access Issue | I152: Cannot get the access to Racpad as it gives an error to contact the administrator | J152: RACPad Support | K152: 00607 - ST.ROBERT - A - M0214 - R0080 - S08 - RACUSA | N152: PRB0045218 | O152: Incident | P152: Access | Q152: RACPAD access not available
A153: INCTEC1584022 | B153: 4 - Low | C153: 46035.429 | D153: 46044.458 | E153: Closed | F153: Pratik Singar | G153: RACPAD - Store | H153: RACPAD access issue . | I153: Unable to access the RACPAD. Employee name- Virgine Viernes Employee id - 357625 >Need access same as Audie Nano EID 355777 | J153: RACPad Support | K153: H0003 - - Active - FSC | N153: PRB0045218 | O153: Incident | P153: Access | Q153: RACPAD access not available
... A160: INCTEC1581260 | B160: 4 - Low | C160: 46028.466 | D160: 46034.75 | E160: Closed | F160: Abhishek TV | G160: RACPAD - other | H160: RACPAD - other | RACPAD Owner Config | | I160: I previously had access to the following tabs: Operations, Payment, Customer, Account Management, Inventory, Reports, and Store. Today I only have access to the Operations and Account Management tabs. Could you please restore my previous access? Employee Name Jackie Valenzuela Email jackeline.valenzuela@acima.com EID 315558 Store : - user is from COmpliance DEPt so need access on all store | J160: RACPad Support | K160: H0004 - - Active - FSC | N160: PRB0045218 | O160: Incident | P160: Access | Q160: RACPAD access not available
A161: INCTEC1590156 | B161: 3 - Moderate | C161: 46049.802 | D161: 46058.417 | E161: Closed | F161: roopesh pothodi | G161: RACPAD - other | H161: ServiceNow | Access | ServiceNow | I161: ServiceNow when entering the email in racpad does not allow entry, this message appears for new hire colleague EVELYN YAHAIRA ORTIZ ALVAREZ. EMPLOYEE # 100955 #AutoTranslated ServiceNow al ingresar el correo en racpad no permite la entrada aparece este mensaje para compañera nuevo ingreso EVELYN YAHAIRA ORTIZ ALVAREZ . EMPLEADO # 100955 | J161: RACPad Support | K161: 08654 - 5 de Mayo y Reforma - A - M1022 - R0100 - S100 - RACMX | O161: Incident | P161: Access | Q161: RACPAD access not available | R161: DataFix
A162: INCTEC1588228 | B162: 4 - Low | C162: 46044.831 | D162: 46051.875 | E162: Closed | F162: Prasanth K | G162: RACPAD - Store | H162: RACPAD - other | RACPAD Owner Config | | I162: As shown in the attached pic, my access has been removed. Please correct R0999@rentacenter.com Store number: R0999 Coworker name and ID: Jacob Garza | 61635 Issue description: he is not able to access racpad getting error "I'm sorry but you don't have the necessary permission to access this page" Were cache and cookies cleared? Yes Was the computer restarted? Yes Is this happening on one computer or all computers? All Example Computer name: Computer IP: Steps were taken to arrive at the problem: MyApps > Racpad Time of occurrence (Recreate the issue and notate the time if needed): Screenshot required: YES Required Screenshots: 1 ADP Active Status 1 OKTA Applications 1 of the 'Console' tab 2 for the 'Network' tab (1 of 'current' and 1 of 'menu-and-stores') 1 for the RACPAD screen 1 for the SIMS screen (if applicable) | J162: RACPad Support | K162: R0999 - - R0999 - S098 - FRC | M162: CHG0050123 | N162: PRB0045218 | O162: Incident | P162: Access | Q162: RACPAD access not available
A163: INCTEC1587170 | B163: 4 - Low | C163: 46042.549 | D163: 46055.625 | E163: Closed | F163: roopesh pothodi | G163: RACPAD - other | H163: RACPAD - other | RACPAD Owner Config | | I163: New coworker Rebecca Tonkin EID 100848 cannot access RACPad. Seems to not be assigned to a store. • Full name: Rebecca Tonkin • Employee ID: 100848 • Location: 00093 - JAMESTOWN - A - M0417 - R0058 - S08 - RACUSA | J163: RACPad Support | K163: 00093 - JAMESTOWN - A - M0417 - R0058 - S08 - RACUSA | N163: PRB0045218 | O163: Incident | P163: Access | Q163: RACPAD access not available
A164: INCTEC1587888 | B164: 4 - Low | C164: 46044.372 | D164: 46052.417 | E164: Closed | F164: Prasanth K | G164: RACPAD - other | H164: RACPAD - other | RACPAD Owner Config | | I164: new employee cant access racpad ----------------------- Store number: 00408 Coworker name and ID: Danielle Schaab || 100919 Computer name: 00408-4VXQTH3 Issue description: RACPAD login issue Steps taken to arrive at problem: error after login RACPAD | J164: RACPad Support | K164: 00408 - - A - M0202 - R0070 - S08 - RACUSA | N164: PRB0045218 | O164: Incident | P164: Access | Q164: RACPAD access not available
A165: INCTEC1585353 | B165: 3 - Moderate | C165: 46038.368 | D165: 46047.792 | E165: Closed | F165: Pratik Singar | G165: RACPAD - other | H165: RACPAD - other | RACPAD Owner Config | | I165: No access to racpad: User: Rick Pradella EMP ID: 104615 Store: 04488 No Stores search-icon search-icon I'm sorry but you currently don't have the necessary permissions to access this page. Please contact an administrator if you feel this is an error. | J165: RACPad Support | K165: 04488 - HUDSON-FAIRVIEW - A - M0273 - R0002 - S07 - RACUSA | N165: PRB0045218 | O165: Incident | P165: Access | Q165: RACPAD access not available
A166: INCTEC1581179 | B166: 4 - Low | C166: 46028.4 | D166: 46033.25 | E166: Closed | F166: Vandana K | G166: RACPAD - other | H166: RACPAD - other | RACPAD Owner Config | ----------------------------------------------------------- * Not able to access RACPAD | I166: racpad access _---------------------------------------------------------------------------------------------------------- Store number: 00507 Coworker name and ID: Jason Hamm2 || 352261 Computer name: 00507-20SCFD3 Issue description: RACPAD issue from MYAPPS Steps taken to arrive at problem: RACPAD dashboard from my apps . | J166: RACPad Support | K166: 00507 - ROUND ROCK - A - M0066 - R0079 - S07 - RACUSA | N166: PRB0045218 | O166: Incident | P166: Access | Q166: RACPAD access not available
A167: INCTEC1587054 | B167: 4 - Low | C167: 46042.463 | D167: 46047.208 | E167: Closed | F167: Tejas Acharya | G167: RACPAD - Dashboard | H167: RACPAD - RACPAD Access Error | I167: Store number: 03851 Coworker name and ID: Jenitza Luna (100911) Issue description: Coworker is not able to access RACPAD, getting "I'm sorry but you currently don't have the necessary permission to access this page" error. Steps taken to arrive at problem: Time of occurrence (Recreate the issue and notate the time if needed): Screen shot required: YES | J167: RACPad Support | K167: 03851 - NEW BEDFORD-KINGS HWY - A - M0520 - R0002 - S07 - RACUSA | N167: PRB0045218 | O167: Incident | P167: Access | Q167: RACPAD access not available
A168: INCTEC1582936 | B168: 4 - Low | C168: 46032.381 | D168: 46041.417 | E168: Closed | F168: shruthika c | G168: RACPAD - Dashboard | H168: RACPAD - RACPAD Access Issue | I168: Store number: 01234 Coworker name and ID: Gio Rodriguez (339450 Issue description: Coworker has been promoted to Store Manager and in RACPAD he should only have access to Store 01234, but he is able to see multiple store in RACPAD Time of occurrence (Recreate the issue and notate the time if needed): 2026-01-10 10:11:30 Screen shot required: YES | J168: RACPad Support | K168: 01234 - SEBRING - A - M0159 - R0024 - S08 - RACUSA | N168: PRB0045218 | O168: Incident | P168: Access | Q168: RACPAD access not available
A169: INCTEC1584685 | B169: 4 - Low | C169: 46036.671 | D169: 46044.208 | E169: Closed | F169: Tejas Acharya | G169: RACPAD - Dashboard | H169: RACPAD - RACPAD Login Error | I169: Store number: 03043 Coworker name and ID: Arthur Ridge (167505) Issue description: Coworker unable to login into RACPAD – error: "I'm sorry but you currently don't have necessary permission to access this page. Please contact an administrator if you feel this an error" Time of occurrence (Recreate the issue and notate the time if needed): 2026-01-14 16:06:19 Screen shot required: YES | J169: RACPad Support | K169: 03043 - M 61ST STREET - A - M0053 - R0079 - S07 - RACUSA | N169: PRB0045218 | O169: Incident | P169: Access | Q169: RACPAD access not available
A170: INCTEC1588809 | B170: 4 - Low | C170: 46046.376 | D170: 46060.625 | E170: Closed | F170: Prasanth K | G170: RACPAD - Dashboard | H170: RACPAD - RACPAD Login Error | I170: Store number: 03940 Coworker name and ID: Terell Minnifield Issue description: Coworker is not able to login into the RACPAD, getting "I'm sorry but you currently don't have the necessary permission to access this page. Please contact an administrator if you feel this is an error" error. Steps taken to arrive at problem: MyApps -> RACPAD Time of occurrence (Recreate the issue and notate the time if needed): 2026-01-24 10:00:59 Screen shot required: YES | J170: RACPad Support | K170: 03940 - WHITEHALL-S.HAMILTON - A - M0368 - R0061 - S08 - RACUSA | N170: PRB0045218 | O170: Incident | P170: Access | Q170: RACPAD access not available
A171: INCTEC1581721 | B171: 4 - Low | C171: 46029.474 | D171: 46038 | E171: Closed | F171: Vandana K | G171: RACPAD - Store | H171: RACPAD Store - Missing Permissions for Access | I171: Store number: M0480 Coworker name and ID: William Dee || 301258 Issue description: DM is attempting to launch Racpad but is getting error of "you currently do not have the necessary permissions to access this page" Were cache and cookies cleared? yes Was the computer restarted? yes Is this happening on one computer or all computers? all Steps were taken to arrive at the problem: 1. Login to Myapps 2. Launch Racpad 3. Error appears Time of occurrence (Recreate the issue and notate the time if needed): 01/07/2026 | J171: RACPad Support | K171: M0480 - N/A - M0480 - R0007 - S08 - RTO | N171: PRB0045218 | O171: Incident | P171: Access | Q171: RACPAD access not available
A172: INCTEC1585642 | B172: 4 - Low | C172: 46038.665 | D172: 46045.375 | E172: Closed | F172: Abhishek TV | G172: RAC External Website | H172: Racpad - Unable to access | I172: Issue with RAC External Website New hire id number 100823 doesn't have access to rac pad ------------------------------- Store number: 04030 Coworker name and ID: Matthias Cardoza Issue description: Unable to access Racpad application Were cache and cookies cleared? Was the computer restarted? Yes Is this happening on one computer or all computers? All computers Example Computer name: Computer IP: Steps were taken to arrive at the problem: Time of occurrence (Recreate the issue and notate the time if needed): Screenshot required: YES | J172: RACPad Support | K172: 04030 - ELKO - A - M0408 - R0040 - S07 - RACUSA | N172: PRB0045218 | O172: Incident | P172: Access | Q172: RACPAD access not available
A173: INCTEC1588831 | B173: 4 - Low | C173: 46046.419 | D173: 46054.333 | E173: Closed | F173: Sushmitha Sannidhi | G173: RACPAD - Dashboard | H173: Racpad - unable to access | I173: Store number: 02288 Coworker name and ID: Gerardo Rodriguez Issue description: Unable to access Racpad Steps taken to arrive at problem: Time of occurrence (Recreate the issue and notate the time if needed): Screen shot required: YES | J173: RACPad Support | K173: 02288 - SAN ANTONIO - 1828 WW WHITE - A - M0062 - R0079 - S07 - RACUSA | N173: PRB0045218 | O173: Incident | P173: Access | Q173: RACPAD access not available
A174: INCTEC1590253 | B174: 4 - Low | C174: 46050.345 | D174: 46054.375 | E174: Closed | F174: Abhishek TV | G174: RACPAD - Dashboard | H174: Racpad - Unable to access | I174: Store number: 02516 Coworker name and ID: Jorge Arroyo Marzan Issue description: Unable to access Racpad getting permission error Steps taken to arrive at problem: Time of occurrence (Recreate the issue and notate the time if needed): Screen shot required: YES | J174: RACPad Support | K174: 02516 - DORCHESTER-COLUMBIA RD - A - M0028 - R0002 - S07 - RACUSA | N174: PRB0045218 | O174: Incident | P174: Access | Q174: RACPAD access not available
... A220: INCTEC1587032 | B220: 4 - Low | C220: 46042.448 | D220: 46047.375 | E220: Closed | F220: Abhishek TV | G220: RACPAD - Store | H220: RACPAD login issue | I220: Unable to access the RACPAD getting error " Please Contact an your administration if you feel this is an error " Employee name- Michael Gundersen Employee id - 100915 Store- 100915 | J220: RACPad Support | K220: 03505 - NOBLESVILLE-CLOVER RD. - A - M0114 - R0019 - S08 - RACUSA | N220: PRB0045218 | O220: Incident | P220: Access | Q220: RACPAD access not available
A221: INCTEC1581388 | B221: 4 - Low | C221: 46028.622 | D221: 46037.458 | E221: Closed | F221: ankita singh | G221: DUO Authentication | H221: DUO codes not working | I221: DM EID: 301258 CW EID: 234965 CW Phone # on DUO: 786 859 3295 Issue: >DUO codes not working for DM William Dee and SM Julia Herndon >DM William Dee is not able to access racpad, getting invalid credentials >Willliam added that racpad is not recognizing his credentials and that's why Duo codes are not going though >Checked DM has racpad application assigned on Entra, attached snip | J221: RACPad Support | K221: 01804 - SALISBURY-INNES - A - M0480 - R0007 - S08 - RACUSA | O221: Incident | P221: Access | Q221: Duo Code
A222: INCTEC1589353 | B222: 4 - Low | C222: 46048.42 | D222: 46053.417 | E222: Closed | F222: Abhishek TV | G222: RACPAD - Dashboard | H222: Racpad permiss | I222: Store number: 01601 Coworker name and ID: Zachary Linn Issue description: New Hire unable to access Racpad getting permission error Were cache and cookies cleared? Yes Was the computer restarted? Is this happening on one computer or all computers? Example Computer name: Computer IP: Steps were taken to arrive at the problem: Time of occurrence (Recreate the issue and notate the time if needed): Screenshot required: YES | J222: RACPad Support | K222: 01601 - CUMBERLAND-QUEEN CITY DR - A - M0288 - R0058 - S08 - RACUSA | N222: PRB0045218 | O222: Incident | P222: Access | Q222: RACPAD access not available
A223: INCTEC1581668 | B223: 4 - Low | C223: 46029.422 | D223: 46034.375 | E223: Closed | F223: racha sahithya | G223: RACPAD - Store | H223: Racpad Permission | I223: Employee Name Gage Pobanz EID 361314 Store 04232 Reported Issue : - Unable to access Racpad Error Please contact an administrator Shanphot attached for ref.. | J223: RACPad Support | K223: 04232 - BOURBONNAIS-KENNEDY DR - A - M0509 - R0019 - S08 - RACUSA | N223: PRB0045218 | O223: Incident | P223: Access | Q223: RACPAD access not available
A224: INCTEC1585219 | B224: 4 - Low | C224: 46037.826 | D224: 46043.708 | E224: Closed | F224: Sushmitha Sannidhi | G224: RACPAD - Dashboard | H224: Racpad permission error | I224: Store number: 02322 Coworker name and ID: Raad Tawil Issue description: RACPAD error "I'm sorry but you don't have the necessary permission to access this page" Were cache and cookies cleared? Yes Was the computer restarted? Yes Is this happening on one computer or all computers? Example Computer name: Computer IP: Steps were taken to arrive at the problem: Time of occurrence (Recreate the issue and notate the time if needed): Screenshot required: YES | J224: RACPad Support | K224: 02322 - CHESTER - A - M0350 - R0058 - S08 - RACUSA | N224: PRB0045218 | O224: Incident | P224: Access | Q224: RACPAD access not available
A225: INCTEC1581186 | B225: 4 - Low | C225: 46028.406 | D225: 46034.458 | E225: Closed | F225: Tejas Acharya | G225: RACPAD - Store | H225: Racpad permission issue | I225: Does not have access to Racpad store User : Ronald Baker EID : 364257 Store : 00140 | J225: RACPad Support | K225: 00140 - - A - M0084 - R0008 - S07 - RACUSA | N225: PRB0045218 | O225: Incident | P225: Access | Q225: RACPAD access not available
A226: INCTEC1586441 | B226: 4 - Low | C226: 46041.397 | D226: 46047.208 | E226: Closed | F226: Tejas Acharya | G226: RACPAD - other | H226: RACPAD store issue . | I226: The user has recently been promoted to Store Manager and needs access to the new store (00338) in RACPAD. However, she is still seeing the old store (00334) in the system Employee name- Zack Lynn Employee id - 155247 Store- 00334 | J226: RACPad Support | K226: 00334 - COLUMBIA - A - M0214 - R0080 - S08 - RACUSA | N226: PRB0045218 | O226: Incident | P226: Access | Q226: RACPAD access not available
A227: INCTEC1588374 | B227: 4 - Low | C227: 46045.394 | D227: 46053.417 | E227: Closed | F227: Abhishek TV | G227: Microsoft Office 365 | H227: RACPAD Store - Missing Permissions for Access | I227: Store number: 01183 Coworker name and ID: Yacel GonzalezZaldivar and 100173 Customer name and number : n/a Agreement #: n/a Issue description: user is not able to access Racpad Were cache and cookies cleared? yes Was the computer restarted? yes Is this happening on one computer or all computers? all computer Example Computer name: 01183-1K8CMB3 Computer IP: n/a Steps were taken to arrive at the problem: logged in Myapps and after clicking on Racpad getting an error Time of occurrence (Recreate the issue and notate the time if needed): Screenshot required: YES Required Screenshots: 1 ADP Active Status 1 OKTA Applications 1 of the 'Console' tab 2 for the 'Network' tab (1 of 'current' and 1 of 'menu-and-stores') 1 for the RACPAD screen 1 for the SIMS screen (if applicable) | J227: RACPad Support | K227: 01183 - HIALEAH-EAST - A - M0158 - R0024 - S08 - RACUSA | N227: PRB0045218 | O227: Incident | P227: Access | Q227: RACPAD access not available
A228: INCTEC1581302 | B228: 4 - Low | C228: 46028.503 | D228: 46037.167 | E228: Closed | F228: Pratik Singar | G228: RACPAD - Store | H228: Racpad store access | I228: Cannot get the Racpad access in the store Employee : Jose Sepulveda EID : 124229 Store : 01840 / 03159 / 01844 | J228: RACPad Support | K228: M0014 - N/A - M0014 - R0065 - S08 - RTO | N228: PRB0045218 | O228: Incident | P228: Access | Q228: RACPAD access not available
A229: INCTEC1580837 | B229: 4 - Low | C229: 46027.603 | D229: 46033.208 | E229: Closed | F229: shruthika c | G229: RACPAD - Store | H229: RacPad Store Access Issue | I229: Name : Jeanette Pando2 Store ID : 02035 Emp ID : 332748 Callback : (405) 354-7444 Ref Ticket # : RITM0135277 User told that she is not able to access racpad for the new store | J229: RACPad Support | K229: 02035 - PENN - A - M0542 - R0080 - S08 - RACUSA | N229: PRB0045218 | O229: Incident | P229: Access | Q229: RACPAD access not available
A230: INCTEC1588524 | B230: 4 - Low | C230: 46045.553 | D230: 46053.417 | E230: Closed | F230: Abhishek TV | G230: RACPAD - Store | H230: Racpad store access | I230: Afternoon, I have an Alexander Taye Employee ID 362691 at Ren t-A- Center store 02017. He is in Workday, but has not access to functions in RACPAD, and cannot type up sales or doing any features in store. Since he is in their Workday can we get him set up in the Racpad system. Thank You Guy Mathieson Dm0096 330-697-4028 | J230: RACPad Support | K230: M0096 - N/A - M0096 - R0061 - S08 - RTO | N230: PRB0045218 | O230: Incident | P230: Access | Q230: RACPAD access not available
A231: INCTEC1583527 | B231: 4 - Low | C231: 46034.431 | D231: 46036.117 | E231: Closed | F231: Prasanth K | G231: RACPAD - Store | H231: Racpad Store Permission | I231: Employee name Kristiana Brant EID 211080 STore 02068 As user is been transfer from Store 02345 to Store 02068 But user dont have access in racpad for Store 02068 | J231: RACPad Support | K231: 02068 - JOHNSTOWN-TOWN CENTRE - A - M0288 - R0058 - S08 - RACUSA | N231: PRB0045218 | O231: Incident | P231: Access | Q231: RACPAD access not available
A232: INCTEC1582817 | B232: 4 - Low | C232: 46031.752 | D232: 46039.75 | E232: Closed | F232: Abhishek TV | G232: RACPAD - Dashboard | H232: RACPAD-DASHBOARD | I232: Store number: 04254 Coworker name and ID: Austin Myrick || 342519 Computer name: 04254-C08BV93 Issue description: Wrong store access in RACPAD. Steps taken to arrive at problem: RACPAD ||DASHBOARD | J232: RACPad Support | K232: 04254 - FT SCOTT-NATIONAL - A - M0222 - R0080 - S08 - RACUSA | N232: PRB0045218 | O232: Incident | P232: Access | Q232: RACPAD access not available
A233: INCTEC1586951 | B233: 4 - Low | C233: 46042.397 | D233: 46047.208 | E233: Closed | F233: Tejas Acharya | G233: RACPAD - Dashboard | H233: RACPAD-Login | I233: Store number: 00830 Coworker name and ID: Wilbert Brown || 368233 Computer name: 00830 -7WJQZB3 Issue description: Issue to access RACPAD Steps taken to arrive at problem: RACPAD Login issue | J233: RACPad Support | K233: 00830 - N CHARLESTON-RIVERS - A - M0001 - R0007 - S08 - RACUSA | N233: PRB0045218 | O233: Incident | P233: Access | Q233: RACPAD access not available
... A236: INCTEC1585469 | B236: 4 - Low | C236: 46038.48 | D236: 46046.208 | E236: Closed | F236: Tejas Acharya | G236: RACPAD - other | H236: remove employee | I236: remove employee >Miguel Benacazar, Karen Colleman have the access to the store 00207 and are assigned to different location on workday Employee : Wilfri AlvarezToribio Store : 00207 Description : Employee not working in the store and having access to racpad on store 00207 : Miguel Benacazar, Karen Colleman and need to remove the racpad access fro the store 00207 | J236: RACPad Support | K236: 00207 - - A - M0155 - R0024 - S08 - RACUSA | N236: PRB0045218 | O236: Incident | P236: Access | Q236: RACPAD access not available
A237: INCTEC1584170 | B237: 4 - Low | C237: 46035.554 | D237: 46041.417 | E237: Closed | F237: shruthika c | G237: RACPAD - Customer | H237: Racpad access | I237: RAC PAD, DE SU APOYO CON LA TRABAJADORA JUANA AGUILAR ALDANA 100484 YA QUE NO LE DEJA INGRESAR AL SISTEMA DE RACPAD LE ARROJA UN ERROR "NO TIENE LOS PERMISOS NECESARIOS" | J237: RACPad Support | K237: H0003 - - Active - FSC | O237: Incident | P237: Access | Q237: RACPAD access not available
A238: INCTEC1589445 | B238: 4 - Low | C238: 46048.499 | D238: 46064.488 | E238: Resolved | F238: Jitheesha Thankachan | G238: RACPAD - Cash Management | H238: Request to Activate CSM Ticketing in RACPad | I238: i @RACPad Support team , and @Briana Coffman, Kindly assist with activating the CSM ticketing in RACPad for the Agents and TL listed below: Agents: gazie.joe@rentacenter.com - 359562 Honey.Gonzales@rentacenter.com - 364861 Please mirror access to Audie.Nano@rentacenter.com — RACID: 355777 | J238: RACPad Support | K238: H0003 - - Active - FSC | O238: Incident | P238: Access | Q238: RACPAD access not available
A239: INCTEC1590133 | B239: 4 - Low | C239: 46049.718 | D239: 46055.208 | E239: Closed | F239: Vandana K | G239: RACPAD Access | H239: SIMS Temporary Store Location Access Request | I239: Request to temporarily have access to a store other than the coworker's home store. Name of the Benefiting Coworker: Drew Priest Benefiting Coworker's Employee ID: 89169 Benefiting Coworker's Home Store: M0234 Store to which Benefiting Coworker requests access: M0233 When should the temporary access begin?: 01/27/2026 When should the temporary access end? Remember, it cannot exceed seven (7) days: 02/07/2026 Where can the benefiting coworker be reached for login verification? 316-880-2148 Store location or contact phone: Who Requested the Access?: [Regional Director] If the person on the phone was not the DM/RD, did you three-way-call the DM or RD for verbal authorization?: [Yes] If the DM or RD did not answer your three-way-call, did you send a verification e-mail?: [Yes]/[No] (include copy of sent verification e-mail in the ticket's Work Notes and escalate) | J239: RACPad Support | K239: R0040 - N/A - R0040 - S07 - RTO | N239: PRB0045218 | O239: Request | P239: Access | Q239: RACPAD access not available
A240: INCTEC1589499 | B240: 4 - Low | C240: 46048.549 | D240: 46062.292 | E240: Closed | F240: Lalit RameshTurkar | G240: RACPAD - other | H240: Thomas Freeman new hire does not have access to RACPAD | I240: Thomas Freeman new hire does not have access to RACPAD Store number: 00440 Coworker name and ID: Thomas Freeman | 100782@rentacenter.com Issue description: Unable to access the racpad getting error "I'm sorry but you don't have the necessary permission to access this page" Were cache and cookies cleared? Yes Was the computer restarted? Yes Is this happening on one computer or all computers? All computers Example Computer name: 00440-8DPSVD3 Computer IP: 10.101.183.55 Steps were taken to arrive at the problem: Time of occurrence (Recreate the issue and notate the time if needed): Screenshot required: YES Required Screenshots: 1 ADP Active Status 1 OKTA Applications 1 of the 'Console' tab 2 for the 'Network' tab (1 of 'current' and 1 of 'menu-and-stores') 1 for the RACPAD screen 1 for the SIMS screen (if applicable) | J240: RACPad Support | K240: 00440 - OXFORD - A - M0046 - R0008 - S07 - RACUSA | N240: PRB0045218 | O240: Incident | P240: Access | Q240: RACPAD access not available
A241: INCTEC1589853 | B241: 4 - Low | C241: 46049.395 | D241: 46054.417 | E241: Closed | F241: Abhishek TV | G241: RACPAD - Store | H241: Unable to access RACPAD | I241: Employee name: Phillip Gayles EMPID: 100381 Store: 02909 Call back number: (601) 469-7990 issue: Unable to access RACPAD Detailed issue: >Received call from CW stated Unable to access RACPAD. >CW said that she getting an error while trying to access RACPAD. Troubleshooting steps: >Connected through remote. >Verified the same issue from user end. >Tried browser optimization and different browser. >However CW getting the same error (SNIP attached) >Informed CW that will escalate the ticket to the concern Team to check further. | J241: RACPad Support | K241: 02909 - FOREST-HIGHWAY 95 - A - M0084 - R0008 - S07 - RACUSA | N241: PRB0045218 | O241: Incident | P241: Access | Q241: RACPAD access not available
...

Sheet Inc Summary
A3: Row Labels | B3: Count of Number
A4: BigPanda | B4: 1439
A5: (blank) | B5: 1439
A6: Payment | B6: 305
A7: Access | B7: 253
A8: Inventory | B8: 236
A9: Customer | B9: 223
A10: Agreement | B10: 152
A11: Store | B11: 91
A12: Account Management | B12: 54
A13: Report | B13: 45
A14: Admin | B14: 31
A15: other | B15: 11
... A21: Grand Total | B21: 2873

Sheet Issue wise details
A1: Module | B1: Type Of Issue | D1: Type Of Issue | E1: No of Occurences | F1: Issue Description | G1: Time to close the tickets | H1: One time/Recurring | I1: Automation/Shift Left | J1: Problem associated? | K1: Problem ticket | L1: Remarks
A2: Agreement | B2: Unable to void agreement | D2: RACPAD Access not available | E2: =COUNTIF(B:B,D2) -> 316 | F2: Spike due to workday migration | H2: One time | I2: Problem Management | J2: Yes | K2: PRB0045218
A3: Access | B3: RACPAD Access not available | D3: PO removal | E3: =COUNTIF(B:B,D3) -> 102 | F3: Request for removal of Manual PO | H3: Recurring | I3: Shift left(Approval) | J3: Yes | K3: PRB0045846 | L3: Form has to be created to eliminate the manual effort to reduce time collecting details from Store and ticket should be directly routed to RACPAD DS team to do data fix.
A4: Access | B4: RACPAD Access not available | D4: AutoPay | E4: =COUNTIF(B:B,D4) -> 62 | F4: Issue due to change in customer phone number or customer might have un-enrolled | G4: 5 hours | H4: Recurring | I4: Partially associated with PRB | J4: Yes
A5: Access | B5: RACPAD Access not available | D5: Customer order missing | E5: =COUNTIF(B:B,D5) -> 40 | F5: This was due to a request to disable customer order for a franchise-CHG0050479 | H5: One time | J5: No
A6: Agreement | B6: Missing Customer agreements which was transfered from previous store | D6: Payment done but not reflecting in RACPAD | E6: =COUNTIF(B:B,D6) -> 39 | F6: Amount got deducted from customer account but not showing in RACPAD | G6: 4 hours | H6: Recurring | I6: Automation/chat bot | J6: No
A7: Inventory | B7: Inventory mismatch between RMS and RACPAD | D7: Report issue | E7: =COUNTIF(B:B,D7) -> 35 | F7: Report related discrepencies | H7: Recurring | J7: Yes
A8: Report | B8: Report issue | D8: Void the agreement and change the inventory status to idle | E8: =COUNTIF(B:B,D8) -> 29 | F8: Void the agreement and update the inventory status to Rent-ready | H8: Recurring | I8: Problem Management | J8: Yes | K8: PRB0045970
A9: Payment | B9: Short Payment | D9: Missing Promo code | E9: =COUNTIF(B:B,D9) -> 28 | F9: Promo codes were not appearing | H9: One time | J9: No
A10: Payment | B10: Pay Date not reflecting | D10: Payment reversal | E10: =COUNTIF(B:B,D10) -> 24 | F10: Request to reverse the payment | H10: Recurring | I10: Problem Management | J10: Yes | K10: PRB0044395
A11: Payment | B11: Reverse the retention | D11: Incorrect processing fee | E11: =COUNTIF(B:B,D11) -> 23 | F11: Caused due to a config change which was then reverted back | H11: One time | J11: No
A12: Inventory | B12: PO removal | D12: Salesperson dropdown issue | E12: =COUNTIF(B:B,D12) -> 22 | F12: The salesperson dropdown list either shows terminated employees or wont have current CW's | H12: One time | I12: Problem Management | J12: Yes | K12: PRB0045968
A13: Inventory | B13: PO removal | D13: Unable to create an Agreement | E13: =COUNTIF(B:B,D13) -> 21 | F13: CW unable to create an agreement | H13: One time | J13: No
A14: Inventory | B14: PO removal | D14: PIN reset | E14: =COUNTIF(B:B,D14) -> 21 | F14: CW asking to reset the PIN | G14: 30 mins | H14: Recurring | I14: Automation | J14: No
A15: Payment | B15: Customer paid but still appearing in past due list | D15: Change the Inventory status | E15: =COUNTIF(B:B,D15) -> 19 | F15: Request to change the inventory status | H15: Recurring | I15: Problem Management | J15: Yes | K15: PRB0045883
A16: Inventory | B16: PO removal | D16: Failed to perform Record check request | E16: =COUNTIF(B:B,D16) -> 15 | F16: Unable to perform Customer record check | H16: One time | J16: No
A17: Inventory | B17: PO removal | D17: Unable to fetch the data | E17: =COUNTIF(B:B,D17) -> 15 | F17: Drop downs not loading in Account management | H17: One time | J17: Yes
A18: Customer | B18: Sales lead issue | D18: Customer needs to be refunded | E18: =COUNTIF(B:B,D18) -> 15 | F18: Refund related issues | H18: Recurring | J18: Yes
A19: Customer | B19: Sales lead issue | D19: CW missing in Sales goal | E19: =COUNTIF(B:B,D19) -> 13 | F19: Missing CW names in sales goal section | H19: Recurring | J19: No
A20: Inventory | B20: PO removal | D20: Inventory status change | E20: =COUNTIF(B:B,D20) -> 13 | F20: Request to change the inventory status | H20: Recurring | I20: Problem Management | J20: Yes | K20: PRB0045196
A21: Customer | B21: Customer level issue. Unable to add furniture | D21: Unable to confirm delivery | E21: =COUNTIF(B:B,D21) -> 12 | F21: CW unable to confirm delivery. Most of the times this will be due to missing customer phone number | H21: Recurring | I21: training issue | J21: No | L21: Making Primary Phone number field mandatory for Old customers
A22: Payment | B22: Unable to refund Web deposit | D22: Need to remove LDW | E22: =COUNTIF(B:B,D22) -> 12 | F22: Remove LDW | H22: Recurring | I22: Problem Management | J22: Yes | K22: PRB0045449
A23: Payment | B23: Unable to refund Web deposit | D23: Unable to receive Purchase order, please try again later | E23: =COUNTIF(B:B,D23) -> 10 | F23: When store tried to receive PO, they get the error "Unable to receive Po, please try again later" | H23: Recurring | J23: No | L23: Price republish
A24: Inventory | B24: PO removal | D24: Switch out issue | E24: =COUNTIF(B:B,D24) -> 10 | F24: Agreement switch-out completed, but inventory remains in "Pending Switch Out" status. | H24: Recurring | I24: Problem Management | J24: Yes | K24: PRB0045906
A25: Inventory | B25: PO removal | D25: Missing Store for CW | E25: =COUNTIF(B:B,D25) -> 9 | F25: CW missing access to transferred store( Will be having access of previous store) | G25: 5 hours | H25: Recurring | I25: Automation
A26: Report | B26: Issue with Manager route | D26: Drop reconciliation issue | E26: =COUNTIF(B:B,D26) -> 8 | F26: Issue while performing drop reconciliation | H26: Recurring | J26: No
A27: Inventory | B27: PO removal | D27: Unable to take payment. Asking to confirm delivery | E27: =COUNTIF(B:B,D27) -> 8 | F27: Issue while taking payment | H27: Recurring | J27: No
A28: Inventory | B28: PO removal | D28: Payment reversal request | E28: =COUNTIF(B:B,D28) -> 8 | F28: Payment reversal request | H28: Recurring | J28: Yes | K28: PRB0044395
A29: Report | B29: Issue with Manager route | D29: Customer level change request | E29: =COUNTIF(B:B,D29) -> 7 | F29: Request to change the level of the customer | H29: Recurring | I29: training issue | J29: No | L29: Form has to be created to eliminate the manual effort to reduce time collecting details from Store and ticket should be directly routed to Operations team for address these requests.
A30: Customer | B30: Unable to save customer details | D30: Welcome Video | E30: =COUNTIF(B:B,D30) -> 7 | F30: Caused due to a deployment | H30: One time | J30: No
A31: Inventory | B31: PO removal | D31: Wrong SAC | E31: =COUNTIF(B:B,D31) -> 7 | F31: Issue with SAC amount/date | H31: Recurring | J31: No
A32: Customer | B32: Unable to save customer details | D32: Promo code issue | E32: =COUNTIF(B:B,D32) -> 7 | F32: Issue with Promo code | H32: One time | J32: No
A33: Customer | B33: Approval level not appearing | D33: Intellicheck issue | E33: =COUNTIF(B:B,D33) -> 6
A34: Payment | B34: AutoPay | D34: Unable to return the agreement | E34: =COUNTIF(B:B,D34) -> 6
A35: Inventory | B35: PO removal | D35: Adjust the SAC amount | E35: =COUNTIF(B:B,D35) -> 6
A36: Inventory | B36: PO removal | D36: Unable to refund Web deposit | E36: =COUNTIF(B:B,D36) -> 5
A37: Payment | B37: AutoPay | D37: Customer level enquiry | E37: =COUNTIF(B:B,D37) -> 5
A38: Inventory | B38: PO removal | D38: Duplicate ticket | E38: =COUNTIF(B:B,D38) -> 5
A39: Inventory | B39: PO removal | D39: Customer charged twice | E39: =COUNTIF(B:B,D39) -> 5
A40: Inventory | B40: PO removal | D40: Item delivered but still showing as Pending | E40: =COUNTIF(B:B,D40) -> 5
A41: Payment | B41: AutoPay | D41: NSF query | E41: =COUNTIF(B:B,D41) -> 5
A42: Payment | B42: AutoPay | D42: Unable to void agreement | E42: =COUNTIF(B:B,D42) -> 4
A43: Inventory | B43: PO removal | D43: Incorrect retention calculation | E43: =COUNTIF(B:B,D43) -> 4
A44: Customer | B44: Incorrect processing fee | D44: Unable to perform Customer Record check | E44: =COUNTIF(B:B,D44) -> 4
... A86: Inventory | B86: PO removal | D86: Remove the clearance flag from items | E86: =COUNTIF(B:B,D86) -> 2
A87: Inventory | B87: PO removal | D87: FT CAP Configuration | E87: =COUNTIF(B:B,D87) -> 2 | F87: Enable/Diable the FT cap | G87: 8 hours | H87: Once in a month | I87: Automation
A88: Customer | B88: Intellicheck issue | D88: 2 way text | E88: =COUNTIF(B:B,D88) -> 2
A89: Payment | B89: Montly rent has increased | D89: Delivery confirmed but items not removed from inventory | E89: =COUNTIF(B:B,D89) -> 2
A90: Access | B90: RACPAD Access not available | D90: Module Access | E90: =COUNTIF(B:B,D90) -> 2
A91: Access | B91: RACPAD Access not available | D91: Past due list not appearing | E91: =COUNTIF(B:B,D91) -> 2
A92: Payment | B92: Payment reversal | D92: text message missing | E92: =COUNTIF(B:B,D92) -> 2
A93: Account Management | B93: Customer wrongly showing in past due list | D93: Unable to finalize the audit | E93: =COUNTIF(B:B,D93) -> 2
A94: Account Management | B94: Commitment Issue | D94: Unable to save customer address | E94: =COUNTIF(B:B,D94) -> 2
A95: Access | B95: RACPAD Access not available | D95: DE declined | E95: =COUNTIF(B:B,D95) -> 2
A96: Customer | B96: Verification link missing | D96: Unable to save card | E96: =COUNTIF(B:B,D96) -> 2
A97: Payment | B97: Payment reversal | D97: Deactivate the club | E97: =COUNTIF(B:B,D97) -> 2
A98: Payment | B98: Payment reversal | D98: Price change request for inventory | E98: =COUNTIF(B:B,D98) -> 2
A99: Customer | B99: Unable to add user as a co-customer | D99: Unable to do non-inventory sales | E99: =COUNTIF(B:B,D99) -> 2
... A106: Payment | B106: Payment reversal | D106: Radius search | E106: =COUNTIF(B:B,D106) -> 2
A107: BigPanda | D107: Remove item from service | E107: =COUNTIF(B:B,D107) -> 2
A108: Store | B108: RACPAD access not available | D108: page not loading | E108: =COUNTIF(B:B,D108) -> 2
A109: BigPanda | D109: Receiving texts meant for other customers | E109: =COUNTIF(B:B,D109) -> 2
A110: BigPanda | D110: EPO button is greyed out | E110: =COUNTIF(B:B,D110) -> 2
A111: Customer | B111: Issue with referral code | D111: Charge off | E111: =COUNTIF(B:B,D111) -> 2
A112: BigPanda | D112: Customer never received merchandise | E112: =COUNTIF(B:B,D112) -> 2
A113: Agreement | B113: Unable to close agreement | D113: Promo code validation | E113: =COUNTIF(B:B,D113) -> 2
A114: BigPanda | D114: Payment query | E114: =COUNTIF(B:B,D114) -> 2
A115: BigPanda | D115: Accept Payment button greyed out | E115: =COUNTIF(B:B,D115) -> 2
A116: Payment | B116: AutoPay | D116: Missing Customer agreements which was transfered from previous store | E116: =COUNTIF(B:B,D116) -> 1
A117: BigPanda | D117: Inventory mismatch between RMS and RACPAD | E117: =COUNTIF(B:B,D117) -> 1
A118: BigPanda | D118: Short Payment | E118: =COUNTIF(B:B,D118) -> 1
A119: BigPanda | D119: Pay Date not reflecting | E119: =COUNTIF(B:B,D119) -> 1
A120: BigPanda | D120: Reverse the retention | E120: =COUNTIF(B:B,D120) -> 1
A121: BigPanda | D121: Customer paid but still appearing in past due list | E121: =COUNTIF(B:B,D121) -> 1
A122: Payment | B122: Short issue | D122: Customer level issue. Unable to add furniture | E122: =COUNTIF(B:B,D122) -> 1
A123: BigPanda | D123: Approval level not appearing | E123: =COUNTIF(B:B,D123) -> 1
A124: BigPanda | D124: Can text customers from other location | E124: =COUNTIF(B:B,D124) -> 1
A125: Payment | B125: Payment done but not reflecting in RACPAD | D125: Tempororily out of stock | E125: =COUNTIF(B:B,D125) -> 1
A126: Payment | B126: Unable to pay off | D126: Customer not happy with product and wants refund | E126: =COUNTIF(B:B,D126) -> 1
A127: BigPanda | D127: Unable to reverse agreement | E127: =COUNTIF(B:B,D127) -> 1
A128: BigPanda | D128: Customer name missing in text messages | E128: =COUNTIF(B:B,D128) -> 1
A129: BigPanda | D129: Customer is receiving text from another store | E129: =COUNTIF(B:B,D129) -> 1
A130: Customer | B130: Verification link not working | D130: Montly rent has increased | E130: =COUNTIF(B:B,D130) -> 1
A131: BigPanda | D131: Customer wrongly showing in past due list | E131: =COUNTIF(B:B,D131) -> 1
A132: BigPanda | D132: Verification link missing | E132: =COUNTIF(B:B,D132) -> 1
A133: Inventory | B133: Reverse the PO | D133: Unable to add user as a co-customer | E133: =COUNTIF(B:B,D133) -> 1
A134: BigPanda | D134: Issue while creating a promo code | E134: =COUNTIF(B:B,D134) -> 1
A135: BigPanda | D135: Issue with referral code | E135: =COUNTIF(B:B,D135) -> 1
A136: BigPanda | D136: Short issue | E136: =COUNTIF(B:B,D136) -> 1
A137: BigPanda | D137: Reverse the PO | E137: =COUNTIF(B:B,D137) -> 1
A138: BigPanda | D138: Customer receving msg to call store location | E138: =COUNTIF(B:B,D138) -> 1
A139: BigPanda | D139: Query on PO reference number | E139: =COUNTIF(B:B,D139) -> 1
A140: BigPanda | D140: Drop issue | E140: =COUNTIF(B:B,D140) -> 1
A141: BigPanda | D141: Promo code changing the SAC value | E141: =COUNTIF(B:B,D141) -> 1
A142: BigPanda | D142: Unable to open verification link | E142: =COUNTIF(B:B,D142) -> 1
A143: BigPanda | D143: Unavble to put items back in inventory | E143: =COUNTIF(B:B,D143) -> 1
A144: BigPanda | D144: Items not appearing | E144: =COUNTIF(B:B,D144) -> 1
A145: BigPanda | D145: Unable to switch cards | E145: =COUNTIF(B:B,D145) -> 1
... A149: BigPanda | D149: CSM | E149: =COUNTIF(B:B,D149) -> 1
A150: Payment | B150: Payment done but not reflecting in RACPAD | D150: Received wrong item under PO | E150: =COUNTIF(B:B,D150) -> 1
...

Sheet Sheet7
A1: Problem id
A2: PRB0045218
A3: PRB0045846
A4: PRB0044727
A5: PRB0045970
A6: PRB0044829
A7: PRB0044395
A8: PRB0045455
A9: PRB0045968
A10: PRB0045883
A11: PRB0045473
A12: PRB0044947
... A81: PRB0045723

Sheet Sheet8
A1: Problem
A2: PRB0045805 | B2: =VLOOKUP(A2,Sheet7!A:A,1,FALSE) -> #N/A
A3: PRB0046021 | B3: =VLOOKUP(A3,Sheet7!A:A,1,FALSE) -> #N/A
A4: PRB0046044 | B4: =VLOOKUP(A4,Sheet7!A:A,1,FALSE) -> #N/A
A5: PRB0046050 | B5: =VLOOKUP(A5,Sheet7!A:A,1,FALSE) -> #N/A
A6: PRB0046041 | B6: =VLOOKUP(A6,Sheet7!A:A,1,FALSE) -> #N/A
A7: PRB0044564 | B7: =VLOOKUP(A7,Sheet7!A:A,1,FALSE) -> PRB0044564
A8: PRB0045499 | B8: =VLOOKUP(A8,Sheet7!A:A,1,FALSE) -> #N/A
A9: PRB0045695 | B9: =VLOOKUP(A9,Sheet7!A:A,1,FALSE) -> PRB0045695
A10: PRB0045802 | B10: =VLOOKUP(A10,Sheet7!A:A,1,FALSE) -> #N/A
A11: PRB0045373 | B11: =VLOOKUP(A11,Sheet7!A:A,1,FALSE) -> #N/A
A12: PRB0045824 | B12: =VLOOKUP(A12,Sheet7!A:A,1,FALSE) -> #N/A
A13: PRB0045280 | B13: =VLOOKUP(A13,Sheet7!A:A,1,FALSE) -> PRB0045280
... A16: PRB0045565 | B16: =VLOOKUP(A16,Sheet7!A:A,1,FALSE) -> PRB0045565
